Workbook

Sheet Working Data
B3: Project ID | C3: Drive Time | D3: Tilt | E3: Azimuth | F3: Panel QTY | G3: System Rating (kW DC) | H3: Inverter Manufacturer | I3: Array Type | J3: Squirrel Screen | K3: Consumption Monitoring | L3: Truss / Rafter | M3: Reinforce- ments | N3: Rough Electrical Inspection | O3: Interconnection Type | P3: Module Length | Q3: Module Width | R3: Module Weight | S3: # of Arrays | T3: # of reinforcement | U3: Roof Type | V3: Attachment Type | W3: Portrait / Landscape | X3: # of Stories | Y3: Install Season | Z3: Total Direct Time for Project for Hourly Employees (Including Drive Time) | AA3: Total # of Days on Site | AB3: Total # Hourly Empoyees on Site | AC3: Estimated # of Salaried Employees on Site | AD3: Estimated Salary Hours | AE3: Estimated Total Direct Time | AG3: Estimated Total # of People on Site | AH3: Notes
B4: 001 | C4: 21 mins | D4: 33° | E4: 180° | F4: 19 | G4: 6.84 | H4: SolarEdge | I4: Roof Mount | J4: Yes | L4: Truss | M4: No | N4: No | O4: A1 | P4: 67.8 | Q4: 40 | R4: 43 | S4: 1 | T4: 0 | U4: Asphalt Shingles | V4: Flashfoot 2 | W4: Portrait | X4: 2 | Y4: Spring | Z4: 0.79166667 | AA4: 1 | AB4: 2 | AC4: 2 | AD4: =IFERROR(Z4/(AA4*AB4)*AC4*AA4,"") -> 0.79166667 | AE4: =Z4+AD4 -> 1.5833333 | AG4: =AB4+AC4 -> 4
B5: 002 | C5: 23 mins | D5: 45° | E5: 139° | F5: 18 | G5: 6.57 | H5: SolarEdge | I5: Roof Mount | J5: Yes | L5: Rafter | M5: Yes | N5: Yes | O5: A1 | P5: 67.8 | Q5: 40 | R5: 43 | S5: 1 | T5: 2 | U5: Asphalt Shingles | V5: Flashfoot 2 | W5: Portrait | X5: 1 | Y5: Spring | Z5: 1.3958333 | AA5: 2 | AB5: 2 | AC5: 2 | AD5: =IFERROR(Z5/(AA5*AB5)*AC5*AA5,"") -> 1.3958333 | AE5: =Z5+AD5 -> 2.7916667 | AG5: =AB5+AC5 -> 4
B6: 003 | C6: 21 mins | D6: 24° | E6: 180° | F6: 16 | G6: 5.12 | H6: SolarEdge | I6: Roof Mount | J6: No | L6: Truss | M6: No | N6: No | O6: A3 | P6: 66.3 | Q6: 39.4 | R6: 41.2 | S6: 2 | T6: 0 | U6: Asphalt Shingles | V6: Flashfoot 2 | W6: Portrait | X6: 1 | Y6: Spring | Z6: 1.0555556 | AA6: 2 | AB6: 2 | AC6: 2 | AD6: =IFERROR(Z6/(AA6*AB6)*AC6*AA6,"") -> 1.0555556 | AE6: =Z6+AD6 -> 2.1111111 | AG6: =AB6+AC6 -> 4
B7: 004 | C7: 38 mins | D7: 20° | E7: 104° | F7: 27 | G7: 10.8 | H7: Enphase | I7: Roof Mount | J7: No | L7: Truss | M7: No | N7: No | O7: C2 | P7: 79.3 | Q7: 39.4 | R7: 51.8 | S7: 1 | T7: 0 | U7: Asphalt Shingles | V7: Flashfoot 2 | W7: Portrait | X7: 1 | Y7: Spring | Z7: 1.125 | AA7: 2 | AB7: 2 | AC7: 2 | AD7: =IFERROR(Z7/(AA7*AB7)*AC7*AA7,"") -> 1.125 | AE7: =Z7+AD7 -> 2.25 | AG7: =AB7+AC7 -> 4 | AH7: Yes this job and the one below it both happened
B8: 005 | C8: 38 mins | D8: 20° | E8: 180° | F8: 27 | G8: 10.8 | H8: Enphase | I8: Roof Mount | J8: No | L8: Truss | M8: No | N8: No | O8: C2 | P8: 79.3 | Q8: 39.4 | R8: 51.8 | S8: 1 | T8: 0 | U8: Asphalt Shingles | V8: Flashfoot 2 | W8: Both | X8: 1 | Y8: Spring | Z8: 1.125 | AA8: 2 | AB8: 2 | AC8: 2 | AD8: =IFERROR(Z8/(AA8*AB8)*AC8*AA8,"") -> 1.125 | AE8: =Z8+AD8 -> 2.25 | AG8: =AB8+AC8 -> 4 | AH8: Yes this job and the one above it both happened
B9: 006 | C9: 45 mins | D9: 18.4° | E9: 180° | F9: 18 | G9: 6.12 | H9: SolarEdge | I9: Roof Mount | J9: No | L9: Truss | M9: No | N9: No | O9: A1 | P9: 68.5 | Q9: 40.5 | R9: 43.9 | S9: 1 | T9: 0 | U9: Asphalt Shingles | V9: Unknown | W9: Portrait | X9: 1 | Y9: Spring | Z9: 0.70833333 | AA9: 1 | AB9: 2 | AC9: 2 | AD9: =IFERROR(Z9/(AA9*AB9)*AC9*AA9,"") -> 0.70833333 | AE9: =Z9+AD9 -> 1.4166667 | AG9: =AB9+AC9 -> 4
B10: 007 | C10: 24 mins | D10: 26° | E10: 200° | F10: 13 | G10: 4.225 | H10: SolarEdge | I10: Roof Mount | J10: Yes | L10: Truss | M10: No | N10: Yes | O10: A3 | P10: 65.43 | Q10: 39.45 | R10: 41.6 | S10: 1 | T10: 0 | U10: Asphalt Shingles | V10: Flashfoot 2 | W10: Portrait | X10: 2 | Y10: Spring | Z10: 0.8125 | AA10: 1 | AB10: 2 | AC10: 2 | AD10: =IFERROR(Z10/(AA10*AB10)*AC10*AA10,"") -> 0.8125 | AE10: =Z10+AD10 -> 1.625 | AG10: =AB10+AC10 -> 4
B11: 008 | C11: 21 mins | D11: 10° | E11: 205° | F11: 20 | G11: 7.3 | H11: SolarEdge | I11: Roof Mount | J11: No | L11: Rafter | M11: No | N11: Yes | O11: B2 | P11: 67.8 | Q11: 40 | R11: 43 | S11: 1 | T11: 0 | U11: Asphalt Shingles | V11: Flashfoot 2 | W11: Portrait | X11: 1 | Y11: Spring | Z11: 1.59375 | AA11: 3 | AB11: 2 | AC11: 2 | AD11: =IFERROR(Z11/(AA11*AB11)*AC11*AA11,"") -> 1.59375 | AE11: =Z11+AD11 -> 3.1875 | AG11: =AB11+AC11 -> 4
B12: 009 | C12: 30 mins | D12: 18° | E12: 185° | F12: 18 | G12: 5.76 | H12: SolarEdge | I12: Roof Mount | J12: No | L12: Truss | M12: No | N12: No | O12: A2 | P12: 65.94 | Q12: 39.25 | R12: 39.7 | S12: 1 | T12: 0 | U12: Asphalt Shingles | V12: Unknown | W12: Portrait | X12: 2 | Y12: Spring | Z12: 1.0729167 | AA12: 2 | AB12: 2 | AC12: 2 | AD12: =IFERROR(Z12/(AA12*AB12)*AC12*AA12,"") -> 1.0729167 | AE12: =Z12+AD12 -> 2.1458333 | AG12: =AB12+AC12 -> 4
B13: 010 | C13: 6 mins | D13: 31° | E13: 90° | F13: 16 | G13: 5.12 | H13: SolarEdge | I13: Roof Mount | J13: Yes | L13: Rafter | M13: Yes | N13: Yes | O13: B2 | P13: 65.94 | Q13: 39.25 | R13: 39.7 | S13: 1 | T13: 10 | U13: Asphalt Shingles | V13: Flashfoot 2 | W13: Landscape | X13: 1 | Y13: Spring | Z13: 1.40625 | AA13: 2 | AB13: 2 | AC13: 2 | AD13: =IFERROR(Z13/(AA13*AB13)*AC13*AA13,"") -> 1.40625 | AE13: =Z13+AD13 -> 2.8125 | AG13: =AB13+AC13 -> 4
B14: 011 | C14: 16 mins | D14: 26.6° | E14: 130° | F14: 22 | G14: 8.03 | H14: Enphase | I14: Roof Mount | J14: Yes | L14: Truss | M14: No | N14: No | O14: A1 | P14: 67.8 | Q14: 40 | R14: 43 | S14: 2 | T14: 0 | U14: Asphalt Shingles | V14: Flashfoot 2 | W14: Portrait | X14: 2 | Y14: Spring | Z14: 1.8125 | AA14: 4 | AB14: 2 | AC14: 2 | AD14: =IFERROR(Z14/(AA14*AB14)*AC14*AA14,"") -> 1.8125 | AE14: =Z14+AD14 -> 3.625 | AG14: =AB14+AC14 -> 4
B15: 012 | C15: 51 mins | D15: 45° | E15: 180° | F15: 24 | G15: 8.52 | H15: Enphase | I15: Roof Mount | J15: No | L15: Truss | M15: No | N15: No | O15: C* | P15: 67.8 | Q15: 40 | R15: 43 | S15: 1 | T15: 0 | U15: Asphalt Shingles | V15: Flashfoot 2 | W15: Portrait | X15: 2 | Y15: Spring | Z15: 0.53125 | AA15: 1 | AB15: 1 | AC15: 2 | AD15: =IFERROR(Z15/(AA15*AB15)*AC15*AA15,"") -> 1.0625 | AE15: =Z15+AD15 -> 1.59375 | AG15: =AB15+AC15 -> 3
B16: 013 | C16: 10 mins | D16: 45° | E16: 215° | F16: 20 | G16: 7.3 | H16: SolarEdge | I16: Roof Mount | J16: No | L16: Rafter | M16: No | N16: No | O16: C* | P16: 67.8 | Q16: 40 | R16: 43 | S16: 1 | T16: 0 | U16: Asphalt Shingles | V16: Flashfoot 2 | W16: Portrait | X16: 2 | Y16: Spring | Z16: 1.5625 | AA16: 2 | AB16: 2 | AC16: 2 | AD16: =IFERROR(Z16/(AA16*AB16)*AC16*AA16,"") -> 1.5625 | AE16: =Z16+AD16 -> 3.125 | AG16: =AB16+AC16 -> 4
B17: 014 | C17: 36 mins | D17: 35°/27° | E17: 230°/140° | F17: 31 | G17: 11.005 | H17: SolarEdge | I17: Roof Mount | J17: No | L17: Truss | M17: No | N17: No | O17: C3 | P17: 67.8 | Q17: 40 | R17: 43 | S17: 5 | T17: 0 | U17: Asphalt Shingles | V17: Flashfoot 2 | W17: Portrait | X17: 1 | Y17: Spring | Z17: 1.4791667 | AA17: 3 | AB17: 2 | AC17: 2 | AD17: =IFERROR(Z17/(AA17*AB17)*AC17*AA17,"") -> 1.4791667 | AE17: =Z17+AD17 -> 2.9583333 | AG17: =AB17+AC17 -> 4
B18: 015 | C18: 9 mins | D18: 24° | E18: 180° | F18: 32 | G18: 11.36 | H18: Enphase | I18: Roof Mount | J18: No | L18: Truss | M18: No | N18: Yes | O18: C1 | P18: 67.8 | Q18: 40 | R18: 43 | S18: 3 | T18: 0 | U18: Asphalt Shingles | V18: Flashfoot 2 | W18: Portrait | X18: 2 | Y18: Spring | Z18: 1.6875 | AA18: 3 | AB18: 3 | AC18: 2 | AD18: =IFERROR(Z18/(AA18*AB18)*AC18*AA18,"") -> 1.125 | AE18: =Z18+AD18 -> 2.8125 | AG18: =AB18+AC18 -> 5
B19: 016 | C19: 30 mins | D19: 32° | E19: 218° | F19: 23 | G19: 7.59 | H19: SolarEdge | I19: Roof Mount | J19: No | L19: Truss | M19: No | N19: No | O19: A2 | P19: 66.53 | Q19: 39.21 | R19: 39.7 | S19: 2 | T19: 0 | U19: Asphalt Shingles | V19: Flashfoot 2 | W19: Portrait | X19: 1 | Y19: Spring | Z19: 1.2291667 | AA19: 2 | AB19: 2 | AC19: 2 | AD19: =IFERROR(Z19/(AA19*AB19)*AC19*AA19,"") -> 1.2291667 | AE19: =Z19+AD19 -> 2.4583333 | AG19: =AB19+AC19 -> 4
B20: 017 | C20: 21 mins | D20: 24° | E20: 180° | F20: 20 | G20: 6.4 | H20: SolarEdge | I20: Roof Mount | J20: No | L20: Truss | M20: No | N20: No | O20: A1 | P20: 39.4 | Q20: 66.9 | R20: 41 | S20: 2 | T20: 0 | U20: Asphalt Shingles | V20: Flashfoot 2 | W20: Portrait | X20: 2 | Y20: Spring | Z20: 0.83333333 | AA20: 1 | AB20: 2 | AC20: 2 | AD20: =IFERROR(Z20/(AA20*AB20)*AC20*AA20,"") -> 0.83333333 | AE20: =Z20+AD20 -> 1.6666667 | AG20: =AB20+AC20 -> 4
... B29: 026 | C29: 29 mins | D29: 16°/16° | E29: 178°/267° | F29: 12 | G29: 4.44 | H29: Enphase | I29: Roof Mount | J29: Yes | L29: Rafter | M29: No | N29: No | O29: B1 | P29: 70.67 | Q29: 39.98 | R29: 41.9 | S29: 2 | T29: 0 | U29: Asphalt Shingles | V29: Flashfoot 2 | W29: Portrait | X29: 2 | Y29: Fall | Z29: 0.5625 | AA29: 1 | AB29: 2 | AC29: 2 | AD29: =IFERROR(Z29/(AA29*AB29)*AC29*AA29,"") -> 0.5625 | AE29: =Z29+AD29 -> 1.125 | AG29: =AB29+AC29 -> 4
B30: 027 | C30: 28 mins | D30: 20° | F30: 14 | G30: 4.9 | H30: SMA | I30: Roof Mount | J30: No | L30: Truss | M30: No | N30: Yes | O30: A1 | P30: 69.44 | Q30: 41.26 | R30: 46.5 | S30: 2 | T30: 0 | U30: Asphalt Shingles | V30: Flashfoot 2 | W30: Portrait | X30: 2 | Y30: Summer | Z30: 1.3020833 | AA30: 2 | AB30: 3 | AC30: 2 | AD30: =IFERROR(Z30/(AA30*AB30)*AC30*AA30,"") -> 0.86805556 | AE30: =Z30+AD30 -> 2.1701389 | AG30: =AB30+AC30 -> 5
B31: 028 | C31: 25 mins | D31: 24° | E31: 180° | F31: 22 | G31: 7.81 | H31: Enphase | I31: Roof Mount | J31: Yes | L31: Truss | M31: No | N31: Yes | O31: A2 | P31: 68.5 | Q31: 41 | R31: 41 | S31: 3 | T31: 0 | U31: Asphalt Shingles | V31: Flashfoot 2 | W31: Portrait | X31: 2 | Y31: Summer | Z31: 1.625 | AA31: 3 | AB31: 2 | AC31: 2 | AD31: =IFERROR(Z31/(AA31*AB31)*AC31*AA31,"") -> 1.625 | AE31: =Z31+AD31 -> 3.25 | AG31: =AB31+AC31 -> 4
B32: 029 | C32: 4 mins | D32: 25° | E32: 165° | F32: 11 | G32: 4.07 | H32: SolarEdge | I32: Roof Mount | J32: No | L32: Truss | M32: No | N32: Yes | O32: A1 | P32: 70.67 | Q32: 39.98 | R32: 41.9 | S32: 1 | T32: 0 | U32: Asphalt Shingles | V32: Flashfoot 2 | W32: Portrait | X32: 1 | Y32: Summer | Z32: 0.98958333 | AA32: 2 | AB32: 2 | AC32: 2 | AD32: =IFERROR(Z32/(AA32*AB32)*AC32*AA32,"") -> 0.98958333 | AE32: =Z32+AD32 -> 1.9791667 | AG32: =AB32+AC32 -> 4
B33: 030 | C33: 16 mins | D33: 18° | E33: 180° | F33: 13 | G33: 4.29 | H33: Enphase | I33: Roof Mount | J33: No | L33: Truss | M33: No | N33: No | O33: A1 | P33: 66.9 | Q33: 39.4 | R33: 41 | S33: 1 | T33: 0 | U33: Asphalt Shingles | V33: Flashfoot 2 | W33: Portrait | X33: 1 | Y33: Summer | Z33: 0.72916667 | AA33: 2 | AB33: 2 | AC33: 3 | AD33: =IFERROR(Z33/(AA33*AB33)*AC33*AA33,"") -> 1.09375 | AE33: =Z33+AD33 -> 1.8229167 | AG33: =AB33+AC33 -> 5
B34: 031 | C34: 26 mins | D34: 34° | E34: 260° | F34: 15 | G34: 5.1 | H34: SolarEdge | I34: Roof Mount | J34: No | L34: Truss | M34: No | N34: No | O34: A1 | P34: 68.5 | Q34: 40.5 | R34: 43.9 | S34: 2 | T34: 0 | U34: Asphalt Shingles | V34: Flashfoot 2 | W34: Portrait | X34: 2 | Y34: Summer | Z34: 1.0381944 | AA34: 1 | AB34: 3 | AC34: 3 | AD34: =IFERROR(Z34/(AA34*AB34)*AC34*AA34,"") -> 1.0381944 | AE34: =Z34+AD34 -> 2.0763889 | AG34: =AB34+AC34 -> 6
B35: 032 | C35: 12 mins | D35: 19° | E35: 177°/260° | F35: 16 | G35: 5.92 | H35: Enphase | I35: Roof Mount | J35: No | L35: Truss | M35: No | N35: No | O35: A1 | P35: 70.67 | Q35: 39.98 | R35: 41.9 | S35: 2 | T35: 0 | U35: Asphalt Shingles | V35: Flashfoot 2 | W35: Portrait | X35: 1 | Y35: Summer | Z35: 1.0902778 | AA35: 1 | AB35: 3 | AC35: 3 | AD35: =IFERROR(Z35/(AA35*AB35)*AC35*AA35,"") -> 1.0902778 | AE35: =Z35+AD35 -> 2.1805556 | AG35: =AB35+AC35 -> 6
B36: 033 | C36: 13 mins | D36: 18° | E36: 200° | F36: 11 | G36: 4.07 | H36: SolarEdge | I36: Roof Mount | J36: Yes | L36: Rafter | M36: Yes | N36: No | O36: B2 | P36: 70.67 | Q36: 39.98 | R36: 41.9 | S36: 1 | T36: 18 | U36: Asphalt Shingles | V36: Flashfoot 2 | W36: Portrait | X36: 1 | Y36: Summer | Z36: 1.0069444 | AA36: 1 | AB36: 3 | AC36: 3 | AD36: =IFERROR(Z36/(AA36*AB36)*AC36*AA36,"") -> 1.0069444 | AE36: =Z36+AD36 -> 2.0138889 | AG36: =AB36+AC36 -> 6
B37: 034 | C37: 42 mins | D37: 30° | E37: 180° | F37: 13 | G37: 4.81 | H37: SolarEdge | I37: Roof Mount | J37: No | L37: Rafter | M37: Yes | N37: No | O37: C2 | P37: 70.67 | Q37: 39.98 | R37: 41.9 | S37: 1 | T37: 11 | U37: Asphalt Shingles | V37: Flashfoot 2 | W37: Portrait | X37: 1 | Y37: Summer | Z37: 1.2152778 | AA37: 1 | AB37: 3 | AC37: 3 | AD37: =IFERROR(Z37/(AA37*AB37)*AC37*AA37,"") -> 1.2152778 | AE37: =Z37+AD37 -> 2.4305556 | AG37: =AB37+AC37 -> 6
B38: 035 | C38: 15 mins | D38: 25° | E38: 270° | F38: 23 | G38: 7.59 | H38: SolarEdge | I38: Roof Mount | J38: No | L38: Truss | M38: No | N38: No | O38: A1 | P38: 66.53 | Q38: 39.21 | R38: 39.7 | S38: 1 | T38: 0 | U38: Asphalt Shingles | V38: Flashfoot 2 | W38: Portrait | X38: 1 | Y38: Summer | Z38: 1.1145833 | AA38: 1 | AB38: 3 | AC38: 3 | AD38: =IFERROR(Z38/(AA38*AB38)*AC38*AA38,"") -> 1.1145833 | AE38: =Z38+AD38 -> 2.2291667 | AG38: =AB38+AC38 -> 6
B39: 036 | C39: 21 mins | D39: 30° | E39: 180° | F39: 13 | G39: 4.81 | H39: Enphase | I39: Roof Mount | J39: Yes | L39: Truss | M39: No | N39: Yes | O39: A1 | P39: 70.67 | Q39: 39.98 | R39: 41.9 | S39: 1 | T39: 0 | U39: Asphalt Shingles | V39: Flashfoot 2 | W39: Portrait | X39: 1 | Y39: Summer | Z39: 1.0520833 | AA39: 1 | AB39: 3 | AC39: 3 | AD39: =IFERROR(Z39/(AA39*AB39)*AC39*AA39,"") -> 1.0520833 | AE39: =Z39+AD39 -> 2.1041667 | AG39: =AB39+AC39 -> 6
B40: 037 | C40: 26 mins | D40: 38° | E40: 173° | F40: 9 | G40: 4.05 | H40: Enphase | I40: Roof Mount | J40: No | L40: Rafter | M40: No | N40: Yes | O40: A3 | P40: 83.07 | Q40: 41 | R40: 50.71 | S40: 1 | T40: 0 | U40: Standing Seam Metal Roof | V40: S-5! | W40: Landscape | X40: 1 | Y40: Fall | Z40: 2.9583333 | AA40: 3 | AB40: 3 | AC40: 3 | AD40: =IFERROR(Z40/(AA40*AB40)*AC40*AA40,"") -> 2.9583333 | AE40: =Z40+AD40 -> 5.9166667 | AG40: =AB40+AC40 -> 6
B41: 038 | C41: 15 mins | D41: 16° | E41: 192° | F41: 29 | G41: 10.73 | H41: Enphase | I41: Roof Mount | J41: Yes | L41: Truss | M41: No | N41: Yes | O41: C1 | P41: 70.67 | Q41: 39.98 | R41: 41.9 | S41: 2 | T41: 0 | U41: Asphalt Shingles | V41: Flashfoot 2 | W41: Portrait | X41: 2 | Y41: Summer | Z41: 1.58125 | AA41: 2 | AB41: 3 | AC41: 3 | AD41: =IFERROR(Z41/(AA41*AB41)*AC41*AA41,"") -> 1.58125 | AE41: =Z41+AD41 -> 3.1625 | AG41: =AB41+AC41 -> 6
B42: 039 | C42: 25 mins | D42: 18° | E42: 157° | F42: 16 | G42: 6.08 | H42: SolarEdge | I42: Roof Mount | J42: No | L42: Rafter | M42: No | N42: Yes | O42: B2 | P42: 72.4 | Q42: 40.6 | R42: 43 | S42: 2 | T42: 0 | U42: Asphalt Shingles | V42: Flashfoot 2 | W42: Portrait | X42: 1 | Y42: Summer | Z42: 1.1819444 | AA42: 1 | AB42: 3 | AC42: 3 | AD42: =IFERROR(Z42/(AA42*AB42)*AC42*AA42,"") -> 1.1819444 | AE42: =Z42+AD42 -> 2.3638889 | AG42: =AB42+AC42 -> 6
B43: 040 | C43: 22 mins | E43: 148°/240° | F43: 43 | G43: 15.695 | H43: Enphase | I43: Roof Mount | J43: No | L43: Truss | M43: No | N43: No | O43: C1 | P43: 67.8 | Q43: 40 | R43: 43 | S43: 8 | T43: 0 | U43: Asphalt Shingles | V43: Flashfoot 2 | W43: Portrait | X43: 2 | Y43: Summer | Z43: 3.1770833 | AA43: 3 | AB43: 3 | AC43: 3 | AD43: =IFERROR(Z43/(AA43*AB43)*AC43*AA43,"") -> 3.1770833 | AE43: =Z43+AD43 -> 6.3541667 | AG43: =AB43+AC43 -> 6
B44: 041 | C44: 36 mins | D44: 30° | E44: 260° | F44: 36 | G44: 13.32 | H44: SolarEdge | I44: Roof Mount | J44: No | L44: Truss | M44: No | N44: No | O44: C* | P44: 70.67 | Q44: 39.98 | R44: 41.9 | S44: 1 | T44: 0 | U44: Asphalt Shingles | V44: Flashfoot 2 | W44: Portrait | X44: 1 | Y44: Summer | Z44: 2.2875 | AA44: 3 | AB44: 3 | AC44: 3 | AD44: =IFERROR(Z44/(AA44*AB44)*AC44*AA44,"") -> 2.2875 | AE44: =Z44+AD44 -> 4.575 | AG44: =AB44+AC44 -> 6
B45: 042 | C45: 25 mins | D45: 10° | E45: 162° | F45: 16 | G45: 5.28 | H45: SolarEdge | I45: Roof Mount | J45: No | L45: Truss | M45: No | N45: Yes | O45: B2 | P45: 66.9 | Q45: 39.4 | R45: 41 | S45: 1 | T45: 0 | U45: Standing Seam Metal Roof | V45: S-5! | W45: Portrait | X45: 1 | Y45: Summer | Z45: 0.72916667 | AA45: 1 | AB45: 2 | AC45: 3 | AD45: =IFERROR(Z45/(AA45*AB45)*AC45*AA45,"") -> 1.09375 | AE45: =Z45+AD45 -> 1.8229167 | AG45: =AB45+AC45 -> 5
B46: 044 | C46: 22 mins | D46: 20°/37° | E46: 215°/125° | F46: 21 | G46: 7.77 | H46: Enphase | I46: Roof Mount | J46: Yes | L46: Truss | M46: No | N46: No | O46: A1 | P46: 70.67 | Q46: 39.98 | R46: 41.9 | S46: 3 | T46: 0 | U46: Asphalt Shingles | V46: Flashfoot 2 | W46: Portrait | X46: 2 | Y46: Fall | Z46: 0.98958333 | AA46: 2 | AB46: 3 | AC46: 3 | AD46: =IFERROR(Z46/(AA46*AB46)*AC46*AA46,"") -> 0.98958333 | AE46: =Z46+AD46 -> 1.9791667 | AG46: =AB46+AC46 -> 6
B47: 045 | C47: 10 mins | D47: 23° | E47: 135° | F47: 9 | G47: 3.33 | H47: Enphase | I47: Roof Mount | J47: Yes | L47: Rafter | M47: Yes | N47: Yes | O47: B2 | P47: 70.67 | Q47: 39.98 | R47: 41.9 | S47: 1 | T47: 11 | U47: Asphalt Shingles | V47: Flashfoot 2 | W47: Portrait | X47: 1 | Y47: Summer | Z47: 1.3819444 | AA47: 2 | AB47: 3 | AC47: 3 | AD47: =IFERROR(Z47/(AA47*AB47)*AC47*AA47,"") -> 1.3819444 | AE47: =Z47+AD47 -> 2.7638889 | AG47: =AB47+AC47 -> 6
B48: 046 | C48: 16 mins | D48: 30° | E48: 180° | F48: 54 | G48: 23.22 | H48: Enphase | I48: Ground Mount | J48: No | L48: Grount Mount | M48: No | N48: No | O48: C2 | P48: 81.89 | Q48: 40.56 | R48: 55.11 | S48: 2 | T48: 0 | U48: Ground Mount | V48: Ground Mount | W48: Portrait | X48: 0 | Y48: Fall | Z48: 4.3611111 | AA48: 8 | AB48: 3 | AC48: 3 | AD48: =IFERROR(Z48/(AA48*AB48)*AC48*AA48,"") -> 4.3611111 | AE48: =Z48+AD48 -> 8.7222222 | AG48: =AB48+AC48 -> 6
B49: 047 | C49: 18 mins | D49: 28° | E49: 200° | F49: 14 | G49: 5.18 | H49: SolarEdge | I49: Roof Mount | J49: Yes | L49: Truss | M49: No | N49: No | O49: A1 | P49: 70.67 | Q49: 39.98 | R49: 41.9 | S49: 1 | T49: 0 | U49: Asphalt Shingles | V49: Flashfoot 2 | W49: Portrait | X49: 1 | Y49: Fall | Z49: 0.5625 | AA49: 2 | AB49: 1 | AC49: 3 | AD49: =IFERROR(Z49/(AA49*AB49)*AC49*AA49,"") -> 1.6875 | AE49: =Z49+AD49 -> 2.25 | AG49: =AB49+AC49 -> 4
B50: 049 | C50: 43 mins | D50: 25° | E50: 180° | F50: 20 | G50: 7.4 | H50: Enphase | I50: Roof Mount | J50: No | L50: Truss | M50: No | N50: No | O50: A3 | P50: 70.67 | Q50: 39.98 | R50: 41.9 | S50: 1 | T50: 0 | U50: Asphalt Shingles | V50: Flashfoot 2 | W50: Portrait | X50: 2 | Y50: Fall | Z50: 1.7291667 | AA50: 3 | AB50: 2 | AC50: 3 | AD50: =IFERROR(Z50/(AA50*AB50)*AC50*AA50,"") -> 2.59375 | AE50: =Z50+AD50 -> 4.3229167 | AG50: =AB50+AC50 -> 5
B51: 050 | C51: 56 mins | D51: 30° | E51: 180° | F51: 48 | G51: 17.76 | H51: SolarEdge | I51: Ground Mount | J51: No | L51: Grount Mount | M51: No | N51: No | O51: C* | P51: 70.67 | Q51: 39.98 | R51: 41.9 | S51: 2 | T51: 0 | U51: Ground Mount | V51: Ground Mount | W51: Portrait | X51: 0 | Y51: Fall | Z51: 5.375 | AA51: 7 | AB51: 3 | AC51: 3 | AD51: =IFERROR(Z51/(AA51*AB51)*AC51*AA51,"") -> 5.375 | AE51: =Z51+AD51 -> 10.75 | AG51: =AB51+AC51 -> 6
B52: 051 | C52: 27 mins | D52: 24° | E52: 180°/90° | F52: 19 | G52: 7.03 | H52: Enphase | I52: Roof Mount | J52: No | L52: Truss | M52: No | N52: Yes | O52: A2 | P52: 70.67 | Q52: 39.98 | R52: 41.9 | S52: 2 | T52: 0 | U52: Asphalt Shingles | V52: Flashfoot 2 | W52: Portrait | X52: 2 | Y52: Fall | Z52: 1.0208333 | AA52: 1 | AB52: 3 | AC52: 3 | AD52: =IFERROR(Z52/(AA52*AB52)*AC52*AA52,"") -> 1.0208333 | AE52: =Z52+AD52 -> 2.0416667 | AG52: =AB52+AC52 -> 6
B53: 052 | C53: 16 mins | D53: 24° | E53: 185° | F53: 31 | G53: 11.625 | H53: SolarEdge | I53: Roof Mount | J53: No | L53: Truss | M53: No | N53: No | O53: A1 | P53: 67.8 | Q53: 40 | R53: 43 | S53: 3 | T53: 0 | U53: Asphalt Shingles | V53: Flashfoot 2 | W53: Both | X53: 2 | Y53: Fall | Z53: 0.81875 | AA53: 1 | AB53: 2 | AC53: 3 | AD53: =IFERROR(Z53/(AA53*AB53)*AC53*AA53,"") -> 1.228125 | AE53: =Z53+AD53 -> 2.046875 | AG53: =AB53+AC53 -> 5
B54: 054 | C54: 25 mins | D54: 20° | E54: 175° | F54: 12 | G54: 4.38 | H54: Enphase | I54: Roof Mount | J54: Yes | L54: Truss | M54: No | N54: Yes | O54: A1 | P54: 67.8 | Q54: 40 | R54: 43 | S54: 1 | T54: 0 | U54: Asphalt Shingles | V54: Flashfoot 2 | W54: Portrait | X54: 1 | Y54: Fall | Z54: 0.69444444 | AA54: 1 | AB54: 2 | AC54: 3 | AD54: =IFERROR(Z54/(AA54*AB54)*AC54*AA54,"") -> 1.0416667 | AE54: =Z54+AD54 -> 1.7361111 | AG54: =AB54+AC54 -> 5
B55: 055 | C55: 42 mins | D55: 22° | E55: 180° | F55: 14 | G55: 4.97 | H55: Enphase | I55: Roof Mount | J55: Yes | L55: Truss | M55: No | N55: No | O55: C2 | P55: 67.8 | Q55: 40 | R55: 43 | S55: 2 | T55: 0 | U55: Asphalt Shingles | V55: Flashfoot 2 | W55: Both | X55: 2 | Y55: Fall | Z55: 0.71527778 | AA55: 1 | AB55: 2 | AC55: 3 | AD55: =IFERROR(Z55/(AA55*AB55)*AC55*AA55,"") -> 1.0729167 | AE55: =Z55+AD55 -> 1.7881944 | AG55: =AB55+AC55 -> 5
... B61: 062 | C61: 37 mins | D61: 20° | E61: 245° | F61: 21 | G61: 7.77 | H61: SolarEdge | I61: Roof Mount | J61: No | L61: Truss | M61: No | N61: No | O61: A1 | P61: 70.67 | Q61: 39.98 | R61: 41.9 | S61: 1 | T61: 0 | U61: Asphalt Shingles | V61: Flashfoot 2 | W61: Portrait | X61: 2 | Y61: Winter | Z61: 0.96875 | AA61: 2 | AB61: 3 | AC61: 3 | AD61: =IFERROR(Z61/(AA61*AB61)*AC61*AA61,"") -> 0.96875 | AE61: =Z61+AD61 -> 1.9375 | AG61: =AB61+AC61 -> 6
B62: 063 | C62: 23 mins | F62: 22 | G62: 8.03 | H62: SolarEdge | I62: Roof Mount | J62: Yes | L62: Rafter | M62: Yes | N62: Yes | O62: A1 | P62: 67.8 | Q62: 40 | R62: 43 | S62: 1 | T62: 14 | U62: Asphalt Shingles | V62: Flashfoot 2 | W62: Portrait | X62: 2 | Y62: Fall | Z62: 1.2708333 | AA62: 2 | AB62: 2 | AC62: 3 | AD62: =IFERROR(Z62/(AA62*AB62)*AC62*AA62,"") -> 1.90625 | AE62: =Z62+AD62 -> 3.1770833 | AG62: =AB62+AC62 -> 5
B63: 064 | C63: 22 mins | D63: 30° | E63: 230° | F63: 16 | G63: 6.08 | H63: SolarEdge | I63: Roof Mount | J63: Yes | L63: Rafter | M63: Yes | N63: Yes | O63: A1 | P63: 70.67 | Q63: 39.98 | R63: 41.9 | S63: 2 | T63: 2 | U63: Asphalt Shingles | V63: Flashfoot 2 | W63: Portrait | X63: 2 | Y63: Fall | Z63: 1.1527778 | AA63: 2 | AB63: 2 | AC63: 3 | AD63: =IFERROR(Z63/(AA63*AB63)*AC63*AA63,"") -> 1.7291667 | AE63: =Z63+AD63 -> 2.8819444 | AG63: =AB63+AC63 -> 5
B64: 065 | C64: 26 mins | D64: 18° | E64: 270° | F64: 13 | G64: 4.81 | H64: Enphase | I64: Roof Mount | J64: No | L64: Truss | M64: No | N64: Yes | O64: A2 | P64: 70.67 | Q64: 39.98 | R64: 41.9 | S64: 1 | T64: 0 | U64: Asphalt Shingles | V64: Unknown | W64: Portrait | X64: 2 | Y64: Fall | Z64: 1.2708333 | AA64: 2 | AB64: 3 | AC64: 3 | AD64: =IFERROR(Z64/(AA64*AB64)*AC64*AA64,"") -> 1.2708333 | AE64: =Z64+AD64 -> 2.5416667 | AG64: =AB64+AC64 -> 6
B65: 066 | C65: 24 mins | D65: 30° | E65: 135° | F65: 19 | G65: 7.03 | H65: Enphase | I65: Roof Mount | J65: No | L65: Truss | M65: No | N65: Yes | O65: A1 | P65: 67.8 | Q65: 40 | R65: 43 | S65: 4 | T65: 0 | U65: Asphalt Shingles | V65: Flashfoot 2 | W65: Both | X65: 2 | Y65: Fall | Z65: 1.125 | AA65: 1 | AB65: 3 | AC65: 3 | AD65: =IFERROR(Z65/(AA65*AB65)*AC65*AA65,"") -> 1.125 | AE65: =Z65+AD65 -> 2.25 | AG65: =AB65+AC65 -> 6
B66: 067 | C66: 40 mins | D66: 31° | E66: 180° | F66: 20 | G66: 7.6 | H66: Enphase | I66: Roof Mount | J66: No | L66: Truss | M66: No | N66: No | O66: A1 | P66: 68.5 | Q66: 41.02 | R66: 40.8 | S66: 1 | T66: 0 | U66: Asphalt Shingles | V66: Flashfoot 2 | W66: Portrait | X66: 1 | Y66: Fall | Z66: 1.0625 | AA66: 1 | AB66: 3 | AC66: 3 | AD66: =IFERROR(Z66/(AA66*AB66)*AC66*AA66,"") -> 1.0625 | AE66: =Z66+AD66 -> 2.125 | AG66: =AB66+AC66 -> 6
B67: 068 | C67: 24 mins | D67: 16° | E67: 180° | F67: 12 | G67: 4.38 | H67: Enphase | I67: Roof Mount | J67: Yes | L67: Rafter | M67: Yes | N67: No | O67: A1 | P67: 69.37 | Q67: 40.91 | R67: 44.09 | S67: 1 | T67: 7 | U67: Asphalt Shingles | V67: Flashfoot 2 | W67: Portrait | X67: 2 | Y67: Winter | Z67: 1.2256944 | AA67: 2 | AB67: 3 | AC67: 3 | AD67: =IFERROR(Z67/(AA67*AB67)*AC67*AA67,"") -> 1.2256944 | AE67: =Z67+AD67 -> 2.4513889 | AG67: =AB67+AC67 -> 6
B68: 069 | C68: 27 mins | D68: 22.6° | E68: 90°/180°/270° | F68: 21 | G68: 7.77 | H68: Enphase | I68: Roof Mount | J68: No | L68: Truss | M68: No | N68: Yes | O68: A1 | P68: 70.67 | Q68: 39.98 | R68: 41.9 | S68: 4 | T68: 0 | U68: Asphalt Shingles | V68: Flashfoot 2 | W68: Portrait | X68: 2 | Y68: Fall | Z68: 1.125 | AA68: 2 | AB68: 3 | AC68: 3 | AD68: =IFERROR(Z68/(AA68*AB68)*AC68*AA68,"") -> 1.125 | AE68: =Z68+AD68 -> 2.25 | AG68: =AB68+AC68 -> 6 | AH68: Installed a car charger
B69: 070 | C69: 32 mins | D69: 18° | E69: 180° | F69: 36 | G69: 13.32 | H69: Enphase | I69: Roof Mount | J69: No | L69: Truss | M69: No | N69: No | O69: A1 | P69: 70.67 | Q69: 39.98 | R69: 41.9 | S69: 1 | T69: 0 | U69: Ag Metal | V69: Ejot | W69: Landscape | X69: 2 | Y69: Winter | Z69: 2.34375 | AA69: 3 | AB69: 3 | AC69: 3 | AD69: =IFERROR(Z69/(AA69*AB69)*AC69*AA69,"") -> 2.34375 | AE69: =Z69+AD69 -> 4.6875 | AG69: =AB69+AC69 -> 6
B70: 071 | C70: 30 mins | D70: 21° | E70: 180° | F70: 17 | G70: 5.61 | H70: SolarEdge | I70: Roof Mount | J70: No | L70: Truss | M70: No | N70: No | O70: A1 | P70: 66.53 | Q70: 39.21 | R70: 39.7 | S70: 2 | T70: 0 | U70: Asphalt Shingles | V70: Flashfoot 2 | W70: Both | X70: 2 | Y70: Fall | Z70: 0.97569444 | AA70: 2 | AB70: 3 | AC70: 3 | AD70: =IFERROR(Z70/(AA70*AB70)*AC70*AA70,"") -> 0.97569444 | AE70: =Z70+AD70 -> 1.9513889 | AG70: =AB70+AC70 -> 6
B71: 072 | C71: 14 mins | D71: 26° | E71: 200° | F71: 16 | G71: 5.52 | H71: SolarEdge | I71: Roof Mount | J71: Yes | L71: Truss | M71: No | N71: Yes | O71: A1 | P71: 68.8 | Q71: 41.5 | R71: 44.8 | S71: 2 | T71: 0 | U71: Asphalt Shingles | V71: Flashfoot 2 | W71: Portrait | X71: 1 | Y71: Fall | Z71: 1.375 | AA71: 3 | AB71: 3 | AC71: 3 | AD71: =IFERROR(Z71/(AA71*AB71)*AC71*AA71,"") -> 1.375 | AE71: =Z71+AD71 -> 2.75 | AG71: =AB71+AC71 -> 6
B72: 073 | C72: 26 mins | D72: 32° | E72: 180° | F72: 14 | G72: 5.32 | H72: Enphase | I72: Roof Mount | J72: No | L72: Truss | M72: No | N72: No | O72: A1 | P72: 70.67 | Q72: 39.98 | R72: 41.9 | S72: 1 | T72: 0 | U72: Asphalt Shingles | V72: Unknown | W72: Portrait | X72: 1 | Y72: Fall | Z72: 1.0208333 | AA72: 1 | AB72: 3 | AC72: 3 | AD72: =IFERROR(Z72/(AA72*AB72)*AC72*AA72,"") -> 1.0208333 | AE72: =Z72+AD72 -> 2.0416667 | AG72: =AB72+AC72 -> 6
B73: 074 | C73: 15 mins | D73: 22.6° | E73: 180° | F73: 19 | G73: 7.22 | H73: SolarEdge | I73: Roof Mount | J73: Yes | L73: Truss | M73: No | N73: No | O73: A2 | P73: 70.67 | Q73: 39.98 | R73: 41.9 | S73: 1 | T73: 0 | U73: Asphalt Shingles | V73: Unknown | W73: Portrait | X73: 1 | Y73: Winter | Z73: 0.84375 | AA73: 1 | AB73: 3 | AC73: 3 | AD73: =IFERROR(Z73/(AA73*AB73)*AC73*AA73,"") -> 0.84375 | AE73: =Z73+AD73 -> 1.6875 | AG73: =AB73+AC73 -> 6
B74: 075 | C74: 3 mins | D74: 24° | E74: 200° | F74: 4 | G74: 1.52 | H74: Enphase | I74: Roof Mount | J74: No | L74: Truss | M74: No | N74: Yes | O74: A1 | P74: 70.67 | Q74: 39.98 | R74: 41.9 | S74: 1 | T74: 0 | U74: Asphalt Shingles | V74: Flashfoot 2 | W74: Portrait | X74: 1 | Y74: Winter | Z74: 0.86458333 | AA74: 1 | AB74: 3 | AC74: 1 | AD74: =IFERROR(Z74/(AA74*AB74)*AC74*AA74,"") -> 0.28819444 | AE74: =Z74+AD74 -> 1.1527778 | AG74: =AB74+AC74 -> 4
B75: 076 | C75: 28 mins | D75: 30° | E75: 210° | F75: 36 | G75: 13.32 | H75: Enphase | I75: Roof Mount | J75: Yes | L75: Truss | M75: No | N75: Yes | O75: A1 | P75: 67.8 | Q75: 40 | R75: 43 | S75: 1 | T75: 0 | U75: Asphalt Shingles | V75: Flashfoot 2 | W75: Portrait | X75: 2 | Y75: Winter | Z75: 1.625 | AA75: 2 | AB75: 2 | AC75: 3 | AD75: =IFERROR(Z75/(AA75*AB75)*AC75*AA75,"") -> 2.4375 | AE75: =Z75+AD75 -> 4.0625 | AG75: =AB75+AC75 -> 5
B76: 077 | C76: 39 mins | D76: 30° | E76: 180° | F76: 14 | G76: 5.95 | H76: SolarEdge | I76: Ground Mount | J76: No | L76: Grount Mount | M76: No | N76: No | O76: A1 | P76: 81.9 | Q76: 40.6 | R76: 55.1 | S76: 1 | T76: 0 | U76: Ground Mount | V76: Ground Mount | W76: Portrait | X76: 0 | Y76: Spring | Z76: 1.5173611 | AA76: 2 | AB76: 3 | AC76: 2 | AD76: =IFERROR(Z76/(AA76*AB76)*AC76*AA76,"") -> 1.0115741 | AE76: =Z76+AD76 -> 2.5289352 | AG76: =AB76+AC76 -> 5
B77: 078 | C77: 25 mins | E77: 140° | F77: 18 | G77: 6.66 | H77: Enphase | I77: Roof Mount | J77: Yes | L77: Truss | M77: No | N77: Yes | O77: B1 | P77: 67.8 | Q77: 40 | R77: 43 | S77: 1 | T77: 0 | U77: Asphalt Shingles | V77: Flashfoot 2 | W77: Portrait | X77: 1 | Y77: Summer | Z77: 0.64583333 | AA77: 1 | AB77: 2 | AC77: 2 | AD77: =IFERROR(Z77/(AA77*AB77)*AC77*AA77,"") -> 0.64583333 | AE77: =Z77+AD77 -> 1.2916667 | AG77: =AB77+AC77 -> 4
B78: 079 | C78: 10 mins | D78: 26° | E78: 260°/80° | F78: 28 | G78: 11.2 | H78: Enphase | I78: Roof Mount | J78: Yes | L78: Truss | M78: No | N78: No | O78: B1 | P78: 71.7 | Q78: 40 | R78: 45 | S78: 2 | T78: 0 | U78: Asphalt Shingles | V78: Flashfoot 2 | W78: Portrait | X78: 1 | Y78: Spring | Z78: 1.46875 | AA78: 2 | AB78: 2 | AC78: 2 | AD78: =IFERROR(Z78/(AA78*AB78)*AC78*AA78,"") -> 1.46875 | AE78: =Z78+AD78 -> 2.9375 | AG78: =AB78+AC78 -> 4
B79: 080 | C79: 27 mins | F79: 29 | G79: 10.73 | H79: Enphase | I79: Roof Mount | J79: Yes | L79: Rafter | M79: No | N79: Yes | O79: A* | P79: 67.8 | Q79: 40 | R79: 43 | S79: 4 | T79: 0 | U79: Asphalt Shingles | V79: Flashfoot 2 | W79: Portrait | X79: 1 | Y79: Spring | Z79: 1.5104167 | AA79: 4 | AB79: 2 | AC79: 2 | AD79: =IFERROR(Z79/(AA79*AB79)*AC79*AA79,"") -> 1.5104167 | AE79: =Z79+AD79 -> 3.0208333 | AG79: =AB79+AC79 -> 4
B80: 084 | C80: 44 mins | D80: 17° | E80: 180° | F80: 15 | G80: 5.55 | H80: Enphase | I80: Roof Mount | J80: Yes | L80: Truss | M80: No | N80: No | O80: A1 | P80: 67.8 | Q80: 40 | R80: 43 | S80: 1 | T80: 0 | U80: Asphalt Shingles | V80: Flashfoot 2 | W80: Landscape | X80: 1 | Y80: Spring | Z80: 1.5868056 | AA80: 5 | AB80: 3 | AC80: 2 | AD80: =IFERROR(Z80/(AA80*AB80)*AC80*AA80,"") -> 1.0578704 | AE80: =Z80+AD80 -> 2.6446759 | AG80: =AB80+AC80 -> 5 | AH80: Time data looks wrong to me
B81: 085 | C81: 25 mins | D81: 37° | E81: 155° | F81: 28 | G81: 10.36 | H81: SolarEdge | I81: Roof Mount | J81: Yes | L81: TJI | M81: No | N81: Yes | O81: A1 | P81: 67.8 | Q81: 40 | R81: 43 | S81: 1 | T81: 0 | U81: Asphalt Shingles | V81: RT Mini | W81: Portrait | X81: 1 | Y81: Spring | Z81: 0.92013889 | AA81: 2 | AB81: 1 | AC81: 2 | AD81: =IFERROR(Z81/(AA81*AB81)*AC81*AA81,"") -> 1.8402778 | AE81: =Z81+AD81 -> 2.7604167 | AG81: =AB81+AC81 -> 3
B82: 087 | C82: 7 mins | D82: 18° | E82: 270°/180°/90° | F82: 9 | G82: 3.42 | H82: Enphase | I82: Roof Mount | J82: Yes | L82: Rafter | M82: No | N82: Yes | O82: A1 | P82: 70.67 | Q82: 39.98 | R82: 41.9 | S82: 3 | T82: 0 | U82: Asphalt Shingles | V82: Flashfoot 2 | W82: Portrait | X82: 1 | Y82: Spring | Z82: 1.03125 | AA82: 2 | AB82: 2 | AC82: 2 | AD82: =IFERROR(Z82/(AA82*AB82)*AC82*AA82,"") -> 1.03125 | AE82: =Z82+AD82 -> 2.0625 | AG82: =AB82+AC82 -> 4
B83: 089 | C83: 13 mins | D83: 26.6° | E83: 115° | F83: 24 | G83: 9.12 | H83: Enphase | I83: Roof Mount | J83: Yes | L83: Truss | M83: No | N83: Yes | O83: A2 | P83: 70.67 | Q83: 39.98 | R83: 41.9 | S83: 2 | T83: 0 | U83: Asphalt Shingles | V83: Flashfoot 2 | W83: Portrait | X83: 1 | Y83: Spring | Z83: 0.0625 | AA83: 1 | AB83: 1 | AC83: 2 | AD83: =IFERROR(Z83/(AA83*AB83)*AC83*AA83,"") -> 0.125 | AE83: =Z83+AD83 -> 0.1875 | AG83: =AB83+AC83 -> 3 | AH83: time data looks wrong to me
B84: 090 | C84: 27 mins | D84: 26° | E84: 270°/90° | F84: 11 | G84: 4.07 | H84: SolarEdge | I84: Roof Mount | J84: No | L84: Truss | M84: No | N84: Yes | O84: A1 | P84: 69.4 | Q84: 40.8 | R84: 43 | S84: 2 | T84: 0 | U84: Asphalt Shingles | V84: Flashfoot 2 | W84: Portrait | X84: 1 | Y84: Spring | Z84: 0.62152778 | AA84: 2 | AB84: 2 | AC84: 2 | AD84: =IFERROR(Z84/(AA84*AB84)*AC84*AA84,"") -> 0.62152778 | AE84: =Z84+AD84 -> 1.2430556 | AG84: =AB84+AC84 -> 4
B85: 091 | C85: 25 mins | D85: 14°/18° | E85: 180°/270° | F85: 21 | G85: 7.98 | H85: Enphase | I85: Roof Mount | J85: No | L85: Truss | M85: No | N85: No | O85: A3 | P85: 70.67 | Q85: 39.98 | R85: 41.9 | S85: 3 | T85: 0 | U85: Asphalt Shingles | V85: Flashfoot 2 | W85: Both | X85: 1 | Y85: Spring | Z85: 0.4375 | AA85: 1 | AB85: 1 | AC85: 2 | AD85: =IFERROR(Z85/(AA85*AB85)*AC85*AA85,"") -> 0.875 | AE85: =Z85+AD85 -> 1.3125 | AG85: =AB85+AC85 -> 3
B86: 092 | C86: 34 mins | D86: 18° | E86: 180° | F86: 10 | G86: 3.7 | H86: SolarEdge | I86: Roof Mount | J86: No | L86: Truss | M86: No | N86: No | O86: C* | P86: 69.13 | Q86: 40.91 | R86: 45.19 | S86: 1 | T86: 0 | U86: Asphalt Shingles | V86: Flashfoot 2 | W86: Portrait | X86: 1 | Y86: Spring | Z86: 0.41666667 | AA86: 1 | AB86: 1 | AC86: 2 | AD86: =IFERROR(Z86/(AA86*AB86)*AC86*AA86,"") -> 0.83333333 | AE86: =Z86+AD86 -> 1.25 | AG86: =AB86+AC86 -> 3
B87: 093 | C87: 48 mins | D87: 18° | E87: 145° | F87: 14 | G87: 5.6 | H87: Enphase | I87: Roof Mount | J87: No | L87: Purlin | M87: No | N87: No | O87: A2 | P87: 71.7 | Q87: 40 | R87: 45 | S87: 1 | T87: 0 | U87: Ag Metal | V87: Ejot | W87: Portrait | X87: 2 | Y87: Spring | Z87: 0.9 | AA87: 1 | AB87: 3 | AC87: 2 | AD87: =IFERROR(Z87/(AA87*AB87)*AC87*AA87,"") -> 0.6 | AE87: =Z87+AD87 -> 1.5 | AG87: =AB87+AC87 -> 5
B88: 094 | C88: 14 mins | D88: 26° | E88: 180° | F88: 16 | G88: 6.4 | H88: Enphase | I88: Roof Mount | J88: Yes | L88: Truss | M88: No | N88: Yes | O88: A1 | P88: 71.7 | Q88: 40 | R88: 45 | S88: 1 | T88: 0 | U88: Asphalt Shingles | V88: Flashfoot 2 | W88: Portrait | X88: 1 | Y88: Spring | Z88: 1.2465278 | AA88: 3 | AB88: 3 | AC88: 2 | AD88: =IFERROR(Z88/(AA88*AB88)*AC88*AA88,"") -> 0.83101852 | AE88: =Z88+AD88 -> 2.0775463 | AG88: =AB88+AC88 -> 5
B89: 095 | C89: 1 hour 32 mins | D89: 18° | E89: 135° | F89: 20 | G89: 9 | H89: SolarEdge | I89: Roof Mount | J89: No | L89: Purlin | M89: No | N89: No | O89: A* | P89: 82.79 | Q89: 40.94 | R89: 55.12 | S89: 1 | T89: 0 | U89: Ag Metal | V89: Ejot | W89: Landscape | X89: 1 | Y89: Spring | Z89: 0.77083333 | AA89: 1 | AB89: 2 | AC89: 2 | AD89: =IFERROR(Z89/(AA89*AB89)*AC89*AA89,"") -> 0.77083333 | AE89: =Z89+AD89 -> 1.5416667 | AG89: =AB89+AC89 -> 4
B90: 096 | C90: 21 mins | D90: 30° | E90: 90°/180°/270° | F90: 56 | G90: 20.72 | H90: SolarEdge | I90: Roof Mount | J90: Yes | L90: Truss | M90: No | N90: No | O90: A* | P90: 67.8 | Q90: 40 | R90: 43 | S90: 7 | T90: 0 | U90: Asphalt Shingles | V90: Flashfoot 2 | W90: Portrait | X90: 2 | Y90: Spring | Z90: 1.825 | AA90: 5 | AB90: 1 | AC90: 2 | AD90: =IFERROR(Z90/(AA90*AB90)*AC90*AA90,"") -> 3.65 | AE90: =Z90+AD90 -> 5.475 | AG90: =AB90+AC90 -> 3
B91: 104 | C91: 21 mins | D91: 30° | E91: 175° | F91: 24 | G91: 8.88 | H91: Enphase | I91: Roof Mount | J91: No | L91: Truss | M91: No | N91: No | O91: A1 | P91: 68.5 | Q91: 41.01 | R91: 41.02 | S91: 1 | T91: 0 | U91: Asphalt Shingles | V91: Flashfoot 2 | W91: Portrait | X91: 1 | Y91: Spring | Z91: 0.76041667 | AA91: 1 | AB91: 2 | AC91: 2 | AD91: =IFERROR(Z91/(AA91*AB91)*AC91*AA91,"") -> 0.76041667 | AE91: =Z91+AD91 -> 1.5208333 | AG91: =AB91+AC91 -> 4
B92: 112 | C92: 25 mins | D92: 26° | E92: 170°/260° | F92: 26 | G92: 9.62 | H92: Enphase | I92: Roof Mount | J92: Yes | L92: Truss | M92: No | N92: Yes | O92: A2 | P92: 69.13 | Q92: 40.91 | R92: 45.19 | S92: 2 | T92: 0 | U92: Asphalt Shingles | V92: Flashfoot 2 | W92: Portrait | X92: 1 | Y92: Summer | Z92: 0.13194444 | AA92: 1 | AB92: 1 | AC92: 2 | AD92: =IFERROR(Z92/(AA92*AB92)*AC92*AA92,"") -> 0.26388889 | AE92: =Z92+AD92 -> 0.39583333 | AG92: =AB92+AC92 -> 3 | AH92: Time data looks wrong to me
B93: 119 | C93: 29 mins | D93: 24° | E93: 200°/110° | F93: 27 | G93: 10.8 | H93: Enphase | I93: Roof Mount | J93: Yes | L93: Truss | M93: No | N93: No | O93: A1 | P93: 71.7 | Q93: 40 | R93: 45 | S93: 3 | T93: 0 | U93: Asphalt Shingles | V93: Flashfoot 2 | W93: Portrait | X93: 2 | Y93: Summer | Z93: 1.5173611 | AA93: 2 | AB93: 2 | AC93: 2 | AD93: =IFERROR(Z93/(AA93*AB93)*AC93*AA93,"") -> 1.5173611 | AE93: =Z93+AD93 -> 3.0347222 | AG93: =AB93+AC93 -> 4
B94: 160 | C94: 31 mins | D94: 24° | E94: 120°/210° | F94: 37 | G94: 13.69 | H94: Enphase | I94: Roof Mount | J94: No | K94: Yes | L94: Truss | M94: No | N94: No | O94: B1 | P94: 69.4 | Q94: 40.8 | R94: 43 | S94: 5 | T94: 0 | U94: Asphalt Shingles | V94: Flashfoot 2 | W94: Portrait | X94: 2 | Y94: Spring | Z94: 2 | AA94: 3 | AB94: 3 | AC94: 1 | AD94: =IFERROR(Z94/(AA94*AB94)*AC94*AA94,"") -> 0.66666667 | AE94: =Z94+AD94 -> 2.6666667 | AG94: =AB94+AC94 -> 4 | AH94: Data from here onwards is much more accurate
B95: 161 | C95: 31 mins | D95: 30° | E95: 180° | F95: 14 | G95: 5.6 | H95: Enphase | I95: Roof Mount | J95: Yes | K95: No | L95: Rafter | M95: Yes | N95: No | O95: B2 | P95: 71.7 | Q95: 40 | R95: 45 | S95: 1 | T95: 1 | U95: Asphalt Shingles | V95: Flashfoot 2 | W95: Portrait | X95: 1 | Y95: Winter | Z95: 0.61458333 | AA95: 2 | AB95: 2 | AC95: 1 | AD95: =IFERROR(Z95/(AA95*AB95)*AC95*AA95,"") -> 0.30729167 | AE95: =Z95+AD95 -> 0.921875 | AG95: =AB95+AC95 -> 3
B96: 162 | C96: 22 mins | D96: 25° | E96: 180° | F96: 21 | G96: 8.4 | H96: Enphase | I96: Roof Mount | J96: Yes | K96: Yes | L96: Truss | M96: No | N96: No | O96: A4 | P96: 71.7 | Q96: 40 | R96: 45 | S96: 2 | T96: 0 | U96: Asphalt Shingles | V96: Flashfoot 2 | W96: Portrait | X96: 2 | Y96: Spring | Z96: 1.5104167 | AA96: 2 | AB96: 2 | AC96: 0 | AD96: =IFERROR(Z96/(AA96*AB96)*AC96*AA96,"") -> 0 | AE96: =Z96+AD96 -> 1.5104167 | AG96: =AB96+AC96 -> 2
B97: 163 | C97: 23 mins | D97: 22° | E97: 180° | F97: 18 | G97: 7.2 | H97: Enphase | I97: Roof Mount | J97: Yes | K97: Yes | L97: Rafter | M97: Yes | N97: No | O97: B1 | P97: 71.7 | Q97: 40 | R97: 45 | S97: 1 | T97: 23 | U97: Asphalt Shingles | V97: Flashfoot 2 | W97: Portrait | X97: 1 | Y97: Winter | Z97: 3.2777778 | AA97: 4 | AB97: 3 | AC97: 1 | AD97: =IFERROR(Z97/(AA97*AB97)*AC97*AA97,"") -> 1.0925926 | AE97: =Z97+AD97 -> 4.3703704 | AG97: =AB97+AC97 -> 4
B98: 164 | C98: 36 mins | D98: 30° | E98: 270° | F98: 18 | G98: 8.1 | H98: SolarEdge | I98: Roof Mount | J98: Yes | K98: No | L98: Rafter | M98: No | N98: No | O98: A* | P98: 82.79 | Q98: 40.94 | R98: 55.12 | S98: 4 | T98: 0 | U98: Asphalt Shingles | V98: Flashfoot 2 | W98: Portrait | X98: 1 | Y98: Spring | Z98: 1.8541667 | AA98: 3 | AB98: 3 | AC98: 0 | AD98: =IFERROR(Z98/(AA98*AB98)*AC98*AA98,"") -> 0 | AE98: =Z98+AD98 -> 1.8541667 | AG98: =AB98+AC98 -> 3
B99: 165 | C99: 31 mins | D99: 40° | E99: 170° | F99: 26 | G99: 10.4 | H99: Enphase | I99: Roof Mount | J99: Yes | K99: Yes | L99: Truss | M99: No | N99: No | O99: A1 | P99: 71.7 | Q99: 40 | R99: 45 | S99: 3 | T99: 0 | U99: Asphalt Shingles | V99: Flashfoot 2 | W99: Portrait | X99: 2 | Y99: Fall | Z99: 2.8958333 | AA99: 2 | AB99: 4 | AC99: 0 | AD99: =IFERROR(Z99/(AA99*AB99)*AC99*AA99,"") -> 0 | AE99: =Z99+AD99 -> 2.8958333 | AG99: =AB99+AC99 -> 4 | AH99: New construction
B100: 166 | C100: 30 mins | D100: 26°/40° | E100: 260°/170° | F100: 24 | G100: 9.36 | H100: SolarEdge | I100: Roof Mount | J100: Yes | K100: No | L100: Truss | M100: No | N100: No | O100: A1 | P100: 69.06 | Q100: 43.15 | R100: 46.3 | S100: 3 | T100: 0 | U100: Asphalt Shingles | V100: Flashfoot 2 | W100: Portrait | X100: 2 | Y100: Spring | Z100: 3.5 | AA100: 5 | AB100: 4 | AC100: 0 | AD100: =IFERROR(Z100/(AA100*AB100)*AC100*AA100,"") -> 0 | AE100: =Z100+AD100 -> 3.5 | AG100: =AB100+AC100 -> 4 | AH100: New construction - lots of trips
B101: 167 | C101: 24 mins | D101: 26° | E101: 190° | F101: 17 | G101: 6.63 | H101: SolarEdge | I101: Roof Mount | J101: No | K101: No | L101: Truss | M101: No | N101: No | O101: A1 | P101: 69.06 | Q101: 43.15 | R101: 46.3 | S101: 1 | T101: 0 | U101: Asphalt Shingles | V101: Flashfoot 2 | W101: Portrait | X101: 2 | Y101: Spring | Z101: 2.1944444 | AA101: 3 | AB101: 3 | AC101: 0 | AD101: =IFERROR(Z101/(AA101*AB101)*AC101*AA101,"") -> 0 | AE101: =Z101+AD101 -> 2.1944444 | AG101: =AB101+AC101 -> 3
B102: 168 | C102: 16 mins | D102: 34° | E102: 205° | F102: 15 | G102: 5.85 | H102: SolarEdge | I102: Roof Mount | J102: No | K102: No | L102: Truss | M102: No | N102: No | O102: A4 | P102: 69.06 | Q102: 43.15 | R102: 46.3 | S102: 2 | T102: 0 | U102: Asphalt Shingles | V102: Flashfoot 2 | W102: Portrait | X102: 1 | Y102: Spring | Z102: 0.88541667 | AA102: 1 | AB102: 2 | AC102: 0 | AD102: =IFERROR(Z102/(AA102*AB102)*AC102*AA102,"") -> 0 | AE102: =Z102+AD102 -> 0.88541667 | AG102: =AB102+AC102 -> 2
B103: 169 | C103: 32 mins | D103: 26° | E103: 90° | F103: 26 | G103: 10.4 | H103: Enphase | I103: Roof Mount | J103: Yes | K103: Yes | L103: Truss | M103: No | N103: No | O103: A1 | P103: 71.7 | Q103: 40 | R103: 45 | S103: 2 | T103: 0 | U103: Asphalt Shingles | V103: Flashfoot 2 | W103: Portrait | X103: 2 | Y103: Winter | Z103: 2.3541667 | AA103: 2 | AB103: 3 | AC103: 1 | AD103: =IFERROR(Z103/(AA103*AB103)*AC103*AA103,"") -> 0.78472222 | AE103: =Z103+AD103 -> 3.1388889 | AG103: =AB103+AC103 -> 4
B104: 170 | C104: 14 mins | D104: 26° | E104: 200° | F104: 20 | G104: 8 | H104: Enphase | I104: Roof Mount | J104: Yes | K104: Yes | L104: Truss | M104: No | N104: No | O104: A1 | P104: 71.7 | Q104: 40 | R104: 45 | S104: 2 | T104: 0 | U104: Asphalt Shingles | V104: Flashfoot 2 | W104: Portrait | X104: 2 | Y104: Winter | Z104: 1.8888889 | AA104: 3 | AB104: 3 | AC104: 0 | AD104: =IFERROR(Z104/(AA104*AB104)*AC104*AA104,"") -> 0 | AE104: =Z104+AD104 -> 1.8888889 | AG104: =AB104+AC104 -> 3
B105: 171 | C105: 37 mins | D105: 30° | E105: 180° | F105: 20 | G105: 9.7 | H105: SMA | I105: Ground Mount | J105: No | K105: No | L105: Grount Mount | M105: No | N105: No | O105: A* | P105: 87.2 | Q105: 41.1 | R105: 64.2 | S105: 1 | T105: 0 | U105: Ground Mount | V105: Ground Mount | W105: Landscape | X105: 0 | Y105: Spring | Z105: 3.4881944 | AA105: 2 | AB105: 4 | AC105: 0 | AD105: =IFERROR(Z105/(AA105*AB105)*AC105*AA105,"") -> 0 | AE105: =Z105+AD105 -> 3.4881944 | AG105: =AB105+AC105 -> 4
B106: 172 | C106: 19 mins | D106: 19° | E106: 180° | F106: 16 | G106: 6.4 | H106: Enphase | I106: Roof Mount | J106: Yes | K106: No | L106: Rafter | M106: No | N106: No | O106: A1 | P106: 71.7 | Q106: 40 | R106: 45 | S106: 1 | T106: 0 | U106: Asphalt Shingles | V106: Flashfoot 2 | W106: Portrait | X106: 2 | Y106: Summer | Z106: 1.3159722 | AA106: 1 | AB106: 4 | AC106: 0 | AD106: =IFERROR(Z106/(AA106*AB106)*AC106*AA106,"") -> 0 | AE106: =Z106+AD106 -> 1.3159722 | AG106: =AB106+AC106 -> 4
B107: 173 | C107: 56 mins | D107: 30° | E107: 180° | F107: 48 | G107: 19.2 | H107: SMA | I107: Ground Mount | J107: No | K107: No | L107: Grount Mount | M107: No | N107: No | O107: C* | P107: 74 | Q107: 41.1 | R107: 48.5 | S107: 2 | T107: 0 | U107: Ground Mount | V107: Ground Mount | W107: Portrait | X107: 0 | Y107: Spring | Z107: 5.8791667 | AA107: 4 | AB107: 4 | AC107: 2 | AD107: =IFERROR(Z107/(AA107*AB107)*AC107*AA107,"") -> 2.9395833 | AE107: =Z107+AD107 -> 8.81875 | AG107: =AB107+AC107 -> 6
B108: 174 | C108: 36 mins | D108: 30° | E108: 180° | F108: 9 | G108: 4.365 | H108: SolarEdge | I108: Ground Mount | J108: No | K108: No | L108: Grount Mount | M108: No | N108: No | O108: A1 | P108: 87.2 | Q108: 41.1 | R108: 64.2 | S108: 1 | T108: 0 | U108: Ground Mount | V108: Ground Mount | W108: Landscape | X108: 0 | Y108: Spring | Z108: 4.4895833 | AA108: 3 | AB108: 4 | AC108: 0 | AD108: =IFERROR(Z108/(AA108*AB108)*AC108*AA108,"") -> 0 | AE108: =Z108+AD108 -> 4.4895833 | AG108: =AB108+AC108 -> 4
B109: 175 | C109: 43 mins | D109: 30° | E109: 190° | F109: 9 | G109: 3.6 | H109: SolarEdge | I109: Roof Mount | J109: Yes | K109: No | L109: Truss | M109: No | N109: No | O109: C* | P109: 71.7 | Q109: 40 | R109: 45 | S109: 1 | T109: 0 | U109: Asphalt Shingles | V109: Flashfoot 2 | W109: Portrait | X109: 1 | Y109: Spring | Z109: 1.1875 | AA109: 1 | AB109: 3 | AC109: 0 | AD109: =IFERROR(Z109/(AA109*AB109)*AC109*AA109,"") -> 0 | AE109: =Z109+AD109 -> 1.1875 | AG109: =AB109+AC109 -> 3
B110: 176 | C110: 42 mins | D110: 26 | E110: 240°/60° | F110: 50 | G110: 24.25 | H110: SolarEdge | I110: Roof Mount | J110: Yes | K110: No | L110: Truss | M110: No | N110: No | O110: A* | P110: 87.2 | Q110: 41.1 | R110: 64.2 | S110: 2 | T110: 0 | U110: Asphalt Shingles | V110: RT Mini | W110: Portrait | X110: 1 | Y110: Fall | Z110: 5.3541667 | AA110: 5 | AB110: 5 | AC110: 2 | AD110: =IFERROR(Z110/(AA110*AB110)*AC110*AA110,"") -> 2.1416667 | AE110: =Z110+AD110 -> 7.4958333 | AG110: =AB110+AC110 -> 7 | AH110: This is the time for both this project and the one below combined
B111: 178 | C111: 44 mins | D111: 40° | E111: 180° | F111: 23 | G111: 8.97 | H111: Enphase | I111: Roof Mount | J111: Yes | K111: No | L111: Truss | M111: No | N111: No | O111: A1 | P111: 69.06 | Q111: 43.15 | R111: 46.3 | S111: 1 | T111: 0 | U111: Asphalt Shingles | V111: Flashfoot 2 | W111: Portrait | X111: 1 | Y111: Spring | Z111: 1.3020833 | AA111: 1 | AB111: 3 | AC111: 0 | AD111: =IFERROR(Z111/(AA111*AB111)*AC111*AA111,"") -> 0 | AE111: =Z111+AD111 -> 1.3020833 | AG111: =AB111+AC111 -> 3
B112: 179 | C112: 7 mins | D112: 14° | E112: 260° | F112: 36 | G112: 14.4 | H112: Enphase | I112: Roof Mount | J112: Yes | K112: Yes | L112: Truss | M112: No | N112: Yes | O112: B2 | P112: 71.7 | Q112: 40 | R112: 45 | S112: 2 | T112: 0 | U112: Asphalt Shingles | V112: Flashfoot 2 | W112: Portrait | X112: 1 | Y112: Spring | Z112: 1.6145833 | AA112: 2 | AB112: 3 | AC112: 0 | AD112: =IFERROR(Z112/(AA112*AB112)*AC112*AA112,"") -> 0 | AE112: =Z112+AD112 -> 1.6145833 | AG112: =AB112+AC112 -> 3
B113: 180 | C113: 24 mins | D113: 26° | E113: 205° | F113: 12 | G113: 4.68 | H113: SolarEdge | I113: Roof Mount | J113: Yes | K113: No | L113: Truss | M113: No | N113: Yes | O113: A1 | P113: 69.06 | Q113: 43.15 | R113: 46.3 | S113: 2 | T113: 0 | U113: Asphalt Shingles | V113: Flashfoot 2 | W113: Portrait | X113: 1 | Y113: Spring | Z113: 2.1840278 | AA113: 2 | AB113: 3 | AC113: 0 | AD113: =IFERROR(Z113/(AA113*AB113)*AC113*AA113,"") -> 0 | AE113: =Z113+AD113 -> 2.1840278 | AG113: =AB113+AC113 -> 3
B114: 181 | C114: 7 mins | D114: 30° | E114: 180° | F114: 16 | G114: 6.4 | H114: Enphase | I114: Roof Mount | J114: Yes | K114: Yes | L114: Truss | M114: No | N114: Yes | O114: A1 | P114: 71.7 | Q114: 40 | R114: 45 | S114: 1 | T114: 0 | U114: Asphalt Shingles | V114: Flashfoot 2 | W114: Portrait | X114: 1 | Y114: Spring | Z114: 1.4270833 | AA114: 1 | AB114: 5 | AC114: 0 | AD114: =IFERROR(Z114/(AA114*AB114)*AC114*AA114,"") -> 0 | AE114: =Z114+AD114 -> 1.4270833 | AG114: =AB114+AC114 -> 5
B115: 182 | C115: 58 mins | D115: 40° | E115: 165° | F115: 46 | G115: 18.4 | H115: Enphase | I115: Roof Mount | J115: Yes | K115: Yes | L115: Truss | M115: No | N115: No | O115: A1 | P115: 71.7 | Q115: 40 | R115: 45 | S115: 4 | T115: 0 | U115: Asphalt Shingles | V115: Flashfoot 2 | W115: Portrait | X115: 2 | Y115: Spring | Z115: 3.8159722 | AA115: 3 | AB115: 5 | AC115: 1 | AD115: =IFERROR(Z115/(AA115*AB115)*AC115*AA115,"") -> 0.76319444 | AE115: =Z115+AD115 -> 4.5791667 | AG115: =AB115+AC115 -> 6
...

Sheet Technical Analysis
C2: Analysis of MSP Residential and Commercial Data
B3: Year | C3: 2019 | D3: 2020 | E3: 2021 | F3: 2022 | G3: 2023 | H3: 2024 | I3: 2025 | J3: 2025 Estimated Full Year Info Based on Data | K3: 2025 Estimated Full Year of Info Based on Business Plan
B4: # of Installs | C4: 55 | D4: 62 | E4: 81 | F4: 86 | G4: 84 | H4: 119 | I4: #REF!
B5: kW Installed | C5: 480 | D5: 650 | E5: 670 | F5: 828 | G5: 947 | H5: 1249 | I5: #REF!
B6: Install Revenue | C6: 1400000 | D6: 1675000 | E6: 1810000 | F6: 2339533 | G6: 2668936 | H6: 3266869 | I6: #REF!
B7: Est. CoGs | C7: - | D7: - | E7: - | F7: - | G7: 1681254 | H7: 2062602 | I7: #REF!
B8: Est. Margin $ | C8: - | D8: - | E8: - | F8: - | G8: 984551 | H8: 1221323 | I8: #REF!
B9: Estimated Direct Labor Costs | G9: 185660 | H9: 267683 | I9: #REF!
B10: Estimated EC Cost | C10: - | D10: - | E10: - | F10: - | G10: 154200 | H10: 204936 | I10: #REF!
B11: Actual EC Cost | C11: - | D11: - | E11: - | F11: - | G11: 113558 | H11: 85130 | I11: #REF!
B12: Average System Price | C12: - | D12: - | E12: 22353 | F12: 27203 | G12: 31773 | H12: 27685 | I12: #DIV/0!
B13: Median System Price | D13: - | E13: 19206 | F13: 24305 | G13: 26342 | H13: 21978 | I13: #REF!
B14: Average kW/Install | C14: - | D14: - | E14: 8.3 | F14: 8.76 | G14: 11.28 | H14: 10.5 | I14: =I5/I4 -> #REF!
B15: Median kW/Install | C15: - | D15: - | E15: 6.6 | F15: 7.79 | G15: 8.3 | H15: 7.82 | I15: #REF!
B16: Average $/W | C16: 2.93 | D16: 2.61 | E16: 2.7 | F16: 2.83 | G16: 2.82 | H16: 2.62 | I16: =I6/(I5*1000) -> #REF!
B17: Median $/W | C17: - | D17: - | E17: 2.84 | F17: 2.98 | G17: 3.01 | H17: 2.83 | I17: #REF!
B18: # of People | C18: 5 | D18: 8 | E18: 9 | F18: 10 | G18: 12 | H18: 14 | I18: 15
B20: Utility Breakdown - Count
B21: MGE | C21: - | D21: - | E21: 40 | F21: 28 | G21: 24 | H21: 46 | I21: #REF!
B22: Alliant | C22: - | D22: - | E22: 23 | F22: 50 | G22: 46 | H22: 55 | I22: #REF!
B23: WE Energies | C23: - | D23: - | E23: 6 | F23: 1 | G23: 2 | H23: 2 | I23: #REF!
B24: Other | C24: - | D24: - | E24: 10 | F24: 7 | G24: 12 | H24: 10 | I24: #REF!
B26: Utility Breakdown - Percent
B27: MGE | C27: - | D27: - | E27: =E21/E$4 -> 0.49382716 | F27: =F21/F$4 -> 0.3255814 | G27: 0.286 | H27: 0.365 | I27: =I21/$I$4 -> #VALUE!
B28: Alliant | C28: - | D28: - | E28: =E22/E$4 -> 0.28395062 | F28: =F22/F$4 -> 0.58139535 | G28: 0.548 | H28: 0.437 | I28: =I22/$I$4 -> #VALUE!
B29: WE Energies | C29: - | D29: - | E29: =E23/E$4 -> 0.074074074 | F29: =F23/F$4 -> 0.011627907 | G29: 0.024 | H29: 0.016 | I29: =I23/$I$4 -> #VALUE!
B30: Other | C30: - | D30: - | E30: =E24/E$4 -> 0.12345679 | F30: =F24/F$4 -> 0.081395349 | G30: 0.143 | H30: 0.079 | I30: =I24/$I$4 -> #REF!
B32: Inverter Manufacturer - Count
B33: Enphase | C33: - | D33: - | E33: 37 | F33: 43 | G33: 63 | H33: 106 | I33: #VALUE!
B34: SolarEdge | C34: - | D34: - | E34: 41 | F34: 41 | G34: 16 | H34: 5 | I34: #VALUE!
B35: SMA | C35: - | D35: - | E35: 2 | F35: 2 | G35: 4 | H35: 1 | I35: #VALUE!
B36: Other | C36: - | D36: - | E36: 1 | F36: 0 | G36: 1 | H36: 4 | I36: #VALUE!
B38: Inverter Manufacturer - Percent
B39: Enphase | C39: - | D39: - | E39: =E33/E$4 -> 0.45679012 | F39: =F33/F$4 -> 0.5 | G39: 0.75 | H39: 0.841 | I39: =I33/$I$4 -> #VALUE!
B40: SolarEdge | C40: - | D40: - | E40: =E34/E$4 -> 0.50617284 | F40: =F34/F$4 -> 0.47674419 | G40: 0.19 | H40: 0.04 | I40: =I34/$I$4 -> #VALUE!
B41: SMA | C41: - | D41: - | E41: =E35/E$4 -> 0.024691358 | F41: =F35/F$4 -> 0.023255814 | G41: 0.048 | H41: 0.008 | I41: =I35/$I$4 -> #VALUE!
B42: Other | C42: - | D42: - | E42: =E36/E$4 -> 0.012345679 | F42: =F36/F$4 -> 0 | G42: 0.012 | H42: 0.032 | I42: =I36/$I$4 -> #VALUE!
B44: Panel Manufacturer - Count
B45: REC | C45: - | D45: - | E45: 19 | F45: 30 | G45: 51 | H45: 98 | I45: #REF!
B46: Silfab | C46: - | D46: - | E46: 32 | F46: 19 | G46: 4 | H46: 0 | I46: #REF!
B47: Aptos Solar | C47: - | D47: - | E47: 0 | F47: 12 | G47: 0 | H47: 0 | I47: #REF!
B48: Q-Cell | C48: - | D48: - | E48: 10 | F48: 9 | G48: 8 | H48: 3 | I48: #REF!
B49: Phono Solar | C49: - | D49: - | E49: 3 | F49: 9 | G49: 1 | H49: 0 | I49: #REF!
B50: Trina Solar | C50: - | D50: - | E50: 3 | F50: 2 | G50: 15 | H50: 6 | I50: #REF!
B51: Other | C51: - | D51: - | E51: 14 | F51: 5 | G51: 5 | H51: 12 | I51: #REF!
B53: Panel Manufacturer - Percentage
B54: REC | C54: - | D54: - | E54: =E45/E$4 -> 0.2345679 | F54: =F45/F$4 -> 0.34883721 | G54: 0.607 | H54: 0.778 | I54: =I45/$I$4 -> #VALUE!
B55: Silfab | C55: - | D55: - | E55: =E46/E$4 -> 0.39506173 | F55: =F46/F$4 -> 0.22093023 | G55: 0.048 | H55: 0 | I55: =I46/$I$4 -> #VALUE!
B56: Aptos Solar | C56: - | D56: - | E56: =E47/E$4 -> 0 | F56: =F47/F$4 -> 0.13953488 | G56: 0 | H56: 0 | I56: =I47/$I$4 -> #VALUE!
B57: Q-Cell | C57: - | D57: - | E57: =E48/E$4 -> 0.12345679 | F57: =F48/F$4 -> 0.10465116 | G57: 0.095 | H57: 0.024 | I57: =I48/$I$4 -> #VALUE!
B58: Phono Solar | C58: - | D58: - | E58: =E49/E$4 -> 0.037037037 | F58: =F49/F$4 -> 0.10465116 | G58: 0.012 | H58: 0 | I58: =I49/$I$4 -> #VALUE!
B59: Trina Solar | C59: - | D59: - | E59: =E50/E$4 -> 0.037037037 | F59: =F50/F$4 -> 0.023255814 | G59: 0.179 | H59: 0.048 | I59: =I50/$I$4 -> #VALUE!
B60: Other | C60: - | D60: - | E60: =E51/E$4 -> 0.17283951 | F60: =F51/F$4 -> 0.058139535 | G60: 0.06 | H60: 0.095 | I60: =I51/$I$4 -> #REF!
B62: System Size (kW)
B63: 0-2 | C63: - | D63: - | E63: 1 | F63: 1 | G63: 1 | H63: 0 | I63: #VALUE!
B64: 44961 | C64: - | D64: - | E64: 5 | F64: 6 | G64: 5 | H64: 7 | I64: #VALUE!
B65: 45022 | C65: - | D65: - | E65: 29 | F65: 16 | G65: 12 | H65: 31 | I65: #VALUE!
B66: 45085 | C66: - | D66: - | E66: 21 | F66: 21 | G66: 19 | H66: 25 | I66: #VALUE!
B67: 45148 | C67: - | D67: - | E67: 5 | F67: 21 | G67: 16 | H67: 17 | I67: #VALUE!
B68: 44846 | C68: - | D68: - | E68: 7 | F68: 9 | G68: 12 | H68: 16 | I68: #VALUE!
B69: 44910 | C69: - | D69: - | E69: 4 | F69: 3 | G69: 7 | H69: 8 | I69: #VALUE!
B70: 15-20 | C70: - | D70: - | E70: 5 | F70: 4 | G70: 5 | H70: 9 | I70: #VALUE!
B71: 20-50 | C71: - | D71: - | E71: 4 | F71: 4 | G71: 5 | H71: 4 | I71: #VALUE!
B72: >50 | C72: - | D72: - | E72: 0 | F72: 1 | G72: 2 | H72: 2 | I72: #VALUE!
B74: System Size - Percentage
B75: 0-2 | C75: - | D75: - | E75: =E63/E$4 -> 0.012345679 | F75: =F63/F$4 -> 0.011627907 | G75: 0.012 | H75: 0 | I75: =I63/$I$4 -> #VALUE!
B76: 44961 | C76: - | D76: - | E76: =E64/E$4 -> 0.061728395 | F76: =F64/F$4 -> 0.069767442 | G76: 0.06 | H76: 0.056 | I76: =I64/$I$4 -> #VALUE!
B77: 45022 | C77: - | D77: - | E77: =E65/E$4 -> 0.35802469 | F77: =F65/F$4 -> 0.18604651 | G77: 0.143 | H77: 0.246 | I77: =I65/$I$4 -> #VALUE!
B78: 45085 | C78: - | D78: - | E78: =E66/E$4 -> 0.25925926 | F78: =F66/F$4 -> 0.24418605 | G78: 0.226 | H78: 0.198 | I78: =I66/$I$4 -> #VALUE!
B79: 45148 | C79: - | D79: - | E79: =E67/E$4 -> 0.061728395 | F79: =F67/F$4 -> 0.24418605 | G79: 0.19 | H79: 0.135 | I79: =I67/$I$4 -> #VALUE!
B80: 44846 | C80: - | D80: - | E80: =E68/E$4 -> 0.086419753 | F80: =F68/F$4 -> 0.10465116 | G80: 0.143 | H80: 0.127 | I80: =I68/$I$4 -> #VALUE!
B81: 44910 | C81: - | D81: - | E81: =E69/E$4 -> 0.049382716 | F81: =F69/F$4 -> 0.034883721 | G81: 0.083 | H81: 0.063 | I81: =I69/$I$4 -> #VALUE!
B82: 15-20 | C82: - | D82: - | E82: =E70/E$4 -> 0.061728395 | F82: =F70/F$4 -> 0.046511628 | G82: 0.06 | H82: 0.071 | I82: =I70/$I$4 -> #VALUE!
B83: 20-50 | C83: - | D83: - | E83: =E71/E$4 -> 0.049382716 | F83: =F71/F$4 -> 0.046511628 | G83: 0.06 | H83: 0.032 | I83: =I71/$I$4 -> #VALUE!
B84: >50 | C84: - | D84: - | E84: =E72/E$4 -> 0 | F84: =F72/F$4 -> 0.011627907 | G84: 0.024 | H84: 0.016 | I84: =I72/$I$4 -> #VALUE!
B86: Contract Value - Count
B87: $0 - $10,000 | C87: - | D87: - | E87: 1 | F87: 2 | G87: 1 | H87: 0 | I87: #REF!
B88: $10,001 - $15,000 | C88: - | D88: - | E88: 18 | F88: 7 | G88: 10 | H88: 29 | I88: #REF!
B89: $15,001 - $20,000 | C89: - | D89: - | E89: 25 | F89: 16 | G89: 6 | H89: 18 | I89: #REF!
B90: $20,001 - $25,000 | C90: - | D90: - | E90: 18 | F90: 24 | G90: 22 | H90: 25 | I90: #REF!
B91: $25,001 - $30,000 | C91: - | D91: - | E91: 4 | F91: 18 | G91: 21 | H91: 20 | I91: #REF!
B92: $30,001 - $35,000 | C92: - | D92: - | E92: 7 | F92: 7 | G92: 7 | H92: 5 | I92: #REF!
B93: $35,001 - $40,000 | C93: - | D93: - | E93: 2 | F93: 2 | G93: 3 | H93: 9 | I93: #REF!
B94: $40,001 - $45,000 | C94: - | D94: - | E94: 2 | F94: 4 | G94: 5 | H94: 4 | I94: #REF!
B95: $45,001 - $50,000 | C95: - | D95: - | E95: 2 | F95: 2 | G95: 0 | H95: 1 | I95: #REF!
B96: Above $50,000 | C96: - | D96: - | E96: 2 | F96: 4 | G96: 9 | H96: 7 | I96: #REF!
B98: Contract Value - Percent
B99: $0 - $10,000 | C99: - | D99: - | E99: =E87/E$4 -> 0.012345679 | F99: =F87/F$4 -> 0.023255814 | G99: 0.012 | H99: 0 | I99: =I87/$I$4 -> #REF!
B100: $10,001 - $15,000 | C100: - | D100: - | E100: =E88/E$4 -> 0.22222222 | F100: =F88/F$4 -> 0.081395349 | G100: 0.119 | H100: 0.23 | I100: =I88/$I$4 -> #REF!
B101: $15,001 - $20,000 | C101: - | D101: - | E101: =E89/E$4 -> 0.30864198 | F101: =F89/F$4 -> 0.18604651 | G101: 0.071 | H101: 0.143 | I101: =I89/$I$4 -> #REF!
B102: $20,001 - $25,000 | C102: - | D102: - | E102: =E90/E$4 -> 0.22222222 | F102: =F90/F$4 -> 0.27906977 | G102: 0.262 | H102: 0.198 | I102: =I90/$I$4 -> #REF!
B103: $25,001 - $30,000 | C103: - | D103: - | E103: =E91/E$4 -> 0.049382716 | F103: =F91/F$4 -> 0.20930233 | G103: 0.25 | H103: 0.159 | I103: =I91/$I$4 -> #REF!
B104: $30,001 - $35,000 | C104: - | D104: - | E104: =E92/E$4 -> 0.086419753 | F104: =F92/F$4 -> 0.081395349 | G104: 0.083 | H104: 0.04 | I104: =I92/$I$4 -> #REF!
B105: $35,001 - $40,000 | C105: - | D105: - | E105: =E93/E$4 -> 0.024691358 | F105: =F93/F$4 -> 0.023255814 | G105: 0.036 | H105: 0.071 | I105: =I93/$I$4 -> #REF!
B106: $40,001 - $45,000 | C106: - | D106: - | E106: =E94/E$4 -> 0.024691358 | F106: =F94/F$4 -> 0.046511628 | G106: 0.06 | H106: 0.032 | I106: =I94/$I$4 -> #REF!
B107: $45,001 - $50,000 | C107: - | D107: - | E107: =E95/E$4 -> 0.024691358 | F107: =F95/F$4 -> 0.023255814 | G107: 0 | H107: 0.008 | I107: =I95/$I$4 -> #REF!
B108: Above $50,000 | C108: - | D108: - | E108: =E96/E$4 -> 0.024691358 | F108: =F96/F$4 -> 0.046511628 | G108: 0.107 | H108: 0.056 | I108: =I96/$I$4 -> #REF!
B110: Interconnection Type - Count
B111: A1 | C111: - | D111: - | E111: - | F111: 42 | G111: 46 | H111: 76 | I111: #VALUE!
B112: A2 | C112: - | D112: - | E112: - | F112: 11 | G112: 4 | H112: 3 | I112: #VALUE!
...

Sheet CORE METRICS +
H2: OVERALL - RESIDENTIAL + COMMERCIAL
H3: Budgetted Bookings | K3: Actual Bookings (non service) | N3: Permits | S3: Utility Applications | X3: Budgetted Install Schedule | AA3: Planned Installs at Contract Signing (non service) | AD3: Actual Installations (non service) | AH3: Budgeted Bookings vs Actual Bookings | AL3: Budgeted Installs vs Actual Installs | AP3: Planned Installs at Contract vs Actual Install
F4: Month | G4: Derived Booking Value percentage per Month | H4: QTY Booked | I4: kW Booked | J4: Contract Value of Booked Systems | K4: QTY Booked | L4: kW Booked | M4: Contract Value of Booked Systems | N4: Permits Submitted | O4: Permits Approved | P4: Jobs with Unsubmitted Permits | Q4: Outstanding Submitted Permits MTD or at Months End | R4: Total Approved But Uninstalled Permits MTD or at Month End | S4: Utility Applications Submitted | T4: Utility Applications Approved | U4: Jobs with Unsubmitted Utility Applications | V4: Outstanding Submitted Utility Applications MTD or at Months End | W4: Total Approved but Uninstalled Utility Applications MTD or at Months End | X4: QTY Installed | Y4: kW Installed | Z4: Contract Value of Installed Systems | AA4: QTY Installed | AB4: kW Installed | AC4: Contract Value of Installed Systems | AD4: QTY Installed | AE4: kW Installed | AF4: Contract Value of Installed Systems | AH4: QTY Booked | AI4: kW Booked | AJ4: Contract Value of Booked Systems | AL4: QTY Installed | AM4: kW Installed | AN4: Contract Value of Installed Systems | AP4: QTY Installed | AQ4: kW Installed | AR4: Contract Value of Installed Systems
B5: >=1/1/23 | C5: <1/1/24 | D5: 0 | E5: =CONCATENATE(LEFT(B5,FIND(">=",B5) + 1),RIGHT(C5,LEN(C5) - (FIND("<",C5)))) -> >=1/1/24 | F5: 2023 | G5: N/A | K5: =COUNTIFS(#REF!,$B5,#REF!,$C5) -> #REF! | L5: =SUMIFS(#REF!,#REF!,$B5,#REF!,$C5) -> #REF! | M5: =SUMIFS(#REF!,#REF!,$B5,#REF!,$C5) -> #REF! | N5: =COUNTIFS(#REF!,$B5,#REF!,$C5) -> #REF! | O5: =COUNTIFS(#REF!,$B5,#REF!,$C5) -> #REF! | P5: =IF(MONTH(TODAY())>=$D5,COUNTIFS(#REF!,$C5)-COUNTIFS(#REF!,$C5),"") -> #REF! | Q5: 0 | R5: =IF(MONTH(TODAY())>=$D5,COUNTIFS(#REF!,$C5)-COUNTIFS(#REF!,$C5),"") -> #REF! | S5: =COUNTIFS(#REF!,$B5,#REF!,$C5) -> #REF! | T5: =COUNTIFS(#REF!,$B5,#REF!,$C5) -> #REF! | U5: =IF(MONTH(TODAY())>=$D5,COUNTIFS(#REF!,$C5)-COUNTIFS(#REF!,$C5),"") -> #REF! | V5: 0 | W5: =IF(MONTH(TODAY())>=$D5,COUNTIFS(#REF!,$C5)-COUNTIFS(#REF!,$C5),"") -> #REF! | AA5: =COUNTIFS(#REF!,$B5,#REF!,$C5) -> #REF! | AB5: =SUMIFS(#REF!,#REF!,$B5,#REF!,$C5) -> #REF! | AC5: =SUMIFS(#REF!,#REF!,$B5,#REF!,$C5) -> #REF! | AP5: =IF(MONTH(TODAY())>=$D5,AD5-AA5,"") -> #REF! | AQ5: =IF(MONTH(TODAY())>=$D5,AE5-AB5,"") -> #REF! | AR5: =IF(MONTH(TODAY())>=$D5,AF5-AC5,"") -> #REF!
B6: >=1/1/24 | C6: <2/1/24 | D6: 1 | E6: =CONCATENATE(LEFT(B6,FIND(">=",B6) + 1),RIGHT(C6,LEN(C6) - (FIND("<",C6)))) -> >=2/1/24 | F6: January | G6: =J6/$J$19 -> 0.0603 | H6: =H55+H95 -> 6 | I6: =I55+I95 -> 101.65917 | J6: 211050 | K6: =COUNTIFS(#REF!,$B6,#REF!,$C6) -> #REF! | L6: =SUMIFS(#REF!,#REF!,$B6,#REF!,$C6) -> #REF! | M6: =SUMIFS(#REF!,#REF!,$B6,#REF!,$C6) -> #REF! | N6: =COUNTIFS(#REF!,$B6,#REF!,$C6) -> #REF! | O6: =COUNTIFS(#REF!,$B6,#REF!,$C6) -> #REF! | P6: =IF(MONTH(TODAY())>=$D6,COUNTIFS(#REF!,$C6)-COUNTIFS(#REF!,$C6),"") -> #REF! | Q6: 0 | R6: =IF(MONTH(TODAY())>=$D6,COUNTIFS(#REF!,$C6)-COUNTIFS(#REF!,$C6),"") -> #REF! | S6: =COUNTIFS(#REF!,$B6,#REF!,$C6) -> #REF! | T6: =COUNTIFS(#REF!,$B6,#REF!,$C6) -> #REF! | U6: =IF(MONTH(TODAY())>=$D6,COUNTIFS(#REF!,$C6)-COUNTIFS(#REF!,$C6),"") -> #REF! | V6: 0 | W6: =IF(MONTH(TODAY())>=$D6,COUNTIFS(#REF!,$C6)-COUNTIFS(#REF!,$C6),"") -> #REF! | X6: 4 | Y6: =Y55+Y95 -> 40 | Z6: =Z55+Z95 -> 111072.42 | AA6: =COUNTIFS(#REF!,$B6,#REF!,$C6) -> #REF! | AB6: =SUMIFS(#REF!,#REF!,$B6,#REF!,$C6) -> #REF! | AC6: =SUMIFS(#REF!,#REF!,$B6,#REF!,$C6) -> #REF! | AD6: =COUNTIFS(#REF!,$B6,#REF!,$C6) -> #REF! | AE6: =SUMIFS(#REF!,#REF!,$B6,#REF!,$C6) -> #REF! | AF6: =SUMIFS(#REF!,#REF!,$B6,#REF!,$C6) -> #REF! | AH6: =IF(MONTH(TODAY())>=$D6,K6-H6,"") -> #REF! | AI6: =IF(MONTH(TODAY())>=$D6,L6-I6,"") -> #REF! | AJ6: =IF(MONTH(TODAY())>=$D6,M6-J6,"") -> #REF! | AL6: =IF(MONTH(TODAY())>=$D6,AD6-X6,"") -> #REF! | AM6: =IF(MONTH(TODAY())>=$D6,AE6-Y6,"") -> #REF! | AN6: =IF(MONTH(TODAY())>=$D6,AF6-Z6,"") -> #REF! | AP6: =IF(MONTH(TODAY())>=$D6,AD6-AA6,"") -> #REF! | AQ6: =IF(MONTH(TODAY())>=$D6,AE6-AB6,"") -> #REF! | AR6: =IF(MONTH(TODAY())>=$D6,AF6-AC6,"") -> #REF!
B7: >=2/1/24 | C7: <3/1/24 | D7: 2 | E7: =CONCATENATE(LEFT(B7,FIND(">=",B7) + 1),RIGHT(C7,LEN(C7) - (FIND("<",C7)))) -> >=3/1/24 | F7: February | G7: =J7/$J$19 -> 0.0547 | H7: =H56+H96 -> 6 | I7: =I56+I96 -> 94.60047 | J7: 191450 | K7: =COUNTIFS(#REF!,$B7,#REF!,$C7) -> #REF! | L7: =SUMIFS(#REF!,#REF!,$B7,#REF!,$C7) -> #REF! | M7: =SUMIFS(#REF!,#REF!,$B7,#REF!,$C7) -> #REF! | N7: =COUNTIFS(#REF!,$B7,#REF!,$C7) -> #REF! | O7: =COUNTIFS(#REF!,$B7,#REF!,$C7) -> #REF! | P7: =IF(MONTH(TODAY())>=$D7,COUNTIFS(#REF!,$C7)-COUNTIFS(#REF!,$C7),"") -> #REF! | R7: =IF(MONTH(TODAY())>=$D7,COUNTIFS(#REF!,$C7)-COUNTIFS(#REF!,$C7),"") -> #REF! | S7: =COUNTIFS(#REF!,$B7,#REF!,$C7) -> #REF! | T7: =COUNTIFS(#REF!,$B7,#REF!,$C7) -> #REF! | U7: =IF(MONTH(TODAY())>=$D7,COUNTIFS(#REF!,$C7)-COUNTIFS(#REF!,$C7),"") -> #REF! | W7: =IF(MONTH(TODAY())>=$D7,COUNTIFS(#REF!,$C7)-COUNTIFS(#REF!,$C7),"") -> #REF! | X7: 2 | Y7: =Y56+Y96 -> 20 | Z7: =Z56+Z96 -> 55536.21 | AA7: =COUNTIFS(#REF!,$B7,#REF!,$C7) -> #REF! | AB7: =SUMIFS(#REF!,#REF!,$B7,#REF!,$C7) -> #REF! | AC7: =SUMIFS(#REF!,#REF!,$B7,#REF!,$C7) -> #REF! | AD7: =COUNTIFS(#REF!,$B7,#REF!,$C7) -> #REF! | AE7: =SUMIFS(#REF!,#REF!,$B7,#REF!,$C7) -> #REF! | AF7: =SUMIFS(#REF!,#REF!,$B7,#REF!,$C7) -> #REF! | AH7: =IF(MONTH(TODAY())>=$D7,K7-H7,"") -> #REF! | AI7: =IF(MONTH(TODAY())>=$D7,L7-I7,"") -> #REF! | AJ7: =IF(MONTH(TODAY())>=$D7,M7-J7,"") -> #REF! | AL7: =IF(MONTH(TODAY())>=$D7,AD7-X7,"") -> #REF! | AM7: =IF(MONTH(TODAY())>=$D7,AE7-Y7,"") -> #REF! | AN7: =IF(MONTH(TODAY())>=$D7,AF7-Z7,"") -> #REF! | AP7: =IF(MONTH(TODAY())>=$D7,AD7-AA7,"") -> #REF! | AQ7: =IF(MONTH(TODAY())>=$D7,AE7-AB7,"") -> #REF! | AR7: =IF(MONTH(TODAY())>=$D7,AF7-AC7,"") -> #REF!
B8: >=3/1/24 | C8: <4/1/24 | D8: 3 | E8: =CONCATENATE(LEFT(B8,FIND(">=",B8) + 1),RIGHT(C8,LEN(C8) - (FIND("<",C8)))) -> >=4/1/24 | F8: March | G8: =J8/$J$19 -> 0.0804 | H8: =H57+H97 -> 9 | I8: =I57+I97 -> 126.99488 | J8: 281400 | K8: =COUNTIFS(#REF!,$B8,#REF!,$C8) -> #REF! | L8: =SUMIFS(#REF!,#REF!,$B8,#REF!,$C8) -> #REF! | M8: =SUMIFS(#REF!,#REF!,$B8,#REF!,$C8) -> #REF! | N8: =COUNTIFS(#REF!,$B8,#REF!,$C8) -> #REF! | O8: =COUNTIFS(#REF!,$B8,#REF!,$C8) -> #REF! | P8: =IF(MONTH(TODAY())>=$D8,COUNTIFS(#REF!,$C8)-COUNTIFS(#REF!,$C8),"") -> #REF! | R8: =IF(MONTH(TODAY())>=$D8,COUNTIFS(#REF!,$C8)-COUNTIFS(#REF!,$C8),"") -> #REF! | S8: =COUNTIFS(#REF!,$B8,#REF!,$C8) -> #REF! | T8: =COUNTIFS(#REF!,$B8,#REF!,$C8) -> #REF! | U8: =IF(MONTH(TODAY())>=$D8,COUNTIFS(#REF!,$C8)-COUNTIFS(#REF!,$C8),"") -> #REF! | W8: =IF(MONTH(TODAY())>=$D8,COUNTIFS(#REF!,$C8)-COUNTIFS(#REF!,$C8),"") -> #REF! | X8: 7 | Y8: =Y57+Y97 -> 113.5 | Z8: =Z57+Z97 -> 238422.69 | AA8: =COUNTIFS(#REF!,$B8,#REF!,$C8) -> #REF! | AB8: =SUMIFS(#REF!,#REF!,$B8,#REF!,$C8) -> #REF! | AC8: =SUMIFS(#REF!,#REF!,$B8,#REF!,$C8) -> #REF! | AD8: =COUNTIFS(#REF!,$B8,#REF!,$C8) -> #REF! | AE8: =SUMIFS(#REF!,#REF!,$B8,#REF!,$C8) -> #REF! | AF8: =SUMIFS(#REF!,#REF!,$B8,#REF!,$C8) -> #REF! | AH8: =IF(MONTH(TODAY())>=$D8,K8-H8,"") -> #REF! | AI8: =IF(MONTH(TODAY())>=$D8,L8-I8,"") -> #REF! | AJ8: =IF(MONTH(TODAY())>=$D8,M8-J8,"") -> #REF! | AL8: =IF(MONTH(TODAY())>=$D8,AD8-X8,"") -> #REF! | AM8: =IF(MONTH(TODAY())>=$D8,AE8-Y8,"") -> #REF! | AN8: =IF(MONTH(TODAY())>=$D8,AF8-Z8,"") -> #REF! | AP8: =IF(MONTH(TODAY())>=$D8,AD8-AA8,"") -> #REF! | AQ8: =IF(MONTH(TODAY())>=$D8,AE8-AB8,"") -> #REF! | AR8: =IF(MONTH(TODAY())>=$D8,AF8-AC8,"") -> #REF!
B9: >=4/1/24 | C9: <5/1/24 | D9: 4 | E9: =CONCATENATE(LEFT(B9,FIND(">=",B9) + 1),RIGHT(C9,LEN(C9) - (FIND("<",C9)))) -> >=5/1/24 | F9: April | G9: =J9/$J$19 -> 0.1018 | H9: =H58+H98 -> 11 | I9: =I58+I98 -> 153.96921 | J9: 356300 | K9: =COUNTIFS(#REF!,$B9,#REF!,$C9) -> #REF! | L9: =SUMIFS(#REF!,#REF!,$B9,#REF!,$C9) -> #REF! | M9: =SUMIFS(#REF!,#REF!,$B9,#REF!,$C9) -> #REF! | N9: =COUNTIFS(#REF!,$B9,#REF!,$C9) -> #REF! | O9: =COUNTIFS(#REF!,$B9,#REF!,$C9) -> #REF! | P9: =IF(MONTH(TODAY())>=$D9,COUNTIFS(#REF!,$C9)-COUNTIFS(#REF!,$C9),"") | R9: =IF(MONTH(TODAY())>=$D9,COUNTIFS(#REF!,$C9)-COUNTIFS(#REF!,$C9),"") | S9: =COUNTIFS(#REF!,$B9,#REF!,$C9) -> #REF! | T9: =COUNTIFS(#REF!,$B9,#REF!,$C9) -> #REF! | U9: =IF(MONTH(TODAY())>=$D9,COUNTIFS(#REF!,$C9)-COUNTIFS(#REF!,$C9),"") | W9: =IF(MONTH(TODAY())>=$D9,COUNTIFS(#REF!,$C9)-COUNTIFS(#REF!,$C9),"") | X9: 11 | Y9: =Y58+Y98 -> 153.5 | Z9: =Z58+Z98 -> 349495.11 | AA9: =COUNTIFS(#REF!,$B9,#REF!,$C9) -> #REF! | AB9: =SUMIFS(#REF!,#REF!,$B9,#REF!,$C9) -> #REF! | AC9: =SUMIFS(#REF!,#REF!,$B9,#REF!,$C9) -> #REF! | AD9: =COUNTIFS(#REF!,$B9,#REF!,$C9) -> #REF! | AE9: =SUMIFS(#REF!,#REF!,$B9,#REF!,$C9) -> #REF! | AF9: =SUMIFS(#REF!,#REF!,$B9,#REF!,$C9) -> #REF! | AH9: =IF(MONTH(TODAY())>=$D9,K9-H9,"") | AI9: =IF(MONTH(TODAY())>=$D9,L9-I9,"") | AJ9: =IF(MONTH(TODAY())>=$D9,M9-J9,"") | AL9: =IF(MONTH(TODAY())>=$D9,AD9-X9,"") | AM9: =IF(MONTH(TODAY())>=$D9,AE9-Y9,"") | AN9: =IF(MONTH(TODAY())>=$D9,AF9-Z9,"") | AP9: =IF(MONTH(TODAY())>=$D9,AD9-AA9,"") | AQ9: =IF(MONTH(TODAY())>=$D9,AE9-AB9,"") | AR9: =IF(MONTH(TODAY())>=$D9,AF9-AC9,"")
B10: >=5/1/24 | C10: <6/1/24 | D10: 5 | E10: =CONCATENATE(LEFT(B10,FIND(">=",B10) + 1),RIGHT(C10,LEN(C10) - (FIND("<",C10)))) -> >=6/1/24 | F10: May | G10: =J10/$J$19 -> 0.1068 | H10: =H59+H99 -> 12 | I10: =I59+I99 -> 160.27162 | J10: 373800 | K10: =COUNTIFS(#REF!,$B10,#REF!,$C10) -> #REF! | L10: =SUMIFS(#REF!,#REF!,$B10,#REF!,$C10) -> #REF! | M10: =SUMIFS(#REF!,#REF!,$B10,#REF!,$C10) -> #REF! | N10: =COUNTIFS(#REF!,$B10,#REF!,$C10) -> #REF! | O10: =COUNTIFS(#REF!,$B10,#REF!,$C10) -> #REF! | P10: =IF(MONTH(TODAY())>=$D10,COUNTIFS(#REF!,$C10)-COUNTIFS(#REF!,$C10),"") | R10: =IF(MONTH(TODAY())>=$D10,COUNTIFS(#REF!,$C10)-COUNTIFS(#REF!,$C10),"") | S10: =COUNTIFS(#REF!,$B10,#REF!,$C10) -> #REF! | T10: =COUNTIFS(#REF!,$B10,#REF!,$C10) -> #REF! | U10: =IF(MONTH(TODAY())>=$D10,COUNTIFS(#REF!,$C10)-COUNTIFS(#REF!,$C10),"") | W10: =IF(MONTH(TODAY())>=$D10,COUNTIFS(#REF!,$C10)-COUNTIFS(#REF!,$C10),"") | X10: 11 | Y10: =Y59+Y99 -> 153.5 | Z10: =Z59+Z99 -> 349495.11 | AA10: =COUNTIFS(#REF!,$B10,#REF!,$C10) -> #REF! | AB10: =SUMIFS(#REF!,#REF!,$B10,#REF!,$C10) -> #REF! | AC10: =SUMIFS(#REF!,#REF!,$B10,#REF!,$C10) -> #REF! | AD10: =COUNTIFS(#REF!,$B10,#REF!,$C10) -> #REF! | AE10: =SUMIFS(#REF!,#REF!,$B10,#REF!,$C10) -> #REF! | AF10: =SUMIFS(#REF!,#REF!,$B10,#REF!,$C10) -> #REF! | AH10: =IF(MONTH(TODAY())>=$D10,K10-H10,"") | AI10: =IF(MONTH(TODAY())>=$D10,L10-I10,"") | AJ10: =IF(MONTH(TODAY())>=$D10,M10-J10,"") | AL10: =IF(MONTH(TODAY())>=$D10,AD10-X10,"") | AM10: =IF(MONTH(TODAY())>=$D10,AE10-Y10,"") | AN10: =IF(MONTH(TODAY())>=$D10,AF10-Z10,"") | AP10: =IF(MONTH(TODAY())>=$D10,AD10-AA10,"") | AQ10: =IF(MONTH(TODAY())>=$D10,AE10-AB10,"") | AR10: =IF(MONTH(TODAY())>=$D10,AF10-AC10,"")
B11: >=6/1/24 | C11: <7/1/24 | D11: 6 | E11: =CONCATENATE(LEFT(B11,FIND(">=",B11) + 1),RIGHT(C11,LEN(C11) - (FIND("<",C11)))) -> >=7/1/24 | F11: June | G11: =J11/$J$19 -> 0.1037 | H11: =H60+H100 -> 12 | I11: =I60+I100 -> 156.36413 | J11: 362950 | K11: =COUNTIFS(#REF!,$B11,#REF!,$C11) -> #REF! | L11: =SUMIFS(#REF!,#REF!,$B11,#REF!,$C11) -> #REF! | M11: =SUMIFS(#REF!,#REF!,$B11,#REF!,$C11) -> #REF! | N11: =COUNTIFS(#REF!,$B11,#REF!,$C11) -> #REF! | O11: =COUNTIFS(#REF!,$B11,#REF!,$C11) -> #REF! | P11: =IF(MONTH(TODAY())>=$D11,COUNTIFS(#REF!,$C11)-COUNTIFS(#REF!,$C11),"") | R11: =IF(MONTH(TODAY())>=$D11,COUNTIFS(#REF!,$C11)-COUNTIFS(#REF!,$C11),"") | S11: =COUNTIFS(#REF!,$B11,#REF!,$C11) -> #REF! | T11: =COUNTIFS(#REF!,$B11,#REF!,$C11) -> #REF! | U11: =IF(MONTH(TODAY())>=$D11,COUNTIFS(#REF!,$C11)-COUNTIFS(#REF!,$C11),"") | W11: =IF(MONTH(TODAY())>=$D11,COUNTIFS(#REF!,$C11)-COUNTIFS(#REF!,$C11),"") | X11: 11 | Y11: =Y60+Y100 -> 153.5 | Z11: =Z60+Z100 -> 349495.11 | AA11: =COUNTIFS(#REF!,$B11,#REF!,$C11) -> #REF! | AB11: =SUMIFS(#REF!,#REF!,$B11,#REF!,$C11) -> #REF! | AC11: =SUMIFS(#REF!,#REF!,$B11,#REF!,$C11) -> #REF! | AD11: =COUNTIFS(#REF!,$B11,#REF!,$C11) -> #REF! | AE11: =SUMIFS(#REF!,#REF!,$B11,#REF!,$C11) -> #REF! | AF11: =SUMIFS(#REF!,#REF!,$B11,#REF!,$C11) -> #REF! | AH11: =IF(MONTH(TODAY())>=$D11,K11-H11,"") | AI11: =IF(MONTH(TODAY())>=$D11,L11-I11,"") | AJ11: =IF(MONTH(TODAY())>=$D11,M11-J11,"") | AL11: =IF(MONTH(TODAY())>=$D11,AD11-X11,"") | AM11: =IF(MONTH(TODAY())>=$D11,AE11-Y11,"") | AN11: =IF(MONTH(TODAY())>=$D11,AF11-Z11,"") | AP11: =IF(MONTH(TODAY())>=$D11,AD11-AA11,"") | AQ11: =IF(MONTH(TODAY())>=$D11,AE11-AB11,"") | AR11: =IF(MONTH(TODAY())>=$D11,AF11-AC11,"")
B12: >=7/1/24 | C12: <8/1/24 | D12: 7 | E12: =CONCATENATE(LEFT(B12,FIND(">=",B12) + 1),RIGHT(C12,LEN(C12) - (FIND("<",C12)))) -> >=8/1/24 | F12: July | G12: =J12/$J$19 -> 0.0641 | H12: =H61+H101 -> 7 | I12: =I61+I101 -> 106.44901 | J12: 224350 | K12: =COUNTIFS(#REF!,$B12,#REF!,$C12) -> #REF! | L12: =SUMIFS(#REF!,#REF!,$B12,#REF!,$C12) -> #REF! | M12: =SUMIFS(#REF!,#REF!,$B12,#REF!,$C12) -> #REF! | N12: =COUNTIFS(#REF!,$B12,#REF!,$C12) -> #REF! | O12: =COUNTIFS(#REF!,$B12,#REF!,$C12) -> #REF! | P12: =IF(MONTH(TODAY())>=$D12,COUNTIFS(#REF!,$C12)-COUNTIFS(#REF!,$C12),"") | R12: =IF(MONTH(TODAY())>=$D12,COUNTIFS(#REF!,$C12)-COUNTIFS(#REF!,$C12),"") | S12: =COUNTIFS(#REF!,$B12,#REF!,$C12) -> #REF! | T12: =COUNTIFS(#REF!,$B12,#REF!,$C12) -> #REF! | U12: =IF(MONTH(TODAY())>=$D12,COUNTIFS(#REF!,$C12)-COUNTIFS(#REF!,$C12),"") | W12: =IF(MONTH(TODAY())>=$D12,COUNTIFS(#REF!,$C12)-COUNTIFS(#REF!,$C12),"") | X12: 12 | Y12: =Y61+Y101 -> 163.5 | Z12: =Z61+Z101 -> 377263.22 | AA12: =COUNTIFS(#REF!,$B12,#REF!,$C12) -> #REF! | AB12: =SUMIFS(#REF!,#REF!,$B12,#REF!,$C12) -> #REF! | AC12: =SUMIFS(#REF!,#REF!,$B12,#REF!,$C12) -> #REF! | AD12: =COUNTIFS(#REF!,$B12,#REF!,$C12) -> #REF! | AE12: =SUMIFS(#REF!,#REF!,$B12,#REF!,$C12) -> #REF! | AF12: =SUMIFS(#REF!,#REF!,$B12,#REF!,$C12) -> #REF! | AH12: =IF(MONTH(TODAY())>=$D12,K12-H12,"") | AI12: =IF(MONTH(TODAY())>=$D12,L12-I12,"") | AJ12: =IF(MONTH(TODAY())>=$D12,M12-J12,"") | AL12: =IF(MONTH(TODAY())>=$D12,AD12-X12,"") | AM12: =IF(MONTH(TODAY())>=$D12,AE12-Y12,"") | AN12: =IF(MONTH(TODAY())>=$D12,AF12-Z12,"") | AP12: =IF(MONTH(TODAY())>=$D12,AD12-AA12,"") | AQ12: =IF(MONTH(TODAY())>=$D12,AE12-AB12,"") | AR12: =IF(MONTH(TODAY())>=$D12,AF12-AC12,"")
B13: >=8/1/24 | C13: <9/1/24 | D13: 8 | E13: =CONCATENATE(LEFT(B13,FIND(">=",B13) + 1),RIGHT(C13,LEN(C13) - (FIND("<",C13)))) -> >=9/1/24 | F13: August | G13: =J13/$J$19 -> 0.0933 | H13: =H62+H102 -> 10 | I13: =I62+I102 -> 143.2551 | J13: 326550 | K13: =COUNTIFS(#REF!,$B13,#REF!,$C13) -> #REF! | L13: =SUMIFS(#REF!,#REF!,$B13,#REF!,$C13) -> #REF! | M13: =SUMIFS(#REF!,#REF!,$B13,#REF!,$C13) -> #REF! | N13: =COUNTIFS(#REF!,$B13,#REF!,$C13) -> #REF! | O13: =COUNTIFS(#REF!,$B13,#REF!,$C13) -> #REF! | P13: =IF(MONTH(TODAY())>=$D13,COUNTIFS(#REF!,$C13)-COUNTIFS(#REF!,$C13),"") | R13: =IF(MONTH(TODAY())>=$D13,COUNTIFS(#REF!,$C13)-COUNTIFS(#REF!,$C13),"") | S13: =COUNTIFS(#REF!,$B13,#REF!,$C13) -> #REF! | T13: =COUNTIFS(#REF!,$B13,#REF!,$C13) -> #REF! | U13: =IF(MONTH(TODAY())>=$D13,COUNTIFS(#REF!,$C13)-COUNTIFS(#REF!,$C13),"") | W13: =IF(MONTH(TODAY())>=$D13,COUNTIFS(#REF!,$C13)-COUNTIFS(#REF!,$C13),"") | X13: 12 | Y13: =Y62+Y102 -> 163.5 | Z13: =Z62+Z102 -> 377263.22 | AA13: =COUNTIFS(#REF!,$B13,#REF!,$C13) -> #REF! | AB13: =SUMIFS(#REF!,#REF!,$B13,#REF!,$C13) -> #REF! | AC13: =SUMIFS(#REF!,#REF!,$B13,#REF!,$C13) -> #REF! | AD13: =COUNTIFS(#REF!,$B13,#REF!,$C13) -> #REF! | AE13: =SUMIFS(#REF!,#REF!,$B13,#REF!,$C13) -> #REF! | AF13: =SUMIFS(#REF!,#REF!,$B13,#REF!,$C13) -> #REF! | AH13: =IF(MONTH(TODAY())>=$D13,K13-H13,"") | AI13: =IF(MONTH(TODAY())>=$D13,L13-I13,"") | AJ13: =IF(MONTH(TODAY())>=$D13,M13-J13,"") | AL13: =IF(MONTH(TODAY())>=$D13,AD13-X13,"") | AM13: =IF(MONTH(TODAY())>=$D13,AE13-Y13,"") | AN13: =IF(MONTH(TODAY())>=$D13,AF13-Z13,"") | AP13: =IF(MONTH(TODAY())>=$D13,AD13-AA13,"") | AQ13: =IF(MONTH(TODAY())>=$D13,AE13-AB13,"") | AR13: =IF(MONTH(TODAY())>=$D13,AF13-AC13,"")
B14: >=9/1/24 | C14: <10/1/24 | D14: 9 | E14: =CONCATENATE(LEFT(B14,FIND(">=",B14) + 1),RIGHT(C14,LEN(C14) - (FIND("<",C14)))) -> >=10/1/24 | F14: September | G14: =J14/$J$19 -> 0.0829 | H14: =H63+H103 -> 9 | I14: =I63+I103 -> 130.14608 | J14: 290150 | K14: =COUNTIFS(#REF!,$B14,#REF!,$C14) -> #REF! | L14: =SUMIFS(#REF!,#REF!,$B14,#REF!,$C14) -> #REF! | M14: =SUMIFS(#REF!,#REF!,$B14,#REF!,$C14) -> #REF! | N14: =COUNTIFS(#REF!,$B14,#REF!,$C14) -> #REF! | O14: =COUNTIFS(#REF!,$B14,#REF!,$C14) -> #REF! | P14: =IF(MONTH(TODAY())>=$D14,COUNTIFS(#REF!,$C14)-COUNTIFS(#REF!,$C14),"") | R14: =IF(MONTH(TODAY())>=$D14,COUNTIFS(#REF!,$C14)-COUNTIFS(#REF!,$C14),"") | S14: =COUNTIFS(#REF!,$B14,#REF!,$C14) -> #REF! | T14: =COUNTIFS(#REF!,$B14,#REF!,$C14) -> #REF! | U14: =IF(MONTH(TODAY())>=$D14,COUNTIFS(#REF!,$C14)-COUNTIFS(#REF!,$C14),"") | W14: =IF(MONTH(TODAY())>=$D14,COUNTIFS(#REF!,$C14)-COUNTIFS(#REF!,$C14),"") | X14: 11 | Y14: =Y63+Y103 -> 153.5 | Z14: =Z63+Z103 -> 349495.11 | AA14: =COUNTIFS(#REF!,$B14,#REF!,$C14) -> #REF! | AB14: =SUMIFS(#REF!,#REF!,$B14,#REF!,$C14) -> #REF! | AC14: =SUMIFS(#REF!,#REF!,$B14,#REF!,$C14) -> #REF! | AD14: =COUNTIFS(#REF!,$B14,#REF!,$C14) -> #REF! | AE14: =SUMIFS(#REF!,#REF!,$B14,#REF!,$C14) -> #REF! | AF14: =SUMIFS(#REF!,#REF!,$B14,#REF!,$C14) -> #REF! | AH14: =IF(MONTH(TODAY())>=$D14,K14-H14,"") | AI14: =IF(MONTH(TODAY())>=$D14,L14-I14,"") | AJ14: =IF(MONTH(TODAY())>=$D14,M14-J14,"") | AL14: =IF(MONTH(TODAY())>=$D14,AD14-X14,"") | AM14: =IF(MONTH(TODAY())>=$D14,AE14-Y14,"") | AN14: =IF(MONTH(TODAY())>=$D14,AF14-Z14,"") | AP14: =IF(MONTH(TODAY())>=$D14,AD14-AA14,"") | AQ14: =IF(MONTH(TODAY())>=$D14,AE14-AB14,"") | AR14: =IF(MONTH(TODAY())>=$D14,AF14-AC14,"")
B15: >=10/1/24 | C15: <11/1/24 | D15: 10 | E15: =CONCATENATE(LEFT(B15,FIND(">=",B15) + 1),RIGHT(C15,LEN(C15) - (FIND("<",C15)))) -> >=11/1/24 | F15: October | G15: =J15/$J$19 -> 0.1056 | H15: =H64+H104 -> 13 | I15: =I64+I104 -> 133.10698 | J15: 369600 | K15: =COUNTIFS(#REF!,$B15,#REF!,$C15) -> #REF! | L15: =SUMIFS(#REF!,#REF!,$B15,#REF!,$C15) -> #REF! | M15: =SUMIFS(#REF!,#REF!,$B15,#REF!,$C15) -> #REF! | N15: =COUNTIFS(#REF!,$B15,#REF!,$C15) -> #REF! | O15: =COUNTIFS(#REF!,$B15,#REF!,$C15) -> #REF! | P15: =IF(MONTH(TODAY())>=$D15,COUNTIFS(#REF!,$C15)-COUNTIFS(#REF!,$C15),"") | R15: =IF(MONTH(TODAY())>=$D15,COUNTIFS(#REF!,$C15)-COUNTIFS(#REF!,$C15),"") | S15: =COUNTIFS(#REF!,$B15,#REF!,$C15) -> #REF! | T15: =COUNTIFS(#REF!,$B15,#REF!,$C15) -> #REF! | U15: =IF(MONTH(TODAY())>=$D15,COUNTIFS(#REF!,$C15)-COUNTIFS(#REF!,$C15),"") | W15: =IF(MONTH(TODAY())>=$D15,COUNTIFS(#REF!,$C15)-COUNTIFS(#REF!,$C15),"") | X15: 12 | Y15: =Y64+Y104 -> 163.5 | Z15: =Z64+Z104 -> 377263.22 | AA15: =COUNTIFS(#REF!,$B15,#REF!,$C15) -> #REF! | AB15: =SUMIFS(#REF!,#REF!,$B15,#REF!,$C15) -> #REF! | AC15: =SUMIFS(#REF!,#REF!,$B15,#REF!,$C15) -> #REF! | AD15: =COUNTIFS(#REF!,$B15,#REF!,$C15) -> #REF! | AE15: =SUMIFS(#REF!,#REF!,$B15,#REF!,$C15) -> #REF! | AF15: =SUMIFS(#REF!,#REF!,$B15,#REF!,$C15) -> #REF! | AH15: =IF(MONTH(TODAY())>=$D15,K15-H15,"") | AI15: =IF(MONTH(TODAY())>=$D15,L15-I15,"") | AJ15: =IF(MONTH(TODAY())>=$D15,M15-J15,"") | AL15: =IF(MONTH(TODAY())>=$D15,AD15-X15,"") | AM15: =IF(MONTH(TODAY())>=$D15,AE15-Y15,"") | AN15: =IF(MONTH(TODAY())>=$D15,AF15-Z15,"") | AP15: =IF(MONTH(TODAY())>=$D15,AD15-AA15,"") | AQ15: =IF(MONTH(TODAY())>=$D15,AE15-AB15,"") | AR15: =IF(MONTH(TODAY())>=$D15,AF15-AC15,"")
B16: >=11/1/24 | C16: <12/1/24 | D16: 11 | E16: =CONCATENATE(LEFT(B16,FIND(">=",B16) + 1),RIGHT(C16,LEN(C16) - (FIND("<",C16)))) -> >=12/1/24 | F16: November | G16: =J16/$J$19 -> 0.0653 | H16: =H65+H105 -> 8 | I16: =I65+I105 -> 82.309524 | J16: 228550 | K16: =COUNTIFS(#REF!,$B16,#REF!,$C16) -> #REF! | L16: =SUMIFS(#REF!,#REF!,$B16,#REF!,$C16) -> #REF! | M16: =SUMIFS(#REF!,#REF!,$B16,#REF!,$C16) -> #REF! | N16: =COUNTIFS(#REF!,$B16,#REF!,$C16) -> #REF! | O16: =COUNTIFS(#REF!,$B16,#REF!,$C16) -> #REF! | P16: =IF(MONTH(TODAY())>=$D16,COUNTIFS(#REF!,$C16)-COUNTIFS(#REF!,$C16),"") | R16: =IF(MONTH(TODAY())>=$D16,COUNTIFS(#REF!,$C16)-COUNTIFS(#REF!,$C16),"") | S16: =COUNTIFS(#REF!,$B16,#REF!,$C16) -> #REF! | T16: =COUNTIFS(#REF!,$B16,#REF!,$C16) -> #REF! | U16: =IF(MONTH(TODAY())>=$D16,COUNTIFS(#REF!,$C16)-COUNTIFS(#REF!,$C16),"") | W16: =IF(MONTH(TODAY())>=$D16,COUNTIFS(#REF!,$C16)-COUNTIFS(#REF!,$C16),"") | X16: 9 | Y16: =Y65+Y105 -> 90 | Z16: =Z65+Z105 -> 249912.94 | AA16: =COUNTIFS(#REF!,$B16,#REF!,$C16) -> #REF! | AB16: =SUMIFS(#REF!,#REF!,$B16,#REF!,$C16) -> #REF! | AC16: =SUMIFS(#REF!,#REF!,$B16,#REF!,$C16) -> #REF! | AD16: =COUNTIFS(#REF!,$B16,#REF!,$C16) -> #REF! | AE16: =SUMIFS(#REF!,#REF!,$B16,#REF!,$C16) -> #REF! | AF16: =SUMIFS(#REF!,#REF!,$B16,#REF!,$C16) -> #REF! | AH16: =IF(MONTH(TODAY())>=$D16,K16-H16,"") | AI16: =IF(MONTH(TODAY())>=$D16,L16-I16,"") | AJ16: =IF(MONTH(TODAY())>=$D16,M16-J16,"") | AL16: =IF(MONTH(TODAY())>=$D16,AD16-X16,"") | AM16: =IF(MONTH(TODAY())>=$D16,AE16-Y16,"") | AN16: =IF(MONTH(TODAY())>=$D16,AF16-Z16,"") | AP16: =IF(MONTH(TODAY())>=$D16,AD16-AA16,"") | AQ16: =IF(MONTH(TODAY())>=$D16,AE16-AB16,"") | AR16: =IF(MONTH(TODAY())>=$D16,AF16-AC16,"")
B17: >=12/1/24 | C17: <1/1/25 | D17: 12 | E17: =CONCATENATE(LEFT(B17,FIND(">=",B17) + 1),RIGHT(C17,LEN(C17) - (FIND("<",C17)))) -> >=1/1/25 | F17: December | G17: =J17/$J$19 -> 0.0811 | H17: =H66+H106 -> 10 | I17: =I66+I106 -> 102.22515 | J17: 283850 | K17: =COUNTIFS(#REF!,$B17,#REF!,$C17) -> #REF! | L17: =SUMIFS(#REF!,#REF!,$B17,#REF!,$C17) -> #REF! | M17: =SUMIFS(#REF!,#REF!,$B17,#REF!,$C17) -> #REF! | N17: =COUNTIFS(#REF!,$B17,#REF!,$C17) -> #REF! | O17: =COUNTIFS(#REF!,$B17,#REF!,$C17) -> #REF! | P17: =IF(MONTH(TODAY())>=$D17,COUNTIFS(#REF!,$C17)-COUNTIFS(#REF!,$C17),"") | R17: =IF(MONTH(TODAY())>=$D17,COUNTIFS(#REF!,$C17)-COUNTIFS(#REF!,$C17),"") | S17: =COUNTIFS(#REF!,$B17,#REF!,$C17) -> #REF! | T17: =COUNTIFS(#REF!,$B17,#REF!,$C17) -> #REF! | U17: =IF(MONTH(TODAY())>=$D17,COUNTIFS(#REF!,$C17)-COUNTIFS(#REF!,$C17),"") | W17: =IF(MONTH(TODAY())>=$D17,COUNTIFS(#REF!,$C17)-COUNTIFS(#REF!,$C17),"") | X17: 6 | Y17: =Y66+Y106 -> 60 | Z17: =Z66+Z106 -> 166608.63 | AA17: =COUNTIFS(#REF!,$B17,#REF!,$C17) -> #REF! | AB17: =SUMIFS(#REF!,#REF!,$B17,#REF!,$C17) -> #REF! | AC17: =SUMIFS(#REF!,#REF!,$B17,#REF!,$C17) -> #REF! | AD17: =COUNTIFS(#REF!,$B17,#REF!,$C17) -> #REF! | AE17: =SUMIFS(#REF!,#REF!,$B17,#REF!,$C17) -> #REF! | AF17: =SUMIFS(#REF!,#REF!,$B17,#REF!,$C17) -> #REF! | AH17: =IF(MONTH(TODAY())>=$D17,K17-H17,"") | AI17: =IF(MONTH(TODAY())>=$D17,L17-I17,"") | AJ17: =IF(MONTH(TODAY())>=$D17,M17-J17,"") | AL17: =IF(MONTH(TODAY())>=$D17,AD17-X17,"") | AM17: =IF(MONTH(TODAY())>=$D17,AE17-Y17,"") | AN17: =IF(MONTH(TODAY())>=$D17,AF17-Z17,"") | AP17: =IF(MONTH(TODAY())>=$D17,AD17-AA17,"") | AQ17: =IF(MONTH(TODAY())>=$D17,AE17-AB17,"") | AR17: =IF(MONTH(TODAY())>=$D17,AF17-AC17,"")
B18: >=1/1/25 | C18: <1/1/26 | E18: =CONCATENATE(LEFT(B18,FIND(">=",B18) + 1),RIGHT(C18,LEN(C18) - (FIND("<",C18)))) -> >=1/1/26 | F18: 2025 | G18: N/A | K18: =COUNTIFS(#REF!,$B18,#REF!,$C18) -> #REF! | L18: =SUMIFS(#REF!,#REF!,$B18,#REF!,$C18) -> #REF! | M18: =SUMIFS(#REF!,#REF!,$B18,#REF!,$C18) -> #REF! | N18: =COUNTIFS(#REF!,$B18,#REF!,$C18) -> #REF! | O18: =COUNTIFS(#REF!,$B18,#REF!,$C18) -> #REF! | S18: =COUNTIFS(#REF!,$B18,#REF!,$C18) -> #REF! | T18: =COUNTIFS(#REF!,$B18,#REF!,$C18) -> #REF! | AA18: =COUNTIFS(#REF!,$B18,#REF!,$C18) -> #REF! | AB18: =SUMIFS(#REF!,#REF!,$B18,#REF!,$C18) -> #REF! | AC18: =SUMIFS(#REF!,#REF!,$B18,#REF!,$C18) -> #REF!
F19: Total | G19: =SUM(G6:G17) -> 1 | H19: =X19*J19/Z19 -> 112.79128 | I19: =Y19*J19/Z19 -> 1491.3513 | J19: =SUM(J6:J17) -> 3500000 | K19: =SUM(K5:K18) -> #REF! | L19: =SUM(L5:L18) -> #REF! | M19: =SUM(M5:M18) -> #REF! | N19: =SUM(N5:N18) -> #REF! | O19: =SUM(O5:O18) -> #REF! | P19: =INDEX(P5:P18,MONTH(TODAY())+1) -> #REF! | Q19: =INDEX(Q5:Q18,MONTH(TODAY())+1) | R19: =INDEX(R5:R18,MONTH(TODAY())+1) -> #REF! | S19: =SUM(S5:S18) -> #REF! | T19: =SUM(T5:T18) -> #REF! | U19: =INDEX(U5:U18,MONTH(TODAY())+1) -> #REF! | V19: =INDEX(V5:V18,MONTH(TODAY())+1) | W19: =INDEX(W5:W18,MONTH(TODAY())+1) -> #REF! | X19: =SUM(X5:X18) -> 108 | Y19: =SUM(Y5:Y18) -> 1428 | Z19: =3351323 -> 3351323 | AA19: =SUM(AA5:AA18) -> #REF! | AB19: =SUM(AB5:AB18) -> #REF! | AC19: =SUM(AC5:AC18) -> #REF! | AD19: =SUM(AD6:AD17) -> #REF! | AE19: =SUM(AE5:AE18) -> #REF! | AF19: =SUM(AF5:AF18) -> #REF! | AH19: =SUM(AH6:AH17) -> #REF! | AI19: =SUM(AI6:AI17) -> #REF! | AJ19: =SUM(AJ6:AJ17) -> #REF! | AL19: =SUM(AL5:AL18) -> #REF! | AM19: =SUM(AM5:AM18) -> #REF! | AN19: =SUM(AN5:AN18) -> #REF! | AP19: =SUM(AP5:AP18) -> #REF! | AQ19: =SUM(AQ5:AQ18) -> #REF! | AR19: =SUM(AR5:AR18) -> #REF!
F20: Total* | G20: =SUM(G6:G17) -> 1 | K20: =SUM(K6:K17) -> #REF! | L20: =SUM(L6:L17) -> #REF! | M20: =SUM(M6:M17) -> #REF! | N20: =SUM(N6:N17) -> #REF! | O20: =SUM(O6:O17) -> #REF! | S20: =SUM(S6:S17) -> #REF! | T20: =SUM(T6:T17) -> #REF! | AA20: =SUM(AA6:AA17) -> #REF! | AB20: =SUM(AB6:AB17) -> #REF! | AC20: =SUM(AC6:AC17) -> #REF! | AP20: =SUM(AP6:AP17) -> #REF! | AQ20: =SUM(AQ6:AQ17) -> #REF! | AR20: =SUM(AR6:AR17) -> #REF!
H22: *Removes 2023 and 2025 data
L23: June - September is all resi | X23: 1000 kW Resi | AH23: Positive Numbers Indicate we are ahead of schedule in terms of actual bookings | AL23: Positive Numbers Indicate we are ahead of schedule in terms of actual installations | AP23: Positive Numbers Indicate we are ahead of schedule in terms of actual installations vs what we planned on doing at contract signing (BD Actuals)
H24: $3,500,000 in bookings is the target | X24: 428 kW Commercial
H25: Since booking revenue target is 4.44% greater than installed revenue target, kW booked and QTY booked targets are taken to be 1.0444* Install Goals for 2024 | X25: 108 Jobs Total
X26: No plan as to which months the commercial projects will land in
X28: Yearly Avg kW target: 13.23kW/system (blend of resi + commercial)
H29: Yearly Avg kW target: 13.23kW/system (blend of resi + commercial)
AH33: Bookings | AL33: Installs
F34: Month | AF34: # of Months Left | AH34: Average monthly residential + commercial bookings needed to be in line with Budgeted Goals | AL34: Average monthly residential + commercial installs needed to be in line with Budgeted Goals
F35: January | AF35: 12 | AH35: =IF(MONTH(TODAY())=$D6,$AH$47/$AF35,"") | AI35: =IF(MONTH(TODAY())=$D6,$AI$47/$AF35,"") | AJ35: =IF(MONTH(TODAY())=$D6,$AJ$47/$AF35,"") | AL35: =IF(MONTH(TODAY())=$D6,$AL$47/$AF35,"") | AM35: =IF(MONTH(TODAY())=$D6,$AM$47/$AF35,"") | AN35: =IF(MONTH(TODAY())=$D6,$AN$47/AF35,"")
F36: February | AF36: 11 | AH36: =IF(MONTH(TODAY())=$D7,$AH$47/$AF36,"") | AI36: =IF(MONTH(TODAY())=$D7,$AI$47/$AF36,"") | AJ36: =IF(MONTH(TODAY())=$D7,$AJ$47/$AF36,"") | AL36: =IF(MONTH(TODAY())=$D7,$AL$47/$AF36,"") | AM36: =IF(MONTH(TODAY())=$D7,$AM$47/$AF36,"") | AN36: =IF(MONTH(TODAY())=$D7,$AN$47/AF36,"")
F37: March | AF37: 10 | AH37: =IF(MONTH(TODAY())=$D8,$AH$47/$AF37,"") -> #REF! | AI37: =IF(MONTH(TODAY())=$D8,$AI$47/$AF37,"") -> #REF! | AJ37: =IF(MONTH(TODAY())=$D8,$AJ$47/$AF37,"") -> #REF! | AL37: =IF(MONTH(TODAY())=$D8,$AL$47/$AF37,"") -> #REF! | AM37: =IF(MONTH(TODAY())=$D8,$AM$47/$AF37,"") -> #REF! | AN37: =IF(MONTH(TODAY())=$D8,$AN$47/AF37,"") -> #REF!
F38: April | AF38: 9 | AH38: =IF(MONTH(TODAY())=$D9,$AH$47/$AF38,"") | AI38: =IF(MONTH(TODAY())=$D9,$AI$47/$AF38,"") | AJ38: =IF(MONTH(TODAY())=$D9,$AJ$47/$AF38,"") | AL38: =IF(MONTH(TODAY())=$D9,$AL$47/$AF38,"") | AM38: =IF(MONTH(TODAY())=$D9,$AM$47/$AF38,"") | AN38: =IF(MONTH(TODAY())=$D9,$AN$47/AF38,"")
F39: May | AF39: 8 | AH39: =IF(MONTH(TODAY())=$D10,$AH$47/$AF39,"") | AI39: =IF(MONTH(TODAY())=$D10,$AI$47/$AF39,"") | AJ39: =IF(MONTH(TODAY())=$D10,$AJ$47/$AF39,"") | AL39: =IF(MONTH(TODAY())=$D10,$AL$47/$AF39,"") | AM39: =IF(MONTH(TODAY())=$D10,$AM$47/$AF39,"") | AN39: =IF(MONTH(TODAY())=$D10,$AN$47/AF39,"")
F40: June | AF40: 7 | AH40: =IF(MONTH(TODAY())=$D11,$AH$47/$AF40,"") | AI40: =IF(MONTH(TODAY())=$D11,$AI$47/$AF40,"") | AJ40: =IF(MONTH(TODAY())=$D11,$AJ$47/$AF40,"") | AL40: =IF(MONTH(TODAY())=$D11,$AL$47/$AF40,"") | AM40: =IF(MONTH(TODAY())=$D11,$AM$47/$AF40,"") | AN40: =IF(MONTH(TODAY())=$D11,$AN$47/AF40,"")
F41: July | AF41: 6 | AH41: =IF(MONTH(TODAY())=$D12,$AH$47/$AF41,"") | AI41: =IF(MONTH(TODAY())=$D12,$AI$47/$AF41,"") | AJ41: =IF(MONTH(TODAY())=$D12,$AJ$47/$AF41,"") | AL41: =IF(MONTH(TODAY())=$D12,$AL$47/$AF41,"") | AM41: =IF(MONTH(TODAY())=$D12,$AM$47/$AF41,"") | AN41: =IF(MONTH(TODAY())=$D12,$AN$47/AF41,"")
F42: August | AF42: 5 | AH42: =IF(MONTH(TODAY())=$D13,$AH$47/$AF42,"") | AI42: =IF(MONTH(TODAY())=$D13,$AI$47/$AF42,"") | AJ42: =IF(MONTH(TODAY())=$D13,$AJ$47/$AF42,"") | AL42: =IF(MONTH(TODAY())=$D13,$AL$47/$AF42,"") | AM42: =IF(MONTH(TODAY())=$D13,$AM$47/$AF42,"") | AN42: =IF(MONTH(TODAY())=$D13,$AN$47/AF42,"")
F43: September | AF43: 4 | AH43: =IF(MONTH(TODAY())=$D14,$AH$47/$AF43,"") | AI43: =IF(MONTH(TODAY())=$D14,$AI$47/$AF43,"") | AJ43: =IF(MONTH(TODAY())=$D14,$AJ$47/$AF43,"") | AL43: =IF(MONTH(TODAY())=$D14,$AL$47/$AF43,"") | AM43: =IF(MONTH(TODAY())=$D14,$AM$47/$AF43,"") | AN43: =IF(MONTH(TODAY())=$D14,$AN$47/AF43,"")
F44: October | AF44: 3 | AH44: =IF(MONTH(TODAY())=$D15,$AH$47/$AF44,"") | AI44: =IF(MONTH(TODAY())=$D15,$AI$47/$AF44,"") | AJ44: =IF(MONTH(TODAY())=$D15,$AJ$47/$AF44,"") | AL44: =IF(MONTH(TODAY())=$D15,$AL$47/$AF44,"") | AM44: =IF(MONTH(TODAY())=$D15,$AM$47/$AF44,"") | AN44: =IF(MONTH(TODAY())=$D15,$AN$47/AF44,"")
F45: November | AF45: 2 | AH45: =IF(MONTH(TODAY())=$D16,$AH$47/$AF45,"") | AI45: =IF(MONTH(TODAY())=$D16,$AI$47/$AF45,"") | AJ45: =IF(MONTH(TODAY())=$D16,$AJ$47/$AF45,"") | AL45: =IF(MONTH(TODAY())=$D16,$AL$47/$AF45,"") | AM45: =IF(MONTH(TODAY())=$D16,$AM$47/$AF45,"") | AN45: =IF(MONTH(TODAY())=$D16,$AN$47/AF45,"")
F46: December | AF46: 1 | AH46: =IF(MONTH(TODAY())=$D17,$AH$47/$AF46,"") | AI46: =IF(MONTH(TODAY())=$D17,$AI$47/$AF46,"") | AJ46: =IF(MONTH(TODAY())=$D17,$AJ$47/$AF46,"") | AL46: =IF(MONTH(TODAY())=$D17,$AL$47/$AF46,"") | AM46: =IF(MONTH(TODAY())=$D17,$AM$47/$AF46,"") | AN46: =IF(MONTH(TODAY())=$D17,$AN$47/AF46,"")
F47: Total | AH47: =H19-K20 -> #REF! | AI47: =I19-L20 -> #REF! | AJ47: =J19-M20 -> #REF! | AL47: =X19-AD19 -> #REF! | AM47: =Y19-AE19 -> #REF! | AN47: =Z19-AF19 -> #REF!
H51: RESIDENTIAL
H52: Budgetted Bookings | K52: Actual Bookings | N52: Permits | S52: Utility Applications | X52: Budgetted Install Schedule | AA52: Planned Installs at Contract Signing | AD52: Actual Installations | AH52: Budgeted Bookings vs Actual Bookings | AL52: Budgeted Installs vs Actual Installs | AP52: Planned Installs at Contract vs Actual Install
F53: Month | G53: Median Booking %/month 2021-2023 average | H53: QTY Booked | I53: kW Booked | J53: Contract Value of Booked Systems | K53: QTY Booked | L53: kW Booked | M53: Contract Value of Booked Systems | N53: Permits Submitted | O53: Permits Approved | P53: Jobs with Unsubmitted Permits | Q53: Outstanding Submitted Permits MTD or at Months End | R53: Total Approved But Uninstalled Permits MTD or at Month End | S53: Utility Applications Submitted | T53: Utility Applications Approved | U53: Jobs with Unsubmitted Utility Applications | V53: Outstanding Submitted Utility Applications MTD or at Months End | W53: Total Approved but Uninstalled Utility Applications MTD or at Months End | X53: QTY Installed | Y53: kW Installed | Z53: Contract Value of Installed Systems | AA53: QTY Installed | AB53: kW Installed | AC53: Contract Value of Installed Systems | AD53: QTY Installed | AE53: kW Installed | AF53: Contract Value of Installed Systems | AH53: QTY Booked | AI53: kW Booked | AJ53: Contract Value of Booked Systems | AL53: QTY Installed | AM53: kW Installed | AN53: Contract Value of Installed Systems | AP53: QTY Installed | AQ53: kW Installed | AR53: Contract Value of Installed Systems
B54: >=1/1/23 | C54: <1/1/24 | D54: 0 | E54: =CONCATENATE(LEFT(B54,FIND(">=",B54) + 1),RIGHT(C54,LEN(C54) - (FIND("<",C54)))) -> >=1/1/24 | F54: 2023 | G54: N/A | K54: =COUNTIFS(#REF!,$B54,#REF!,$C54,#REF!,$H$51) -> #REF! | L54: =SUMIFS(#REF!,#REF!,$B54,#REF!,$C54,#REF!,$H$51) -> #REF! | M54: =SUMIFS(#REF!,#REF!,$B54,#REF!,$C54,#REF!,$H$51) -> #REF! | N54: =COUNTIFS(#REF!,$B5,#REF!,$C5,#REF!,$H$51) -> #REF! | O54: =COUNTIFS(#REF!,$B54,#REF!,$C54,#REF!,$H$51) -> #REF! | P54: =IF(MONTH(TODAY())>=$D5,COUNTIFS(#REF!,$C54,#REF!,$H$51)-COUNTIFS(#REF!,$C54,#REF!,$H$51),"") -> #REF! | Q54: 0 | R54: =IF(MONTH(TODAY())>=$D5,COUNTIFS(#REF!,$C54,#REF!,$H$51)-COUNTIFS(#REF!,$C54,#REF!,$H$51),"") -> #REF! | S54: =COUNTIFS(#REF!,$B54,#REF!,$C54,#REF!,$H$51) -> #REF! | T54: =COUNTIFS(#REF!,$B54,#REF!,$C54,#REF!,$H$51) -> #REF! | U54: =IF(MONTH(TODAY())>=$D5,COUNTIFS(#REF!,$C54,#REF!,$H$51)-COUNTIFS(#REF!,$C54,#REF!,$H$51),"") -> #REF! | V54: 0 | W54: =IF(MONTH(TODAY())>=$D5,COUNTIFS(#REF!,$C54,#REF!,$H$51)-COUNTIFS(#REF!,$C54,#REF!,$H$51),"") -> #REF! | AA54: =COUNTIFS(#REF!,$B54,#REF!,$C54,#REF!,$H$51) -> #REF! | AB54: =SUMIFS(#REF!,#REF!,$B54,#REF!,$C54,#REF!,$H$51) -> #REF! | AC54: =SUMIFS(#REF!,#REF!,$B54,#REF!,$C54,#REF!,$H$51) -> #REF! | AP54: =IF(MONTH(TODAY())>=$D5,AD54-X54,"") -> 0 | AQ54: =IF(MONTH(TODAY())>=$D5,AE54-Y54,"") -> 0 | AR54: =IF(MONTH(TODAY())>=$D5,AF54-Z54,"") -> 0
B55: >=1/1/24 | C55: <2/1/24 | D55: 1 | E55: =CONCATENATE(LEFT(B55,FIND(">=",B55) + 1),RIGHT(C55,LEN(C55) - (FIND("<",C55)))) -> >=2/1/24 | F55: January | G55: 0.0622 | H55: =ROUND(J55/$J$68*$H$68,0) -> 5 | I55: =J55/$J$68*$I$68 -> 51.997915 | J55: =J6-J95 -> 144383.33 | K55: =COUNTIFS(#REF!,$B55,#REF!,$C55,#REF!,$H$51) -> #REF! | L55: =SUMIFS(#REF!,#REF!,$B55,#REF!,$C55,#REF!,$H$51) -> #REF! | M55: =SUMIFS(#REF!,#REF!,$B55,#REF!,$C55,#REF!,$H$51) -> #REF! | N55: =COUNTIFS(#REF!,$B6,#REF!,$C6,#REF!,$H$51) -> #REF! | O55: =COUNTIFS(#REF!,$B55,#REF!,$C55,#REF!,$H$51) -> #REF! | P55: =IF(MONTH(TODAY())>=$D6,COUNTIFS(#REF!,$C55,#REF!,$H$51)-COUNTIFS(#REF!,$C55,#REF!,$H$51),"") -> #REF! | Q55: 0 | R55: =IF(MONTH(TODAY())>=$D6,COUNTIFS(#REF!,$C55,#REF!,$H$51)-COUNTIFS(#REF!,$C55,#REF!,$H$51),"") -> #REF! | S55: =COUNTIFS(#REF!,$B55,#REF!,$C55,#REF!,$H$51) -> #REF! | T55: =COUNTIFS(#REF!,$B55,#REF!,$C55,#REF!,$H$51) -> #REF! | U55: =IF(MONTH(TODAY())>=$D6,COUNTIFS(#REF!,$C55,#REF!,$H$51)-COUNTIFS(#REF!,$C55,#REF!,$H$51),"") -> #REF! | V55: 0 | W55: =IF(MONTH(TODAY())>=$D6,COUNTIFS(#REF!,$C55,#REF!,$H$51)-COUNTIFS(#REF!,$C55,#REF!,$H$51),"") -> #REF! | X55: =X6-X95 -> 4 | Y55: =X55*10 -> 40 | Z55: =$Z$68/$X$68*X55 -> 111072.42 | AA55: =COUNTIFS(#REF!,$B55,#REF!,$C55,#REF!,$H$51) -> #REF! | AB55: =SUMIFS(#REF!,#REF!,$B55,#REF!,$C55,#REF!,$H$51) -> #REF! | AC55: =SUMIFS(#REF!,#REF!,$B55,#REF!,$C55,#REF!,$H$51) -> #REF! | AD55: =COUNTIFS(#REF!,$B55,#REF!,$C55,#REF!,$H$51) -> #REF! | AE55: =SUMIFS(#REF!,#REF!,$B55,#REF!,$C55,#REF!,$H$51) -> #REF! | AF55: =SUMIFS(#REF!,#REF!,$B55,#REF!,$C55,#REF!,$H$51) -> #REF! | AH55: =IF(MONTH(TODAY())>=$D6,K55-H55,"") -> #REF! | AI55: =IF(MONTH(TODAY())>=$D6,L55-I55,"") -> #REF! | AJ55: =IF(MONTH(TODAY())>=$D6,M55-J55,"") -> #REF! | AL55: =IF(MONTH(TODAY())>=$D6,AD55-X55,"") -> #REF! | AM55: =IF(MONTH(TODAY())>=$D6,AE55-Y55,"") -> #REF! | AN55: =IF(MONTH(TODAY())>=$D6,AF55-Z55,"") -> #REF! | AP55: =IF(MONTH(TODAY())>=$D6,AD55-X55,"") -> #REF! | AQ55: =IF(MONTH(TODAY())>=$D6,AE55-Y55,"") -> #REF! | AR55: =IF(MONTH(TODAY())>=$D6,AF55-Z55,"") -> #REF!
B56: >=2/1/24 | C56: <3/1/24 | D56: 2 | E56: =CONCATENATE(LEFT(B56,FIND(">=",B56) + 1),RIGHT(C56,LEN(C56) - (FIND("<",C56)))) -> >=3/1/24 | F56: February | G56: 0.0664 | H56: =ROUND(J56/$J$68*$H$68,0)+1 -> 5 | I56: =J56/$J$68*$I$68 -> 44.939211 | J56: =J7-J96 -> 124783.33 | K56: =COUNTIFS(#REF!,$B56,#REF!,$C56,#REF!,$H$51) -> #REF! | L56: =SUMIFS(#REF!,#REF!,$B56,#REF!,$C56,#REF!,$H$51) -> #REF! | M56: =SUMIFS(#REF!,#REF!,$B56,#REF!,$C56,#REF!,$H$51) -> #REF! | N56: =COUNTIFS(#REF!,$B7,#REF!,$C7,#REF!,$H$51) -> #REF! | O56: =COUNTIFS(#REF!,$B56,#REF!,$C56,#REF!,$H$51) -> #REF! | P56: =IF(MONTH(TODAY())>=$D7,COUNTIFS(#REF!,$C56,#REF!,$H$51)-COUNTIFS(#REF!,$C56,#REF!,$H$51),"") -> #REF! | R56: =IF(MONTH(TODAY())>=$D7,COUNTIFS(#REF!,$C56,#REF!,$H$51)-COUNTIFS(#REF!,$C56,#REF!,$H$51),"") -> #REF! | S56: =COUNTIFS(#REF!,$B56,#REF!,$C56,#REF!,$H$51) -> #REF! | T56: =COUNTIFS(#REF!,$B56,#REF!,$C56,#REF!,$H$51) -> #REF! | U56: =IF(MONTH(TODAY())>=$D7,COUNTIFS(#REF!,$C56,#REF!,$H$51)-COUNTIFS(#REF!,$C56,#REF!,$H$51),"") -> #REF! | W56: =IF(MONTH(TODAY())>=$D7,COUNTIFS(#REF!,$C56,#REF!,$H$51)-COUNTIFS(#REF!,$C56,#REF!,$H$51),"") -> #REF! | X56: =X7-X96 -> 2 | Y56: =X56*10 -> 20 | Z56: =$Z$68/$X$68*X56 -> 55536.21 | AA56: =COUNTIFS(#REF!,$B56,#REF!,$C56,#REF!,$H$51) -> #REF! | AB56: =SUMIFS(#REF!,#REF!,$B56,#REF!,$C56,#REF!,$H$51) -> #REF! | AC56: =SUMIFS(#REF!,#REF!,$B56,#REF!,$C56,#REF!,$H$51) -> #REF! | AD56: =COUNTIFS(#REF!,$B56,#REF!,$C56,#REF!,$H$51) -> #REF! | AE56: =SUMIFS(#REF!,#REF!,$B56,#REF!,$C56,#REF!,$H$51) -> #REF! | AF56: =SUMIFS(#REF!,#REF!,$B56,#REF!,$C56,#REF!,$H$51) -> #REF! | AH56: =IF(MONTH(TODAY())>=$D7,K56-H56,"") -> #REF! | AI56: =IF(MONTH(TODAY())>=$D7,L56-I56,"") -> #REF! | AJ56: =IF(MONTH(TODAY())>=$D7,M56-J56,"") -> #REF! | AL56: =IF(MONTH(TODAY())>=$D7,AD56-X56,"") -> #REF! | AM56: =IF(MONTH(TODAY())>=$D7,AE56-Y56,"") -> #REF! | AN56: =IF(MONTH(TODAY())>=$D7,AF56-Z56,"") -> #REF! | AP56: =IF(MONTH(TODAY())>=$D7,AD56-X56,"") -> #REF! | AQ56: =IF(MONTH(TODAY())>=$D7,AE56-Y56,"") -> #REF! | AR56: =IF(MONTH(TODAY())>=$D7,AF56-Z56,"") -> #REF!
B57: >=3/1/24 | C57: <4/1/24 | D57: 3 | E57: =CONCATENATE(LEFT(B57,FIND(">=",B57) + 1),RIGHT(C57,LEN(C57) - (FIND("<",C57)))) -> >=4/1/24 | F57: March | G57: 0.0705 | H57: =ROUND(J57/$J$68*$H$68,0) -> 8 | I57: =J57/$J$68*$I$68 -> 77.333618 | J57: =J8-J97 -> 214733.33 | K57: =COUNTIFS(#REF!,$B57,#REF!,$C57,#REF!,$H$51) -> #REF! | L57: =SUMIFS(#REF!,#REF!,$B57,#REF!,$C57,#REF!,$H$51) -> #REF! | M57: =SUMIFS(#REF!,#REF!,$B57,#REF!,$C57,#REF!,$H$51) -> #REF! | N57: =COUNTIFS(#REF!,$B8,#REF!,$C8,#REF!,$H$51) -> #REF! | O57: =COUNTIFS(#REF!,$B57,#REF!,$C57,#REF!,$H$51) -> #REF! | P57: =IF(MONTH(TODAY())>=$D8,COUNTIFS(#REF!,$C57,#REF!,$H$51)-COUNTIFS(#REF!,$C57,#REF!,$H$51),"") -> #REF! | R57: =IF(MONTH(TODAY())>=$D8,COUNTIFS(#REF!,$C57,#REF!,$H$51)-COUNTIFS(#REF!,$C57,#REF!,$H$51),"") -> #REF! | S57: =COUNTIFS(#REF!,$B57,#REF!,$C57,#REF!,$H$51) -> #REF! | T57: =COUNTIFS(#REF!,$B57,#REF!,$C57,#REF!,$H$51) -> #REF! | U57: =IF(MONTH(TODAY())>=$D8,COUNTIFS(#REF!,$C57,#REF!,$H$51)-COUNTIFS(#REF!,$C57,#REF!,$H$51),"") -> #REF! | W57: =IF(MONTH(TODAY())>=$D8,COUNTIFS(#REF!,$C57,#REF!,$H$51)-COUNTIFS(#REF!,$C57,#REF!,$H$51),"") -> #REF! | X57: =X8-X97 -> 6 | Y57: =X57*10 -> 60 | Z57: =$Z$68/$X$68*X57 -> 166608.63 | AA57: =COUNTIFS(#REF!,$B57,#REF!,$C57,#REF!,$H$51) -> #REF! | AB57: =SUMIFS(#REF!,#REF!,$B57,#REF!,$C57,#REF!,$H$51) -> #REF! | AC57: =SUMIFS(#REF!,#REF!,$B57,#REF!,$C57,#REF!,$H$51) -> #REF! | AD57: =COUNTIFS(#REF!,$B57,#REF!,$C57,#REF!,$H$51) -> #REF! | AE57: =SUMIFS(#REF!,#REF!,$B57,#REF!,$C57,#REF!,$H$51) -> #REF! | AF57: =SUMIFS(#REF!,#REF!,$B57,#REF!,$C57,#REF!,$H$51) -> #REF! | AH57: =IF(MONTH(TODAY())>=$D8,K57-H57,"") -> #REF! | AI57: =IF(MONTH(TODAY())>=$D8,L57-I57,"") -> #REF! | AJ57: =IF(MONTH(TODAY())>=$D8,M57-J57,"") -> #REF! | AL57: =IF(MONTH(TODAY())>=$D8,AD57-X57,"") -> #REF! | AM57: =IF(MONTH(TODAY())>=$D8,AE57-Y57,"") -> #REF! | AN57: =IF(MONTH(TODAY())>=$D8,AF57-Z57,"") -> #REF! | AP57: =IF(MONTH(TODAY())>=$D8,AD57-X57,"") -> #REF! | AQ57: =IF(MONTH(TODAY())>=$D8,AE57-Y57,"") -> #REF! | AR57: =IF(MONTH(TODAY())>=$D8,AF57-Z57,"") -> #REF!
B58: >=4/1/24 | C58: <5/1/24 | D58: 4 | E58: =CONCATENATE(LEFT(B58,FIND(">=",B58) + 1),RIGHT(C58,LEN(C58) - (FIND("<",C58)))) -> >=5/1/24 | F58: April | G58: 0.1286 | H58: =ROUND(J58/$J$68*$H$68,0) -> 10 | I58: =J58/$J$68*$I$68 -> 104.30795 | J58: =J9-J98 -> 289633.33 | K58: =COUNTIFS(#REF!,$B58,#REF!,$C58,#REF!,$H$51) -> #REF! | L58: =SUMIFS(#REF!,#REF!,$B58,#REF!,$C58,#REF!,$H$51) -> #REF! | M58: =SUMIFS(#REF!,#REF!,$B58,#REF!,$C58,#REF!,$H$51) -> #REF! | N58: =COUNTIFS(#REF!,$B9,#REF!,$C9,#REF!,$H$51) -> #REF! | O58: =COUNTIFS(#REF!,$B58,#REF!,$C58,#REF!,$H$51) -> #REF! | P58: =IF(MONTH(TODAY())>=$D9,COUNTIFS(#REF!,$C58,#REF!,$H$51)-COUNTIFS(#REF!,$C58,#REF!,$H$51),"") | R58: =IF(MONTH(TODAY())>=$D9,COUNTIFS(#REF!,$C58,#REF!,$H$51)-COUNTIFS(#REF!,$C58,#REF!,$H$51),"") | S58: =COUNTIFS(#REF!,$B58,#REF!,$C58,#REF!,$H$51) -> #REF! | T58: =COUNTIFS(#REF!,$B58,#REF!,$C58,#REF!,$H$51) -> #REF! | U58: =IF(MONTH(TODAY())>=$D9,COUNTIFS(#REF!,$C58,#REF!,$H$51)-COUNTIFS(#REF!,$C58,#REF!,$H$51),"") | W58: =IF(MONTH(TODAY())>=$D9,COUNTIFS(#REF!,$C58,#REF!,$H$51)-COUNTIFS(#REF!,$C58,#REF!,$H$51),"") | X58: =X9-X98 -> 10 | Y58: =X58*10 -> 100 | Z58: =$Z$68/$X$68*X58 -> 277681.05 | AA58: =COUNTIFS(#REF!,$B58,#REF!,$C58,#REF!,$H$51) -> #REF! | AB58: =SUMIFS(#REF!,#REF!,$B58,#REF!,$C58,#REF!,$H$51) -> #REF! | AC58: =SUMIFS(#REF!,#REF!,$B58,#REF!,$C58,#REF!,$H$51) -> #REF! | AD58: =COUNTIFS(#REF!,$B58,#REF!,$C58,#REF!,$H$51) -> #REF! | AE58: =SUMIFS(#REF!,#REF!,$B58,#REF!,$C58,#REF!,$H$51) -> #REF! | AF58: =SUMIFS(#REF!,#REF!,$B58,#REF!,$C58,#REF!,$H$51) -> #REF! | AH58: =IF(MONTH(TODAY())>=$D9,K58-H58,"") | AI58: =IF(MONTH(TODAY())>=$D9,L58-I58,"") | AJ58: =IF(MONTH(TODAY())>=$D9,M58-J58,"") | AL58: =IF(MONTH(TODAY())>=$D9,AD58-X58,"") | AM58: =IF(MONTH(TODAY())>=$D9,AE58-Y58,"") | AN58: =IF(MONTH(TODAY())>=$D9,AF58-Z58,"") | AP58: =IF(MONTH(TODAY())>=$D9,AD58-X58,"") | AQ58: =IF(MONTH(TODAY())>=$D9,AE58-Y58,"") | AR58: =IF(MONTH(TODAY())>=$D9,AF58-Z58,"")
B59: >=5/1/24 | C59: <6/1/24 | D59: 5 | E59: =CONCATENATE(LEFT(B59,FIND(">=",B59) + 1),RIGHT(C59,LEN(C59) - (FIND("<",C59)))) -> >=6/1/24 | F59: May | G59: 0.1328 | H59: =ROUND(J59/$J$68*$H$68,0) -> 11 | I59: =J59/$J$68*$I$68 -> 110.61036 | J59: =J10-J99 -> 307133.33 | K59: =COUNTIFS(#REF!,$B59,#REF!,$C59,#REF!,$H$51) -> #REF! | L59: =SUMIFS(#REF!,#REF!,$B59,#REF!,$C59,#REF!,$H$51) -> #REF! | M59: =SUMIFS(#REF!,#REF!,$B59,#REF!,$C59,#REF!,$H$51) -> #REF! | N59: =COUNTIFS(#REF!,$B10,#REF!,$C10,#REF!,$H$51) -> #REF! | O59: =COUNTIFS(#REF!,$B59,#REF!,$C59,#REF!,$H$51) -> #REF! | P59: =IF(MONTH(TODAY())>=$D10,COUNTIFS(#REF!,$C59,#REF!,$H$51)-COUNTIFS(#REF!,$C59,#REF!,$H$51),"") | R59: =IF(MONTH(TODAY())>=$D10,COUNTIFS(#REF!,$C59,#REF!,$H$51)-COUNTIFS(#REF!,$C59,#REF!,$H$51),"") | S59: =COUNTIFS(#REF!,$B59,#REF!,$C59,#REF!,$H$51) -> #REF! | T59: =COUNTIFS(#REF!,$B59,#REF!,$C59,#REF!,$H$51) -> #REF! | U59: =IF(MONTH(TODAY())>=$D10,COUNTIFS(#REF!,$C59,#REF!,$H$51)-COUNTIFS(#REF!,$C59,#REF!,$H$51),"") | W59: =IF(MONTH(TODAY())>=$D10,COUNTIFS(#REF!,$C59,#REF!,$H$51)-COUNTIFS(#REF!,$C59,#REF!,$H$51),"") | X59: =X10-X99 -> 10 | Y59: =X59*10 -> 100 | Z59: =$Z$68/$X$68*X59 -> 277681.05 | AA59: =COUNTIFS(#REF!,$B59,#REF!,$C59,#REF!,$H$51) -> #REF! | AB59: =SUMIFS(#REF!,#REF!,$B59,#REF!,$C59,#REF!,$H$51) -> #REF! | AC59: =SUMIFS(#REF!,#REF!,$B59,#REF!,$C59,#REF!,$H$51) -> #REF! | AD59: =COUNTIFS(#REF!,$B59,#REF!,$C59,#REF!,$H$51) -> #REF! | AE59: =SUMIFS(#REF!,#REF!,$B59,#REF!,$C59,#REF!,$H$51) -> #REF! | AF59: =SUMIFS(#REF!,#REF!,$B59,#REF!,$C59,#REF!,$H$51) -> #REF! | AH59: =IF(MONTH(TODAY())>=$D10,K59-H59,"") | AI59: =IF(MONTH(TODAY())>=$D10,L59-I59,"") | AJ59: =IF(MONTH(TODAY())>=$D10,M59-J59,"") | AL59: =IF(MONTH(TODAY())>=$D10,AD59-X59,"") | AM59: =IF(MONTH(TODAY())>=$D10,AE59-Y59,"") | AN59: =IF(MONTH(TODAY())>=$D10,AF59-Z59,"") | AP59: =IF(MONTH(TODAY())>=$D10,AD59-X59,"") | AQ59: =IF(MONTH(TODAY())>=$D10,AE59-Y59,"") | AR59: =IF(MONTH(TODAY())>=$D10,AF59-Z59,"")
B60: >=6/1/24 | C60: <7/1/24 | D60: 6 | E60: =CONCATENATE(LEFT(B60,FIND(">=",B60) + 1),RIGHT(C60,LEN(C60) - (FIND("<",C60)))) -> >=7/1/24 | F60: June | G60: 0.0788 | H60: =ROUND(J60/$J$68*$H$68,0) -> 11 | I60: =J60/$J$68*$I$68 -> 106.70287 | J60: =J11-J100 -> 296283.33 | K60: =COUNTIFS(#REF!,$B60,#REF!,$C60,#REF!,$H$51) -> #REF! | L60: =SUMIFS(#REF!,#REF!,$B60,#REF!,$C60,#REF!,$H$51) -> #REF! | M60: =SUMIFS(#REF!,#REF!,$B60,#REF!,$C60,#REF!,$H$51) -> #REF! | N60: =COUNTIFS(#REF!,$B11,#REF!,$C11,#REF!,$H$51) -> #REF! | O60: =COUNTIFS(#REF!,$B60,#REF!,$C60,#REF!,$H$51) -> #REF! | P60: =IF(MONTH(TODAY())>=$D11,COUNTIFS(#REF!,$C60,#REF!,$H$51)-COUNTIFS(#REF!,$C60,#REF!,$H$51),"") | R60: =IF(MONTH(TODAY())>=$D11,COUNTIFS(#REF!,$C60,#REF!,$H$51)-COUNTIFS(#REF!,$C60,#REF!,$H$51),"") | S60: =COUNTIFS(#REF!,$B60,#REF!,$C60,#REF!,$H$51) -> #REF! | T60: =COUNTIFS(#REF!,$B60,#REF!,$C60,#REF!,$H$51) -> #REF! | U60: =IF(MONTH(TODAY())>=$D11,COUNTIFS(#REF!,$C60,#REF!,$H$51)-COUNTIFS(#REF!,$C60,#REF!,$H$51),"") | W60: =IF(MONTH(TODAY())>=$D11,COUNTIFS(#REF!,$C60,#REF!,$H$51)-COUNTIFS(#REF!,$C60,#REF!,$H$51),"") | X60: =X11-X100 -> 10 | Y60: =X60*10 -> 100 | Z60: =$Z$68/$X$68*X60 -> 277681.05 | AA60: =COUNTIFS(#REF!,$B60,#REF!,$C60,#REF!,$H$51) -> #REF! | AB60: =SUMIFS(#REF!,#REF!,$B60,#REF!,$C60,#REF!,$H$51) -> #REF! | AC60: =SUMIFS(#REF!,#REF!,$B60,#REF!,$C60,#REF!,$H$51) -> #REF! | AD60: =COUNTIFS(#REF!,$B60,#REF!,$C60,#REF!,$H$51) -> #REF! | AE60: =SUMIFS(#REF!,#REF!,$B60,#REF!,$C60,#REF!,$H$51) -> #REF! | AF60: =SUMIFS(#REF!,#REF!,$B60,#REF!,$C60,#REF!,$H$51) -> #REF! | AH60: =IF(MONTH(TODAY())>=$D11,K60-H60,"") | AI60: =IF(MONTH(TODAY())>=$D11,L60-I60,"") | AJ60: =IF(MONTH(TODAY())>=$D11,M60-J60,"") | AL60: =IF(MONTH(TODAY())>=$D11,AD60-X60,"") | AM60: =IF(MONTH(TODAY())>=$D11,AE60-Y60,"") | AN60: =IF(MONTH(TODAY())>=$D11,AF60-Z60,"") | AP60: =IF(MONTH(TODAY())>=$D11,AD60-X60,"") | AQ60: =IF(MONTH(TODAY())>=$D11,AE60-Y60,"") | AR60: =IF(MONTH(TODAY())>=$D11,AF60-Z60,"")
B61: >=7/1/24 | C61: <8/1/24 | D61: 7 | E61: =CONCATENATE(LEFT(B61,FIND(">=",B61) + 1),RIGHT(C61,LEN(C61) - (FIND("<",C61)))) -> >=8/1/24 | F61: July | G61: 0.0996 | H61: =ROUND(J61/$J$68*$H$68,0) -> 6 | I61: =J61/$J$68*$I$68 -> 56.787749 | J61: =J12-J101 -> 157683.33 | K61: =COUNTIFS(#REF!,$B61,#REF!,$C61,#REF!,$H$51) -> #REF! | L61: =SUMIFS(#REF!,#REF!,$B61,#REF!,$C61,#REF!,$H$51) -> #REF! | M61: =SUMIFS(#REF!,#REF!,$B61,#REF!,$C61,#REF!,$H$51) -> #REF! | N61: =COUNTIFS(#REF!,$B12,#REF!,$C12,#REF!,$H$51) -> #REF! | O61: =COUNTIFS(#REF!,$B61,#REF!,$C61,#REF!,$H$51) -> #REF! | P61: =IF(MONTH(TODAY())>=$D12,COUNTIFS(#REF!,$C61,#REF!,$H$51)-COUNTIFS(#REF!,$C61,#REF!,$H$51),"") | R61: =IF(MONTH(TODAY())>=$D12,COUNTIFS(#REF!,$C61,#REF!,$H$51)-COUNTIFS(#REF!,$C61,#REF!,$H$51),"") | S61: =COUNTIFS(#REF!,$B61,#REF!,$C61,#REF!,$H$51) -> #REF! | T61: =COUNTIFS(#REF!,$B61,#REF!,$C61,#REF!,$H$51) -> #REF! | U61: =IF(MONTH(TODAY())>=$D12,COUNTIFS(#REF!,$C61,#REF!,$H$51)-COUNTIFS(#REF!,$C61,#REF!,$H$51),"") | W61: =IF(MONTH(TODAY())>=$D12,COUNTIFS(#REF!,$C61,#REF!,$H$51)-COUNTIFS(#REF!,$C61,#REF!,$H$51),"") | X61: =X12-X101 -> 11 | Y61: =X61*10 -> 110 | Z61: =$Z$68/$X$68*X61 -> 305449.15 | AA61: =COUNTIFS(#REF!,$B61,#REF!,$C61,#REF!,$H$51) -> #REF! | AB61: =SUMIFS(#REF!,#REF!,$B61,#REF!,$C61,#REF!,$H$51) -> #REF! | AC61: =SUMIFS(#REF!,#REF!,$B61,#REF!,$C61,#REF!,$H$51) -> #REF! | AD61: =COUNTIFS(#REF!,$B61,#REF!,$C61,#REF!,$H$51) -> #REF! | AE61: =SUMIFS(#REF!,#REF!,$B61,#REF!,$C61,#REF!,$H$51) -> #REF! | AF61: =SUMIFS(#REF!,#REF!,$B61,#REF!,$C61,#REF!,$H$51) -> #REF! | AH61: =IF(MONTH(TODAY())>=$D12,K61-H61,"") | AI61: =IF(MONTH(TODAY())>=$D12,L61-I61,"") | AJ61: =IF(MONTH(TODAY())>=$D12,M61-J61,"") | AL61: =IF(MONTH(TODAY())>=$D12,AD61-X61,"") | AM61: =IF(MONTH(TODAY())>=$D12,AE61-Y61,"") | AN61: =IF(MONTH(TODAY())>=$D12,AF61-Z61,"") | AP61: =IF(MONTH(TODAY())>=$D12,AD61-X61,"") | AQ61: =IF(MONTH(TODAY())>=$D12,AE61-Y61,"") | AR61: =IF(MONTH(TODAY())>=$D12,AF61-Z61,"")
B62: >=8/1/24 | C62: <9/1/24 | D62: 8 | E62: =CONCATENATE(LEFT(B62,FIND(">=",B62) + 1),RIGHT(C62,LEN(C62) - (FIND("<",C62)))) -> >=9/1/24 | F62: August | G62: 0.0456 | H62: =ROUND(J62/$J$68*$H$68,0) -> 9 | I62: =J62/$J$68*$I$68 -> 93.593846 | J62: =J13-J102 -> 259883.33 | K62: =COUNTIFS(#REF!,$B62,#REF!,$C62,#REF!,$H$51) -> #REF! | L62: =SUMIFS(#REF!,#REF!,$B62,#REF!,$C62,#REF!,$H$51) -> #REF! | M62: =SUMIFS(#REF!,#REF!,$B62,#REF!,$C62,#REF!,$H$51) -> #REF! | N62: =COUNTIFS(#REF!,$B13,#REF!,$C13,#REF!,$H$51) -> #REF! | O62: =COUNTIFS(#REF!,$B62,#REF!,$C62,#REF!,$H$51) -> #REF! | P62: =IF(MONTH(TODAY())>=$D13,COUNTIFS(#REF!,$C62,#REF!,$H$51)-COUNTIFS(#REF!,$C62,#REF!,$H$51),"") | R62: =IF(MONTH(TODAY())>=$D13,COUNTIFS(#REF!,$C62,#REF!,$H$51)-COUNTIFS(#REF!,$C62,#REF!,$H$51),"") | S62: =COUNTIFS(#REF!,$B62,#REF!,$C62,#REF!,$H$51) -> #REF! | T62: =COUNTIFS(#REF!,$B62,#REF!,$C62,#REF!,$H$51) -> #REF! | U62: =IF(MONTH(TODAY())>=$D13,COUNTIFS(#REF!,$C62,#REF!,$H$51)-COUNTIFS(#REF!,$C62,#REF!,$H$51),"") | W62: =IF(MONTH(TODAY())>=$D13,COUNTIFS(#REF!,$C62,#REF!,$H$51)-COUNTIFS(#REF!,$C62,#REF!,$H$51),"") | X62: =X13-X102 -> 11 | Y62: =X62*10 -> 110 | Z62: =$Z$68/$X$68*X62 -> 305449.15 | AA62: =COUNTIFS(#REF!,$B62,#REF!,$C62,#REF!,$H$51) -> #REF! | AB62: =SUMIFS(#REF!,#REF!,$B62,#REF!,$C62,#REF!,$H$51) -> #REF! | AC62: =SUMIFS(#REF!,#REF!,$B62,#REF!,$C62,#REF!,$H$51) -> #REF! | AD62: =COUNTIFS(#REF!,$B62,#REF!,$C62,#REF!,$H$51) -> #REF! | AE62: =SUMIFS(#REF!,#REF!,$B62,#REF!,$C62,#REF!,$H$51) -> #REF! | AF62: =SUMIFS(#REF!,#REF!,$B62,#REF!,$C62,#REF!,$H$51) -> #REF! | AH62: =IF(MONTH(TODAY())>=$D13,K62-H62,"") | AI62: =IF(MONTH(TODAY())>=$D13,L62-I62,"") | AJ62: =IF(MONTH(TODAY())>=$D13,M62-J62,"") | AL62: =IF(MONTH(TODAY())>=$D13,AD62-X62,"") | AM62: =IF(MONTH(TODAY())>=$D13,AE62-Y62,"") | AN62: =IF(MONTH(TODAY())>=$D13,AF62-Z62,"") | AP62: =IF(MONTH(TODAY())>=$D13,AD62-X62,"") | AQ62: =IF(MONTH(TODAY())>=$D13,AE62-Y62,"") | AR62: =IF(MONTH(TODAY())>=$D13,AF62-Z62,"")
B63: >=9/1/24 | C63: <10/1/24 | D63: 9 | E63: =CONCATENATE(LEFT(B63,FIND(">=",B63) + 1),RIGHT(C63,LEN(C63) - (FIND("<",C63)))) -> >=10/1/24 | F63: September | G63: 0.0581 | H63: =ROUND(J63/$J$68*$H$68,0) -> 8 | I63: =J63/$J$68*$I$68 -> 80.484825 | J63: =J14-J103 -> 223483.33 | K63: =COUNTIFS(#REF!,$B63,#REF!,$C63,#REF!,$H$51) -> #REF! | L63: =SUMIFS(#REF!,#REF!,$B63,#REF!,$C63,#REF!,$H$51) -> #REF! | M63: =SUMIFS(#REF!,#REF!,$B63,#REF!,$C63,#REF!,$H$51) -> #REF! | N63: =COUNTIFS(#REF!,$B14,#REF!,$C14,#REF!,$H$51) -> #REF! | O63: =COUNTIFS(#REF!,$B63,#REF!,$C63,#REF!,$H$51) -> #REF! | P63: =IF(MONTH(TODAY())>=$D14,COUNTIFS(#REF!,$C63,#REF!,$H$51)-COUNTIFS(#REF!,$C63,#REF!,$H$51),"") | R63: =IF(MONTH(TODAY())>=$D14,COUNTIFS(#REF!,$C63,#REF!,$H$51)-COUNTIFS(#REF!,$C63,#REF!,$H$51),"") | S63: =COUNTIFS(#REF!,$B63,#REF!,$C63,#REF!,$H$51) -> #REF! | T63: =COUNTIFS(#REF!,$B63,#REF!,$C63,#REF!,$H$51) -> #REF! | U63: =IF(MONTH(TODAY())>=$D14,COUNTIFS(#REF!,$C63,#REF!,$H$51)-COUNTIFS(#REF!,$C63,#REF!,$H$51),"") | W63: =IF(MONTH(TODAY())>=$D14,COUNTIFS(#REF!,$C63,#REF!,$H$51)-COUNTIFS(#REF!,$C63,#REF!,$H$51),"") | X63: =X14-X103 -> 10 | Y63: =X63*10 -> 100 | Z63: =$Z$68/$X$68*X63 -> 277681.05 | AA63: =COUNTIFS(#REF!,$B63,#REF!,$C63,#REF!,$H$51) -> #REF! | AB63: =SUMIFS(#REF!,#REF!,$B63,#REF!,$C63,#REF!,$H$51) -> #REF! | AC63: =SUMIFS(#REF!,#REF!,$B63,#REF!,$C63,#REF!,$H$51) -> #REF! | AD63: =COUNTIFS(#REF!,$B63,#REF!,$C63,#REF!,$H$51) -> #REF! | AE63: =SUMIFS(#REF!,#REF!,$B63,#REF!,$C63,#REF!,$H$51) -> #REF! | AF63: =SUMIFS(#REF!,#REF!,$B63,#REF!,$C63,#REF!,$H$51) -> #REF! | AH63: =IF(MONTH(TODAY())>=$D14,K63-H63,"") | AI63: =IF(MONTH(TODAY())>=$D14,L63-I63,"") | AJ63: =IF(MONTH(TODAY())>=$D14,M63-J63,"") | AL63: =IF(MONTH(TODAY())>=$D14,AD63-X63,"") | AM63: =IF(MONTH(TODAY())>=$D14,AE63-Y63,"") | AN63: =IF(MONTH(TODAY())>=$D14,AF63-Z63,"") | AP63: =IF(MONTH(TODAY())>=$D14,AD63-X63,"") | AQ63: =IF(MONTH(TODAY())>=$D14,AE63-Y63,"") | AR63: =IF(MONTH(TODAY())>=$D14,AF63-Z63,"")
B64: >=10/1/24 | C64: <11/1/24 | D64: 10 | E64: =CONCATENATE(LEFT(B64,FIND(">=",B64) + 1),RIGHT(C64,LEN(C64) - (FIND("<",C64)))) -> >=11/1/24 | F64: October | G64: 0.0996 | H64: =ROUND(J64/$J$68*$H$68,0) -> 13 | I64: =J64/$J$68*$I$68 -> 133.10698 | J64: =J15-J104 -> 369600 | K64: =COUNTIFS(#REF!,$B64,#REF!,$C64,#REF!,$H$51) -> #REF! | L64: =SUMIFS(#REF!,#REF!,$B64,#REF!,$C64,#REF!,$H$51) -> #REF! | M64: =SUMIFS(#REF!,#REF!,$B64,#REF!,$C64,#REF!,$H$51) -> #REF! | N64: =COUNTIFS(#REF!,$B15,#REF!,$C15,#REF!,$H$51) -> #REF! | O64: =COUNTIFS(#REF!,$B64,#REF!,$C64,#REF!,$H$51) -> #REF! | P64: =IF(MONTH(TODAY())>=$D15,COUNTIFS(#REF!,$C64,#REF!,$H$51)-COUNTIFS(#REF!,$C64,#REF!,$H$51),"") | R64: =IF(MONTH(TODAY())>=$D15,COUNTIFS(#REF!,$C64,#REF!,$H$51)-COUNTIFS(#REF!,$C64,#REF!,$H$51),"") | S64: =COUNTIFS(#REF!,$B64,#REF!,$C64,#REF!,$H$51) -> #REF! | T64: =COUNTIFS(#REF!,$B64,#REF!,$C64,#REF!,$H$51) -> #REF! | U64: =IF(MONTH(TODAY())>=$D15,COUNTIFS(#REF!,$C64,#REF!,$H$51)-COUNTIFS(#REF!,$C64,#REF!,$H$51),"") | W64: =IF(MONTH(TODAY())>=$D15,COUNTIFS(#REF!,$C64,#REF!,$H$51)-COUNTIFS(#REF!,$C64,#REF!,$H$51),"") | X64: =X15-X104 -> 11 | Y64: =X64*10 -> 110 | Z64: =$Z$68/$X$68*X64 -> 305449.15 | AA64: =COUNTIFS(#REF!,$B64,#REF!,$C64,#REF!,$H$51) -> #REF! | AB64: =SUMIFS(#REF!,#REF!,$B64,#REF!,$C64,#REF!,$H$51) -> #REF! | AC64: =SUMIFS(#REF!,#REF!,$B64,#REF!,$C64,#REF!,$H$51) -> #REF! | AD64: =COUNTIFS(#REF!,$B64,#REF!,$C64,#REF!,$H$51) -> #REF! | AE64: =SUMIFS(#REF!,#REF!,$B64,#REF!,$C64,#REF!,$H$51) -> #REF! | AF64: =SUMIFS(#REF!,#REF!,$B64,#REF!,$C64,#REF!,$H$51) -> #REF! | AH64: =IF(MONTH(TODAY())>=$D15,K64-H64,"") | AI64: =IF(MONTH(TODAY())>=$D15,L64-I64,"") | AJ64: =IF(MONTH(TODAY())>=$D15,M64-J64,"") | AL64: =IF(MONTH(TODAY())>=$D15,AD64-X64,"") | AM64: =IF(MONTH(TODAY())>=$D15,AE64-Y64,"") | AN64: =IF(MONTH(TODAY())>=$D15,AF64-Z64,"") | AP64: =IF(MONTH(TODAY())>=$D15,AD64-X64,"") | AQ64: =IF(MONTH(TODAY())>=$D15,AE64-Y64,"") | AR64: =IF(MONTH(TODAY())>=$D15,AF64-Z64,"")
B65: >=11/1/24 | C65: <12/1/24 | D65: 11 | E65: =CONCATENATE(LEFT(B65,FIND(">=",B65) + 1),RIGHT(C65,LEN(C65) - (FIND("<",C65)))) -> >=12/1/24 | F65: November | G65: 0.0954 | H65: =ROUND(J65/$J$68*$H$68,0) -> 8 | I65: =J65/$J$68*$I$68 -> 82.309524 | J65: =J16-J105 -> 228550 | K65: =COUNTIFS(#REF!,$B65,#REF!,$C65,#REF!,$H$51) -> #REF! | L65: =SUMIFS(#REF!,#REF!,$B65,#REF!,$C65,#REF!,$H$51) -> #REF! | M65: =SUMIFS(#REF!,#REF!,$B65,#REF!,$C65,#REF!,$H$51) -> #REF! | N65: =COUNTIFS(#REF!,$B16,#REF!,$C16,#REF!,$H$51) -> #REF! | O65: =COUNTIFS(#REF!,$B65,#REF!,$C65,#REF!,$H$51) -> #REF! | P65: =IF(MONTH(TODAY())>=$D16,COUNTIFS(#REF!,$C65,#REF!,$H$51)-COUNTIFS(#REF!,$C65,#REF!,$H$51),"") | R65: =IF(MONTH(TODAY())>=$D16,COUNTIFS(#REF!,$C65,#REF!,$H$51)-COUNTIFS(#REF!,$C65,#REF!,$H$51),"") | S65: =COUNTIFS(#REF!,$B65,#REF!,$C65,#REF!,$H$51) -> #REF! | T65: =COUNTIFS(#REF!,$B65,#REF!,$C65,#REF!,$H$51) -> #REF! | U65: =IF(MONTH(TODAY())>=$D16,COUNTIFS(#REF!,$C65,#REF!,$H$51)-COUNTIFS(#REF!,$C65,#REF!,$H$51),"") | W65: =IF(MONTH(TODAY())>=$D16,COUNTIFS(#REF!,$C65,#REF!,$H$51)-COUNTIFS(#REF!,$C65,#REF!,$H$51),"") | X65: =X16-X105 -> 9 | Y65: =X65*10 -> 90 | Z65: =$Z$68/$X$68*X65 -> 249912.94 | AA65: =COUNTIFS(#REF!,$B65,#REF!,$C65,#REF!,$H$51) -> #REF! | AB65: =SUMIFS(#REF!,#REF!,$B65,#REF!,$C65,#REF!,$H$51) -> #REF! | AC65: =SUMIFS(#REF!,#REF!,$B65,#REF!,$C65,#REF!,$H$51) -> #REF! | AD65: =COUNTIFS(#REF!,$B65,#REF!,$C65,#REF!,$H$51) -> #REF! | AE65: =SUMIFS(#REF!,#REF!,$B65,#REF!,$C65,#REF!,$H$51) -> #REF! | AF65: =SUMIFS(#REF!,#REF!,$B65,#REF!,$C65,#REF!,$H$51) -> #REF! | AH65: =IF(MONTH(TODAY())>=$D16,K65-H65,"") | AI65: =IF(MONTH(TODAY())>=$D16,L65-I65,"") | AJ65: =IF(MONTH(TODAY())>=$D16,M65-J65,"") | AL65: =IF(MONTH(TODAY())>=$D16,AD65-X65,"") | AM65: =IF(MONTH(TODAY())>=$D16,AE65-Y65,"") | AN65: =IF(MONTH(TODAY())>=$D16,AF65-Z65,"") | AP65: =IF(MONTH(TODAY())>=$D16,AD65-X65,"") | AQ65: =IF(MONTH(TODAY())>=$D16,AE65-Y65,"") | AR65: =IF(MONTH(TODAY())>=$D16,AF65-Z65,"")
B66: >=12/1/24 | C66: <1/1/25 | D66: 12 | E66: =CONCATENATE(LEFT(B66,FIND(">=",B66) + 1),RIGHT(C66,LEN(C66) - (FIND("<",C66)))) -> >=1/1/25 | F66: December | G66: 0.0622 | H66: =ROUND(J66/$J$68*$H$68,0) -> 10 | I66: =J66/$J$68*$I$68 -> 102.22515 | J66: =J17-J106 -> 283850 | K66: =COUNTIFS(#REF!,$B66,#REF!,$C66,#REF!,$H$51) -> #REF! | L66: =SUMIFS(#REF!,#REF!,$B66,#REF!,$C66,#REF!,$H$51) -> #REF! | M66: =SUMIFS(#REF!,#REF!,$B66,#REF!,$C66,#REF!,$H$51) -> #REF! | N66: =COUNTIFS(#REF!,$B17,#REF!,$C17,#REF!,$H$51) -> #REF! | O66: =COUNTIFS(#REF!,$B66,#REF!,$C66,#REF!,$H$51) -> #REF! | P66: =IF(MONTH(TODAY())>=$D17,COUNTIFS(#REF!,$C66,#REF!,$H$51)-COUNTIFS(#REF!,$C66,#REF!,$H$51),"") | R66: =IF(MONTH(TODAY())>=$D17,COUNTIFS(#REF!,$C66,#REF!,$H$51)-COUNTIFS(#REF!,$C66,#REF!,$H$51),"") | S66: =COUNTIFS(#REF!,$B66,#REF!,$C66,#REF!,$H$51) -> #REF! | T66: =COUNTIFS(#REF!,$B66,#REF!,$C66,#REF!,$H$51) -> #REF! | U66: =IF(MONTH(TODAY())>=$D17,COUNTIFS(#REF!,$C66,#REF!,$H$51)-COUNTIFS(#REF!,$C66,#REF!,$H$51),"") | W66: =IF(MONTH(TODAY())>=$D17,COUNTIFS(#REF!,$C66,#REF!,$H$51)-COUNTIFS(#REF!,$C66,#REF!,$H$51),"") | X66: =X17-X106 -> 6 | Y66: =X66*10 -> 60 | Z66: =$Z$68/$X$68*X66 -> 166608.63 | AA66: =COUNTIFS(#REF!,$B66,#REF!,$C66,#REF!,$H$51) -> #REF! | AB66: =SUMIFS(#REF!,#REF!,$B66,#REF!,$C66,#REF!,$H$51) -> #REF! | AC66: =SUMIFS(#REF!,#REF!,$B66,#REF!,$C66,#REF!,$H$51) -> #REF! | AD66: =COUNTIFS(#REF!,$B66,#REF!,$C66,#REF!,$H$51) -> #REF! | AE66: =SUMIFS(#REF!,#REF!,$B66,#REF!,$C66,#REF!,$H$51) -> #REF! | AF66: =SUMIFS(#REF!,#REF!,$B66,#REF!,$C66,#REF!,$H$51) -> #REF! | AH66: =IF(MONTH(TODAY())>=$D17,K66-H66,"") | AI66: =IF(MONTH(TODAY())>=$D17,L66-I66,"") | AJ66: =IF(MONTH(TODAY())>=$D17,M66-J66,"") | AL66: =IF(MONTH(TODAY())>=$D17,AD66-X66,"") | AM66: =IF(MONTH(TODAY())>=$D17,AE66-Y66,"") | AN66: =IF(MONTH(TODAY())>=$D17,AF66-Z66,"") | AP66: =IF(MONTH(TODAY())>=$D17,AD66-X66,"") | AQ66: =IF(MONTH(TODAY())>=$D17,AE66-Y66,"") | AR66: =IF(MONTH(TODAY())>=$D17,AF66-Z66,"")
B67: >=1/1/25 | C67: <1/1/26 | E67: =CONCATENATE(LEFT(B67,FIND(">=",B67) + 1),RIGHT(C67,LEN(C67) - (FIND("<",C67)))) -> >=1/1/26 | F67: 2025 | G67: N/A | K67: =COUNTIFS(#REF!,$B67,#REF!,$C67,#REF!,$H$51) -> #REF! | L67: =SUMIFS(#REF!,#REF!,$B67,#REF!,$C67,#REF!,$H$51) -> #REF! | M67: =SUMIFS(#REF!,#REF!,$B67,#REF!,$C67,#REF!,$H$51) -> #REF! | S67: =COUNTIFS(#REF!,$B67,#REF!,$C67,#REF!,$H$51) -> #REF! | T67: =COUNTIFS(#REF!,$B67,#REF!,$C67,#REF!,$H$51) -> #REF! | AA67: =COUNTIFS(#REF!,$B67,#REF!,$C67,#REF!,$H$51) -> #REF! | AB67: =SUMIFS(#REF!,#REF!,$B67,#REF!,$C67,#REF!,$H$51) -> #REF! | AC67: =SUMIFS(#REF!,#REF!,$B67,#REF!,$C67,#REF!,$H$51) -> #REF!
F68: Total | G68: N/A | H68: =100*1.0444 -> 104.44 | I68: =1000*1.0444 -> 1044.4 | J68: =2900000 -> 2900000 | K68: =SUM(K54:K67) -> #REF! | L68: =SUM(L54:L67) -> #REF! | M68: =SUM(M54:M67) -> #REF! | N68: =SUM(N54:N67) -> #REF! | O68: =SUM(O54:O67) -> #REF! | P68: =INDEX(P54:P67,MONTH(TODAY())+1) -> #REF! | Q68: =INDEX(Q54:Q67,MONTH(TODAY())+1) | R68: =INDEX(R54:R67,MONTH(TODAY())+1) -> #REF! | S68: =SUM(S54:S67) -> #REF! | T68: =SUM(T54:T67) -> #REF! | U68: =INDEX(U54:U67,MONTH(TODAY())+1) -> #REF! | V68: =INDEX(V54:V67,MONTH(TODAY())+1) | W68: =INDEX(W54:W67,MONTH(TODAY())+1) -> #REF! | X68: =SUM(X54:X67) -> 100 | Y68: =SUM(Y54:Y67) -> 1000 | Z68: =J68/J19*Z19 -> 2776810.5 | AA68: =SUM(AA54:AA67) -> #REF! | AB68: =SUM(AB54:AB67) -> #REF! | AC68: =SUM(AC54:AC67) -> #REF! | AD68: =SUM(AD54:AD67) -> #REF! | AE68: =SUM(AE54:AE67) -> #REF! | AF68: =SUM(AF54:AF67) -> #REF! | AH68: =SUM(AH55:AH66) -> #REF! | AI68: =SUM(AI55:AI67) -> #REF! | AJ68: =SUM(AJ55:AJ67) -> #REF! | AL68: =SUM(AL55:AL67) -> #REF! | AM68: =SUM(AM55:AM67) -> #REF! | AN68: =SUM(AN55:AN67) -> #REF! | AP68: =SUM(AP54:AP67) -> #REF! | AQ68: =SUM(AQ54:AQ67) -> #REF! | AR68: =SUM(AR54:AR67) -> #REF!
F69: Total* | G69: N/A | K69: =SUM(K55:K66) -> #REF! | L69: =SUM(L55:L66) -> #REF! | M69: =SUM(M55:M66) -> #REF! | N69: =SUM(N55:N66) -> #REF! | O69: =SUM(O55:O66) -> #REF! | S69: =SUM(S55:S66) -> #REF! | T69: =SUM(T55:T66) -> #REF! | X69: =SUM(X55:X66) -> 100 | Y69: =SUM(Y55:Y66) -> 1000 | Z69: =SUM(Z55:Z66) -> 2776810.5 | AA69: =SUM(AA54:AA67) -> #REF! | AB69: =SUM(AB54:AB67) -> #REF! | AC69: =SUM(AC54:AC67) -> #REF! | AP69: =SUM(AP55:AP66) -> #REF! | AQ69: =SUM(AQ55:AQ66) -> #REF! | AR69: =SUM(AR55:AR66) -> #REF!
J71: 2450980
AH72: Bookings | AL72: Installs
F73: Month | AF73: # of Months Left | AH73: Average monthly residential bookings needed to be in line with Budgeted Goals | AL73: Average monthly residential installs needed to be in line with Budgeted Goals
F74: January | AF74: 12 | AH74: =IF(MONTH(TODAY())=$D6,$AH$86/$AF74,"") | AI74: =IF(MONTH(TODAY())=$D6,$AI$86/$AF74,"") | AJ74: =IF(MONTH(TODAY())=$D6,$AJ$86/AF74,"") | AL74: =IF(MONTH(TODAY())=$D6,$AL$86/$AF74,"") | AM74: =IF(MONTH(TODAY())=$D6,$AM$86/$AF74,"") | AN74: =IF(MONTH(TODAY())=$D6,$AN$86/AF74,"")
F75: February | AF75: 11 | AH75: =IF(MONTH(TODAY())=$D7,$AH$86/$AF75,"") | AI75: =IF(MONTH(TODAY())=$D7,$AI$86/$AF75,"") | AJ75: =IF(MONTH(TODAY())=$D7,$AJ$86/AF75,"") | AL75: =IF(MONTH(TODAY())=$D7,$AL$86/$AF75,"") | AM75: =IF(MONTH(TODAY())=$D7,$AM$86/$AF75,"") | AN75: =IF(MONTH(TODAY())=$D7,$AN$86/AF75,"")
F76: March | AF76: 10 | AH76: =IF(MONTH(TODAY())=$D8,$AH$86/$AF76,"") -> #REF! | AI76: =IF(MONTH(TODAY())=$D8,$AI$86/$AF76,"") -> #REF! | AJ76: =IF(MONTH(TODAY())=$D8,$AJ$86/AF76,"") -> #REF! | AL76: =IF(MONTH(TODAY())=$D8,$AL$86/$AF76,"") -> #REF! | AM76: =IF(MONTH(TODAY())=$D8,$AM$86/$AF76,"") -> #REF! | AN76: =IF(MONTH(TODAY())=$D8,$AN$86/AF76,"") -> #REF!
F77: April | AF77: 9 | AH77: =IF(MONTH(TODAY())=$D9,$AH$86/$AF77,"") | AI77: =IF(MONTH(TODAY())=$D9,$AI$86/$AF77,"") | AJ77: =IF(MONTH(TODAY())=$D9,$AJ$86/AF77,"") | AL77: =IF(MONTH(TODAY())=$D9,$AL$86/$AF77,"") | AM77: =IF(MONTH(TODAY())=$D9,$AM$86/$AF77,"") | AN77: =IF(MONTH(TODAY())=$D9,$AN$86/AF77,"")
F78: May | AF78: 8 | AH78: =IF(MONTH(TODAY())=$D10,$AH$86/$AF78,"") | AI78: =IF(MONTH(TODAY())=$D10,$AI$86/$AF78,"") | AJ78: =IF(MONTH(TODAY())=$D10,$AJ$86/AF78,"") | AL78: =IF(MONTH(TODAY())=$D10,$AL$86/$AF78,"") | AM78: =IF(MONTH(TODAY())=$D10,$AM$86/$AF78,"") | AN78: =IF(MONTH(TODAY())=$D10,$AN$86/AF78,"")
F79: June | AF79: 7 | AH79: =IF(MONTH(TODAY())=$D11,$AH$86/$AF79,"") | AI79: =IF(MONTH(TODAY())=$D11,$AI$86/$AF79,"") | AJ79: =IF(MONTH(TODAY())=$D11,$AJ$86/AF79,"") | AL79: =IF(MONTH(TODAY())=$D11,$AL$86/$AF79,"") | AM79: =IF(MONTH(TODAY())=$D11,$AM$86/$AF79,"") | AN79: =IF(MONTH(TODAY())=$D11,$AN$86/AF79,"")
F80: July | AF80: 6 | AH80: =IF(MONTH(TODAY())=$D12,$AH$86/$AF80,"") | AI80: =IF(MONTH(TODAY())=$D12,$AI$86/$AF80,"") | AJ80: =IF(MONTH(TODAY())=$D12,$AJ$86/AF80,"") | AL80: =IF(MONTH(TODAY())=$D12,$AL$86/$AF80,"") | AM80: =IF(MONTH(TODAY())=$D12,$AM$86/$AF80,"") | AN80: =IF(MONTH(TODAY())=$D12,$AN$86/AF80,"")
F81: August | AF81: 5 | AH81: =IF(MONTH(TODAY())=$D13,$AH$86/$AF81,"") | AI81: =IF(MONTH(TODAY())=$D13,$AI$86/$AF81,"") | AJ81: =IF(MONTH(TODAY())=$D13,$AJ$86/AF81,"") | AL81: =IF(MONTH(TODAY())=$D13,$AL$86/$AF81,"") | AM81: =IF(MONTH(TODAY())=$D13,$AM$86/$AF81,"") | AN81: =IF(MONTH(TODAY())=$D13,$AN$86/AF81,"")
F82: September | AF82: 4 | AH82: =IF(MONTH(TODAY())=$D14,$AH$86/$AF82,"") | AI82: =IF(MONTH(TODAY())=$D14,$AI$86/$AF82,"") | AJ82: =IF(MONTH(TODAY())=$D14,$AJ$86/AF82,"") | AL82: =IF(MONTH(TODAY())=$D14,$AL$86/$AF82,"") | AM82: =IF(MONTH(TODAY())=$D14,$AM$86/$AF82,"") | AN82: =IF(MONTH(TODAY())=$D14,$AN$86/AF82,"")
F83: October | AF83: 3 | AH83: =IF(MONTH(TODAY())=$D15,$AH$86/$AF83,"") | AI83: =IF(MONTH(TODAY())=$D15,$AI$86/$AF83,"") | AJ83: =IF(MONTH(TODAY())=$D15,$AJ$86/AF83,"") | AL83: =IF(MONTH(TODAY())=$D15,$AL$86/$AF83,"") | AM83: =IF(MONTH(TODAY())=$D15,$AM$86/$AF83,"") | AN83: =IF(MONTH(TODAY())=$D15,$AN$86/AF83,"")
F84: November | AF84: 2 | AH84: =IF(MONTH(TODAY())=$D16,$AH$86/$AF84,"") | AI84: =IF(MONTH(TODAY())=$D16,$AI$86/$AF84,"") | AJ84: =IF(MONTH(TODAY())=$D16,$AJ$86/AF84,"") | AL84: =IF(MONTH(TODAY())=$D16,$AL$86/$AF84,"") | AM84: =IF(MONTH(TODAY())=$D16,$AM$86/$AF84,"") | AN84: =IF(MONTH(TODAY())=$D16,$AN$86/AF84,"")
F85: December | AF85: 1 | AH85: =IF(MONTH(TODAY())=$D17,$AH$86/$AF85,"") | AI85: =IF(MONTH(TODAY())=$D17,$AI$86/$AF85,"") | AJ85: =IF(MONTH(TODAY())=$D17,$AJ$86/AF85,"") | AL85: =IF(MONTH(TODAY())=$D17,$AL$86/$AF85,"") | AM85: =IF(MONTH(TODAY())=$D17,$AM$86/$AF85,"") | AN85: =IF(MONTH(TODAY())=$D17,$AN$86/AF85,"")
F86: Total | AH86: =H68-K69 -> #REF! | AI86: =I68-L69 -> #REF! | AJ86: =J68-M69 -> #REF! | AL86: =X68-AD68 -> #REF! | AM86: =Y68-AE68 -> #REF! | AN86: =Z68-AF68 -> #REF!
H91: COMMERCIAL
H92: Budgetted Bookings | K92: Actual Bookings | N92: Permits | S92: Utility Applications | X92: Budgetted Install Schedule | AA92: Planned Installs at Contract Signing | AD92: Actual Installations | AH92: Budgeted Bookings vs Actual Bookings | AL92: Budgeted Installs vs Actual Installs | AP92: Planned Installs at Contract vs Actual Install
F93: Month | G93: 2023 % of Bookings Per Month | H93: QTY Booked | I93: kW Booked | J93: Contract Value of Booked Systems | K93: QTY Booked | L93: kW Booked | M93: Contract Value of Booked Systems | N93: Permits Submitted | O93: Permits Approved | P93: Jobs with Unsubmitted Permits | Q93: Outstanding Submitted Permits MTD or at Months End | R93: Total Approved But Uninstalled Permits MTD or at Month End | S93: Utility Applications Submitted | T93: Utility Applications Approved | U93: Jobs with Unsubmitted Utility Applications | V93: Outstanding Submitted Utility Applications MTD or at Months End | W93: Total Approved but Uninstalled Utility Applications MTD or at Months End | X93: QTY Installed | Y93: kW Installed | Z93: Contract Value of Installed Systems | AA93: QTY Installed | AB93: kW Installed | AC93: Contract Value of Installed Systems | AD93: QTY Installed | AE93: kW Installed | AF93: Contract Value of Installed Systems | AH93: QTY Booked | AI93: kW Booked | AJ93: Contract Value of Booked Systems | AL93: QTY Installed | AM93: kW Installed | AN93: Contract Value of Installed Systems | AP93: QTY Installed | AQ93: kW Installed | AR93: Contract Value of Installed Systems
B94: >=1/1/23 | C94: <1/1/24 | D94: 0 | E94: =CONCATENATE(LEFT(B94,FIND(">=",B94) + 1),RIGHT(C94,LEN(C94) - (FIND("<",C94)))) -> >=1/1/24 | F94: 2023 | G94: N/A | K94: =COUNTIFS(#REF!,$B94,#REF!,$C94,#REF!,$H$91) -> #REF! | L94: =SUMIFS(#REF!,#REF!,$B94,#REF!,$C94,#REF!,$H$91) -> #REF! | M94: =SUMIFS(#REF!,#REF!,$B94,#REF!,$C94,#REF!,$H$91) -> #REF! | N94: =COUNTIFS(#REF!,$B5,#REF!,$C5,#REF!,$H$91) -> #REF! | O94: =COUNTIFS(#REF!,$B54,#REF!,$C54,#REF!,$H$91) -> #REF! | P94: =IF(MONTH(TODAY())>=$D5,COUNTIFS(#REF!,$C54,#REF!,$H$91)-COUNTIFS(#REF!,$C54,#REF!,$H$91),"") -> #REF! | Q94: 0 | R94: =IF(MONTH(TODAY())>=$D5,COUNTIFS(#REF!,$C54,#REF!,$H$91)-COUNTIFS(#REF!,$C54,#REF!,$H$91),"") -> #REF! | S94: =COUNTIFS(#REF!,$B54,#REF!,$C54,#REF!,$H$91) -> #REF! | T94: =COUNTIFS(#REF!,$B54,#REF!,$C54,#REF!,$H$91) -> #REF! | U94: =IF(MONTH(TODAY())>=$D5,COUNTIFS(#REF!,$C54,#REF!,$H$91)-COUNTIFS(#REF!,$C54,#REF!,$H$91),"") -> #REF! | V94: 0 | W94: =IF(MONTH(TODAY())>=$D5,COUNTIFS(#REF!,$C54,#REF!,$H$91)-COUNTIFS(#REF!,$C54,#REF!,$H$91),"") -> #REF! | AA94: =COUNTIFS(#REF!,$B94,#REF!,$C94,#REF!,$H$91) -> #REF! | AB94: =SUMIFS(#REF!,#REF!,$B94,#REF!,$C94,#REF!,$H$91) -> #REF! | AC94: =SUMIFS(#REF!,#REF!,$B94,#REF!,$C94,#REF!,$H$91) -> #REF! | AD94: =COUNTIFS(#REF!,$B94,#REF!,$C94,#REF!,$H$91) -> #REF! | AE94: =SUMIFS(#REF!,#REF!,$B94,#REF!,$C94,#REF!,$H$91) -> #REF! | AF94: =SUMIFS(#REF!,#REF!,$B94,#REF!,$C94,#REF!,$H$91) -> #REF! | AP94: =IF(MONTH(TODAY())>=$D5,AD94-AA94,"") -> #REF! | AQ94: =IF(MONTH(TODAY())>=$D5,AE94-AB94,"") -> #REF! | AR94: =IF(MONTH(TODAY())>=$D5,AF94-AC94,"") -> #REF!
B95: >=1/1/24 | C95: <2/1/24 | D95: 1 | E95: =CONCATENATE(LEFT(B95,FIND(">=",B95) + 1),RIGHT(C95,LEN(C95) - (FIND("<",C95)))) -> >=2/1/24 | F95: January | G95: N/A | H95: 1 | I95: =$I$108/$H$108*H95 -> 49.661258 | J95: =$J$108/$H$108*H95 -> 66666.667 | K95: =COUNTIFS(#REF!,$B95,#REF!,$C95,#REF!,$H$91) -> #REF! | L95: =SUMIFS(#REF!,#REF!,$B95,#REF!,$C95,#REF!,$H$91) -> #REF! | M95: =SUMIFS(#REF!,#REF!,$B95,#REF!,$C95,#REF!,$H$91) -> #REF! | N95: =COUNTIFS(#REF!,$B6,#REF!,$C6,#REF!,$H$91) -> #REF! | O95: =COUNTIFS(#REF!,$B55,#REF!,$C55,#REF!,$H$91) -> #REF! | P95: =IF(MONTH(TODAY())>=$D6,COUNTIFS(#REF!,$C55,#REF!,$H$91)-COUNTIFS(#REF!,$C55,#REF!,$H$91),"") -> #REF! | Q95: 0 | R95: =IF(MONTH(TODAY())>=$D6,COUNTIFS(#REF!,$C55,#REF!,$H$91)-COUNTIFS(#REF!,$C55,#REF!,$H$91),"") -> #REF! | S95: =COUNTIFS(#REF!,$B55,#REF!,$C55,#REF!,$H$91) -> #REF! | T95: =COUNTIFS(#REF!,$B55,#REF!,$C55,#REF!,$H$91) -> #REF! | U95: =IF(MONTH(TODAY())>=$D6,COUNTIFS(#REF!,$C55,#REF!,$H$91)-COUNTIFS(#REF!,$C55,#REF!,$H$91),"") -> #REF! | V95: 0 | W95: =IF(MONTH(TODAY())>=$D6,COUNTIFS(#REF!,$C55,#REF!,$H$91)-COUNTIFS(#REF!,$C55,#REF!,$H$91),"") -> #REF! | X95: 0 | Y95: =X95*47.6 -> 0 | Z95: =$Z$68/$X$68*X95 -> 0 | AA95: =COUNTIFS(#REF!,$B95,#REF!,$C95,#REF!,$H$91) -> #REF! | AB95: =SUMIFS(#REF!,#REF!,$B95,#REF!,$C95,#REF!,$H$91) -> #REF! | AC95: =SUMIFS(#REF!,#REF!,$B95,#REF!,$C95,#REF!,$H$91) -> #REF! | AD95: =COUNTIFS(#REF!,$B95,#REF!,$C95,#REF!,$H$91) -> #REF! | AE95: =SUMIFS(#REF!,#REF!,$B95,#REF!,$C95,#REF!,$H$91) -> #REF! | AF95: =SUMIFS(#REF!,#REF!,$B95,#REF!,$C95,#REF!,$H$91) -> #REF! | AH95: =IF(MONTH(TODAY())>=$D6,K95-H95,"") -> #REF! | AI95: =IF(MONTH(TODAY())>=$D6,L95-I95,"") -> #REF! | AJ95: =IF(MONTH(TODAY())>=$D6,M95-J95,"") -> #REF! | AL95: =IF(MONTH(TODAY())>=$D6,AD95-X95,"") -> #REF! | AM95: =IF(MONTH(TODAY())>=$D6,AE95-Y95,"") -> #REF! | AN95: =IF(MONTH(TODAY())>=$D6,AF95-Z95,"") -> #REF! | AP95: =IF(MONTH(TODAY())>=$D6,AD95-AA95,"") -> #REF! | AQ95: =IF(MONTH(TODAY())>=$D6,AE95-AB95,"") -> #REF! | AR95: =IF(MONTH(TODAY())>=$D6,AF95-AC95,"") -> #REF!
B96: >=2/1/24 | C96: <3/1/24 | D96: 2 | E96: =CONCATENATE(LEFT(B96,FIND(">=",B96) + 1),RIGHT(C96,LEN(C96) - (FIND("<",C96)))) -> >=3/1/24 | F96: February | G96: N/A | H96: 1 | I96: =$I$108/$H$108*H96 -> 49.661258 | J96: =$J$108/$H$108*H96 -> 66666.667 | K96: =COUNTIFS(#REF!,$B96,#REF!,$C96,#REF!,$H$91) -> #REF! | L96: =SUMIFS(#REF!,#REF!,$B96,#REF!,$C96,#REF!,$H$91) -> #REF! | M96: =SUMIFS(#REF!,#REF!,$B96,#REF!,$C96,#REF!,$H$91) -> #REF! | N96: =COUNTIFS(#REF!,$B7,#REF!,$C7,#REF!,$H$91) -> #REF! | O96: =COUNTIFS(#REF!,$B56,#REF!,$C56,#REF!,$H$91) -> #REF! | P96: =IF(MONTH(TODAY())>=$D7,COUNTIFS(#REF!,$C56,#REF!,$H$91)-COUNTIFS(#REF!,$C56,#REF!,$H$91),"") -> #REF! | R96: =IF(MONTH(TODAY())>=$D7,COUNTIFS(#REF!,$C56,#REF!,$H$91)-COUNTIFS(#REF!,$C56,#REF!,$H$91),"") -> #REF! | S96: =COUNTIFS(#REF!,$B56,#REF!,$C56,#REF!,$H$91) -> #REF! | T96: =COUNTIFS(#REF!,$B56,#REF!,$C56,#REF!,$H$91) -> #REF! | U96: =IF(MONTH(TODAY())>=$D7,COUNTIFS(#REF!,$C56,#REF!,$H$91)-COUNTIFS(#REF!,$C56,#REF!,$H$91),"") -> #REF! | W96: =IF(MONTH(TODAY())>=$D7,COUNTIFS(#REF!,$C56,#REF!,$H$91)-COUNTIFS(#REF!,$C56,#REF!,$H$91),"") -> #REF! | X96: 0 | Y96: =X96*428/$X$108 -> 0 | Z96: =$Z$68/$X$68*X96 -> 0 | AA96: =COUNTIFS(#REF!,$B96,#REF!,$C96,#REF!,$H$91) -> #REF! | AB96: =SUMIFS(#REF!,#REF!,$B96,#REF!,$C96,#REF!,$H$91) -> #REF! | AC96: =SUMIFS(#REF!,#REF!,$B96,#REF!,$C96,#REF!,$H$91) -> #REF! | AD96: =COUNTIFS(#REF!,$B96,#REF!,$C96,#REF!,$H$91) -> #REF! | AE96: =SUMIFS(#REF!,#REF!,$B96,#REF!,$C96,#REF!,$H$91) -> #REF! | AF96: =SUMIFS(#REF!,#REF!,$B96,#REF!,$C96,#REF!,$H$91) -> #REF! | AH96: =IF(MONTH(TODAY())>=$D7,K96-H96,"") -> #REF! | AI96: =IF(MONTH(TODAY())>=$D7,L96-I96,"") -> #REF! | AJ96: =IF(MONTH(TODAY())>=$D7,M96-J96,"") -> #REF! | AL96: =IF(MONTH(TODAY())>=$D7,AD96-X96,"") -> #REF! | AM96: =IF(MONTH(TODAY())>=$D7,AE96-Y96,"") -> #REF! | AN96: =IF(MONTH(TODAY())>=$D7,AF96-Z96,"") -> #REF! | AP96: =IF(MONTH(TODAY())>=$D7,AD96-AA96,"") -> #REF! | AQ96: =IF(MONTH(TODAY())>=$D7,AE96-AB96,"") -> #REF! | AR96: =IF(MONTH(TODAY())>=$D7,AF96-AC96,"") -> #REF!
B97: >=3/1/24 | C97: <4/1/24 | D97: 3 | E97: =CONCATENATE(LEFT(B97,FIND(">=",B97) + 1),RIGHT(C97,LEN(C97) - (FIND("<",C97)))) -> >=4/1/24 | F97: March | G97: N/A | H97: 1 | I97: =$I$108/$H$108*H97 -> 49.661258 | J97: =$J$108/$H$108*H97 -> 66666.667 | K97: =COUNTIFS(#REF!,$B97,#REF!,$C97,#REF!,$H$91) -> #REF! | L97: =SUMIFS(#REF!,#REF!,$B97,#REF!,$C97,#REF!,$H$91) -> #REF! | M97: =SUMIFS(#REF!,#REF!,$B97,#REF!,$C97,#REF!,$H$91) -> #REF! | N97: =COUNTIFS(#REF!,$B8,#REF!,$C8,#REF!,$H$91) -> #REF! | O97: =COUNTIFS(#REF!,$B57,#REF!,$C57,#REF!,$H$91) -> #REF! | P97: =IF(MONTH(TODAY())>=$D8,COUNTIFS(#REF!,$C57,#REF!,$H$91)-COUNTIFS(#REF!,$C57,#REF!,$H$91),"") -> #REF! | R97: =IF(MONTH(TODAY())>=$D8,COUNTIFS(#REF!,$C57,#REF!,$H$91)-COUNTIFS(#REF!,$C57,#REF!,$H$91),"") -> #REF! | S97: =COUNTIFS(#REF!,$B57,#REF!,$C57,#REF!,$H$91) -> #REF! | T97: =COUNTIFS(#REF!,$B57,#REF!,$C57,#REF!,$H$91) -> #REF! | U97: =IF(MONTH(TODAY())>=$D8,COUNTIFS(#REF!,$C57,#REF!,$H$91)-COUNTIFS(#REF!,$C57,#REF!,$H$91),"") -> #REF! | W97: =IF(MONTH(TODAY())>=$D8,COUNTIFS(#REF!,$C57,#REF!,$H$91)-COUNTIFS(#REF!,$C57,#REF!,$H$91),"") -> #REF! | X97: 1 | Y97: =X97*428/$X$108 -> 53.5 | Z97: =X97*$Z$108/$X$108 -> 71814.064 | AA97: =COUNTIFS(#REF!,$B97,#REF!,$C97,#REF!,$H$91) -> #REF! | AB97: =SUMIFS(#REF!,#REF!,$B97,#REF!,$C97,#REF!,$H$91) -> #REF! | AC97: =SUMIFS(#REF!,#REF!,$B97,#REF!,$C97,#REF!,$H$91) -> #REF! | AD97: =COUNTIFS(#REF!,$B97,#REF!,$C97,#REF!,$H$91) -> #REF! | AE97: =SUMIFS(#REF!,#REF!,$B97,#REF!,$C97,#REF!,$H$91) -> #REF! | AF97: =SUMIFS(#REF!,#REF!,$B97,#REF!,$C97,#REF!,$H$91) -> #REF! | AH97: =IF(MONTH(TODAY())>=$D8,K97-H97,"") -> #REF! | AI97: =IF(MONTH(TODAY())>=$D8,L97-I97,"") -> #REF! | AJ97: =IF(MONTH(TODAY())>=$D8,M97-J97,"") -> #REF! | AL97: =IF(MONTH(TODAY())>=$D8,AD97-X97,"") -> #REF! | AM97: =IF(MONTH(TODAY())>=$D8,AE97-Y97,"") -> #REF! | AN97: =IF(MONTH(TODAY())>=$D8,AF97-Z97,"") -> #REF! | AP97: =IF(MONTH(TODAY())>=$D8,AD97-AA97,"") -> #REF! | AQ97: =IF(MONTH(TODAY())>=$D8,AE97-AB97,"") -> #REF! | AR97: =IF(MONTH(TODAY())>=$D8,AF97-AC97,"") -> #REF!
B98: >=4/1/24 | C98: <5/1/24 | D98: 4 | E98: =CONCATENATE(LEFT(B98,FIND(">=",B98) + 1),RIGHT(C98,LEN(C98) - (FIND("<",C98)))) -> >=5/1/24 | F98: April | G98: N/A | H98: 1 | I98: =$I$108/$H$108*H98 -> 49.661258 | J98: =$J$108/$H$108*H98 -> 66666.667 | K98: =COUNTIFS(#REF!,$B98,#REF!,$C98,#REF!,$H$91) -> #REF! | L98: =SUMIFS(#REF!,#REF!,$B98,#REF!,$C98,#REF!,$H$91) -> #REF! | M98: =SUMIFS(#REF!,#REF!,$B98,#REF!,$C98,#REF!,$H$91) -> #REF! | N98: =COUNTIFS(#REF!,$B9,#REF!,$C9,#REF!,$H$91) -> #REF! | O98: =COUNTIFS(#REF!,$B58,#REF!,$C58,#REF!,$H$91) -> #REF! | P98: =IF(MONTH(TODAY())>=$D9,COUNTIFS(#REF!,$C58,#REF!,$H$91)-COUNTIFS(#REF!,$C58,#REF!,$H$91),"") | R98: =IF(MONTH(TODAY())>=$D9,COUNTIFS(#REF!,$C58,#REF!,$H$91)-COUNTIFS(#REF!,$C58,#REF!,$H$91),"") | S98: =COUNTIFS(#REF!,$B58,#REF!,$C58,#REF!,$H$91) -> #REF! | T98: =COUNTIFS(#REF!,$B58,#REF!,$C58,#REF!,$H$91) -> #REF! | U98: =IF(MONTH(TODAY())>=$D9,COUNTIFS(#REF!,$C58,#REF!,$H$91)-COUNTIFS(#REF!,$C58,#REF!,$H$91),"") | W98: =IF(MONTH(TODAY())>=$D9,COUNTIFS(#REF!,$C58,#REF!,$H$91)-COUNTIFS(#REF!,$C58,#REF!,$H$91),"") | X98: 1 | Y98: =X98*428/$X$108 -> 53.5 | Z98: =X98*$Z$108/$X$108 -> 71814.064 | AA98: =COUNTIFS(#REF!,$B98,#REF!,$C98,#REF!,$H$91) -> #REF! | AB98: =SUMIFS(#REF!,#REF!,$B98,#REF!,$C98,#REF!,$H$91) -> #REF! | AC98: =SUMIFS(#REF!,#REF!,$B98,#REF!,$C98,#REF!,$H$91) -> #REF! | AD98: =COUNTIFS(#REF!,$B98,#REF!,$C98,#REF!,$H$91) -> #REF! | AE98: =SUMIFS(#REF!,#REF!,$B98,#REF!,$C98,#REF!,$H$91) -> #REF! | AF98: =SUMIFS(#REF!,#REF!,$B98,#REF!,$C98,#REF!,$H$91) -> #REF! | AH98: =IF(MONTH(TODAY())>=$D9,K98-H98,"") | AI98: =IF(MONTH(TODAY())>=$D9,L98-I98,"") | AJ98: =IF(MONTH(TODAY())>=$D9,M98-J98,"") | AL98: =IF(MONTH(TODAY())>=$D9,AD98-X98,"") | AM98: =IF(MONTH(TODAY())>=$D9,AE98-Y98,"") | AN98: =IF(MONTH(TODAY())>=$D9,AF98-Z98,"") | AP98: =IF(MONTH(TODAY())>=$D9,AD98-AA98,"") | AQ98: =IF(MONTH(TODAY())>=$D9,AE98-AB98,"") | AR98: =IF(MONTH(TODAY())>=$D9,AF98-AC98,"")
B99: >=5/1/24 | C99: <6/1/24 | D99: 5 | E99: =CONCATENATE(LEFT(B99,FIND(">=",B99) + 1),RIGHT(C99,LEN(C99) - (FIND("<",C99)))) -> >=6/1/24 | F99: May | G99: N/A | H99: 1 | I99: =$I$108/$H$108*H99 -> 49.661258 | J99: =$J$108/$H$108*H99 -> 66666.667 | K99: =COUNTIFS(#REF!,$B99,#REF!,$C99,#REF!,$H$91) -> #REF! | L99: =SUMIFS(#REF!,#REF!,$B99,#REF!,$C99,#REF!,$H$91) -> #REF! | M99: =SUMIFS(#REF!,#REF!,$B99,#REF!,$C99,#REF!,$H$91) -> #REF! | N99: =COUNTIFS(#REF!,$B10,#REF!,$C10,#REF!,$H$91) -> #REF! | O99: =COUNTIFS(#REF!,$B59,#REF!,$C59,#REF!,$H$91) -> #REF! | P99: =IF(MONTH(TODAY())>=$D10,COUNTIFS(#REF!,$C59,#REF!,$H$91)-COUNTIFS(#REF!,$C59,#REF!,$H$91),"") | R99: =IF(MONTH(TODAY())>=$D10,COUNTIFS(#REF!,$C59,#REF!,$H$91)-COUNTIFS(#REF!,$C59,#REF!,$H$91),"") | S99: =COUNTIFS(#REF!,$B59,#REF!,$C59,#REF!,$H$91) -> #REF! | T99: =COUNTIFS(#REF!,$B59,#REF!,$C59,#REF!,$H$91) -> #REF! | U99: =IF(MONTH(TODAY())>=$D10,COUNTIFS(#REF!,$C59,#REF!,$H$91)-COUNTIFS(#REF!,$C59,#REF!,$H$91),"") | W99: =IF(MONTH(TODAY())>=$D10,COUNTIFS(#REF!,$C59,#REF!,$H$91)-COUNTIFS(#REF!,$C59,#REF!,$H$91),"") | X99: 1 | Y99: =X99*428/$X$108 -> 53.5 | Z99: =X99*$Z$108/$X$108 -> 71814.064 | AA99: =COUNTIFS(#REF!,$B99,#REF!,$C99,#REF!,$H$91) -> #REF! | AB99: =SUMIFS(#REF!,#REF!,$B99,#REF!,$C99,#REF!,$H$91) -> #REF! | AC99: =SUMIFS(#REF!,#REF!,$B99,#REF!,$C99,#REF!,$H$91) -> #REF! | AD99: =COUNTIFS(#REF!,$B99,#REF!,$C99,#REF!,$H$91) -> #REF! | AE99: =SUMIFS(#REF!,#REF!,$B99,#REF!,$C99,#REF!,$H$91) -> #REF! | AF99: =SUMIFS(#REF!,#REF!,$B99,#REF!,$C99,#REF!,$H$91) -> #REF! | AH99: =IF(MONTH(TODAY())>=$D10,K99-H99,"") | AI99: =IF(MONTH(TODAY())>=$D10,L99-I99,"") | AJ99: =IF(MONTH(TODAY())>=$D10,M99-J99,"") | AL99: =IF(MONTH(TODAY())>=$D10,AD99-X99,"") | AM99: =IF(MONTH(TODAY())>=$D10,AE99-Y99,"") | AN99: =IF(MONTH(TODAY())>=$D10,AF99-Z99,"") | AP99: =IF(MONTH(TODAY())>=$D10,AD99-AA99,"") | AQ99: =IF(MONTH(TODAY())>=$D10,AE99-AB99,"") | AR99: =IF(MONTH(TODAY())>=$D10,AF99-AC99,"")
B100: >=6/1/24 | C100: <7/1/24 | D100: 6 | E100: =CONCATENATE(LEFT(B100,FIND(">=",B100) + 1),RIGHT(C100,LEN(C100) - (FIND("<",C100)))) -> >=7/1/24 | F100: June | G100: N/A | H100: 1 | I100: =$I$108/$H$108*H100 -> 49.661258 | J100: =$J$108/$H$108*H100 -> 66666.667 | K100: =COUNTIFS(#REF!,$B100,#REF!,$C100,#REF!,$H$91) -> #REF! | L100: =SUMIFS(#REF!,#REF!,$B100,#REF!,$C100,#REF!,$H$91) -> #REF! | M100: =SUMIFS(#REF!,#REF!,$B100,#REF!,$C100,#REF!,$H$91) -> #REF! | N100: =COUNTIFS(#REF!,$B11,#REF!,$C11,#REF!,$H$91) -> #REF! | O100: =COUNTIFS(#REF!,$B60,#REF!,$C60,#REF!,$H$91) -> #REF! | P100: =IF(MONTH(TODAY())>=$D11,COUNTIFS(#REF!,$C60,#REF!,$H$91)-COUNTIFS(#REF!,$C60,#REF!,$H$91),"") | R100: =IF(MONTH(TODAY())>=$D11,COUNTIFS(#REF!,$C60,#REF!,$H$91)-COUNTIFS(#REF!,$C60,#REF!,$H$91),"") | S100: =COUNTIFS(#REF!,$B60,#REF!,$C60,#REF!,$H$91) -> #REF! | T100: =COUNTIFS(#REF!,$B60,#REF!,$C60,#REF!,$H$91) -> #REF! | U100: =IF(MONTH(TODAY())>=$D11,COUNTIFS(#REF!,$C60,#REF!,$H$91)-COUNTIFS(#REF!,$C60,#REF!,$H$91),"") | W100: =IF(MONTH(TODAY())>=$D11,COUNTIFS(#REF!,$C60,#REF!,$H$91)-COUNTIFS(#REF!,$C60,#REF!,$H$91),"") | X100: 1 | Y100: =X100*428/$X$108 -> 53.5 | Z100: =X100*$Z$108/$X$108 -> 71814.064 | AA100: =COUNTIFS(#REF!,$B100,#REF!,$C100,#REF!,$H$91) -> #REF! | AB100: =SUMIFS(#REF!,#REF!,$B100,#REF!,$C100,#REF!,$H$91) -> #REF! | AC100: =SUMIFS(#REF!,#REF!,$B100,#REF!,$C100,#REF!,$H$91) -> #REF! | AD100: =COUNTIFS(#REF!,$B100,#REF!,$C100,#REF!,$H$91) -> #REF! | AE100: =SUMIFS(#REF!,#REF!,$B100,#REF!,$C100,#REF!,$H$91) -> #REF! | AF100: =SUMIFS(#REF!,#REF!,$B100,#REF!,$C100,#REF!,$H$91) -> #REF! | AH100: =IF(MONTH(TODAY())>=$D11,K100-H100,"") | AI100: =IF(MONTH(TODAY())>=$D11,L100-I100,"") | AJ100: =IF(MONTH(TODAY())>=$D11,M100-J100,"") | AL100: =IF(MONTH(TODAY())>=$D11,AD100-X100,"") | AM100: =IF(MONTH(TODAY())>=$D11,AE100-Y100,"") | AN100: =IF(MONTH(TODAY())>=$D11,AF100-Z100,"") | AP100: =IF(MONTH(TODAY())>=$D11,AD100-AA100,"") | AQ100: =IF(MONTH(TODAY())>=$D11,AE100-AB100,"") | AR100: =IF(MONTH(TODAY())>=$D11,AF100-AC100,"")
B101: >=7/1/24 | C101: <8/1/24 | D101: 7 | E101: =CONCATENATE(LEFT(B101,FIND(">=",B101) + 1),RIGHT(C101,LEN(C101) - (FIND("<",C101)))) -> >=8/1/24 | F101: July | G101: N/A | H101: 1 | I101: =$I$108/$H$108*H101 -> 49.661258 | J101: =$J$108/$H$108*H101 -> 66666.667 | K101: =COUNTIFS(#REF!,$B101,#REF!,$C101,#REF!,$H$91) -> #REF! | L101: =SUMIFS(#REF!,#REF!,$B101,#REF!,$C101,#REF!,$H$91) -> #REF! | M101: =SUMIFS(#REF!,#REF!,$B101,#REF!,$C101,#REF!,$H$91) -> #REF! | N101: =COUNTIFS(#REF!,$B12,#REF!,$C12,#REF!,$H$91) -> #REF! | O101: =COUNTIFS(#REF!,$B61,#REF!,$C61,#REF!,$H$91) -> #REF! | P101: =IF(MONTH(TODAY())>=$D12,COUNTIFS(#REF!,$C61,#REF!,$H$91)-COUNTIFS(#REF!,$C61,#REF!,$H$91),"") | R101: =IF(MONTH(TODAY())>=$D12,COUNTIFS(#REF!,$C61,#REF!,$H$91)-COUNTIFS(#REF!,$C61,#REF!,$H$91),"") | S101: =COUNTIFS(#REF!,$B61,#REF!,$C61,#REF!,$H$91) -> #REF! | T101: =COUNTIFS(#REF!,$B61,#REF!,$C61,#REF!,$H$91) -> #REF! | U101: =IF(MONTH(TODAY())>=$D12,COUNTIFS(#REF!,$C61,#REF!,$H$91)-COUNTIFS(#REF!,$C61,#REF!,$H$91),"") | W101: =IF(MONTH(TODAY())>=$D12,COUNTIFS(#REF!,$C61,#REF!,$H$91)-COUNTIFS(#REF!,$C61,#REF!,$H$91),"") | X101: 1 | Y101: =X101*428/$X$108 -> 53.5 | Z101: =X101*$Z$108/$X$108 -> 71814.064 | AA101: =COUNTIFS(#REF!,$B101,#REF!,$C101,#REF!,$H$91) -> #REF! | AB101: =SUMIFS(#REF!,#REF!,$B101,#REF!,$C101,#REF!,$H$91) -> #REF! | AC101: =SUMIFS(#REF!,#REF!,$B101,#REF!,$C101,#REF!,$H$91) -> #REF! | AD101: =COUNTIFS(#REF!,$B101,#REF!,$C101,#REF!,$H$91) -> #REF! | AE101: =SUMIFS(#REF!,#REF!,$B101,#REF!,$C101,#REF!,$H$91) -> #REF! | AF101: =SUMIFS(#REF!,#REF!,$B101,#REF!,$C101,#REF!,$H$91) -> #REF! | AH101: =IF(MONTH(TODAY())>=$D12,K101-H101,"") | AI101: =IF(MONTH(TODAY())>=$D12,L101-I101,"") | AJ101: =IF(MONTH(TODAY())>=$D12,M101-J101,"") | AL101: =IF(MONTH(TODAY())>=$D12,AD101-X101,"") | AM101: =IF(MONTH(TODAY())>=$D12,AE101-Y101,"") | AN101: =IF(MONTH(TODAY())>=$D12,AF101-Z101,"") | AP101: =IF(MONTH(TODAY())>=$D12,AD101-AA101,"") | AQ101: =IF(MONTH(TODAY())>=$D12,AE101-AB101,"") | AR101: =IF(MONTH(TODAY())>=$D12,AF101-AC101,"")
B102: >=8/1/24 | C102: <9/1/24 | D102: 8 | E102: =CONCATENATE(LEFT(B102,FIND(">=",B102) + 1),RIGHT(C102,LEN(C102) - (FIND("<",C102)))) -> >=9/1/24 | F102: August | G102: N/A | H102: 1 | I102: =$I$108/$H$108*H102 -> 49.661258 | J102: =$J$108/$H$108*H102 -> 66666.667 | K102: =COUNTIFS(#REF!,$B102,#REF!,$C102,#REF!,$H$91) -> #REF! | L102: =SUMIFS(#REF!,#REF!,$B102,#REF!,$C102,#REF!,$H$91) -> #REF! | M102: =SUMIFS(#REF!,#REF!,$B102,#REF!,$C102,#REF!,$H$91) -> #REF! | N102: =COUNTIFS(#REF!,$B13,#REF!,$C13,#REF!,$H$91) -> #REF! | O102: =COUNTIFS(#REF!,$B62,#REF!,$C62,#REF!,$H$91) -> #REF! | P102: =IF(MONTH(TODAY())>=$D13,COUNTIFS(#REF!,$C62,#REF!,$H$91)-COUNTIFS(#REF!,$C62,#REF!,$H$91),"") | R102: =IF(MONTH(TODAY())>=$D13,COUNTIFS(#REF!,$C62,#REF!,$H$91)-COUNTIFS(#REF!,$C62,#REF!,$H$91),"") | S102: =COUNTIFS(#REF!,$B62,#REF!,$C62,#REF!,$H$91) -> #REF! | T102: =COUNTIFS(#REF!,$B62,#REF!,$C62,#REF!,$H$91) -> #REF! | U102: =IF(MONTH(TODAY())>=$D13,COUNTIFS(#REF!,$C62,#REF!,$H$91)-COUNTIFS(#REF!,$C62,#REF!,$H$91),"") | W102: =IF(MONTH(TODAY())>=$D13,COUNTIFS(#REF!,$C62,#REF!,$H$91)-COUNTIFS(#REF!,$C62,#REF!,$H$91),"") | X102: 1 | Y102: =X102*428/$X$108 -> 53.5 | Z102: =X102*$Z$108/$X$108 -> 71814.064 | AA102: =COUNTIFS(#REF!,$B102,#REF!,$C102,#REF!,$H$91) -> #REF! | AB102: =SUMIFS(#REF!,#REF!,$B102,#REF!,$C102,#REF!,$H$91) -> #REF! | AC102: =SUMIFS(#REF!,#REF!,$B102,#REF!,$C102,#REF!,$H$91) -> #REF! | AD102: =COUNTIFS(#REF!,$B102,#REF!,$C102,#REF!,$H$91) -> #REF! | AE102: =SUMIFS(#REF!,#REF!,$B102,#REF!,$C102,#REF!,$H$91) -> #REF! | AF102: =SUMIFS(#REF!,#REF!,$B102,#REF!,$C102,#REF!,$H$91) -> #REF! | AH102: =IF(MONTH(TODAY())>=$D13,K102-H102,"") | AI102: =IF(MONTH(TODAY())>=$D13,L102-I102,"") | AJ102: =IF(MONTH(TODAY())>=$D13,M102-J102,"") | AL102: =IF(MONTH(TODAY())>=$D13,AD102-X102,"") | AM102: =IF(MONTH(TODAY())>=$D13,AE102-Y102,"") | AN102: =IF(MONTH(TODAY())>=$D13,AF102-Z102,"") | AP102: =IF(MONTH(TODAY())>=$D13,AD102-AA102,"") | AQ102: =IF(MONTH(TODAY())>=$D13,AE102-AB102,"") | AR102: =IF(MONTH(TODAY())>=$D13,AF102-AC102,"")
B103: >=9/1/24 | C103: <10/1/24 | D103: 9 | E103: =CONCATENATE(LEFT(B103,FIND(">=",B103) + 1),RIGHT(C103,LEN(C103) - (FIND("<",C103)))) -> >=10/1/24 | F103: September | G103: N/A | H103: 1 | I103: =$I$108/$H$108*H103 -> 49.661258 | J103: =$J$108/$H$108*H103 -> 66666.667 | K103: =COUNTIFS(#REF!,$B103,#REF!,$C103,#REF!,$H$91) -> #REF! | L103: =SUMIFS(#REF!,#REF!,$B103,#REF!,$C103,#REF!,$H$91) -> #REF! | M103: =SUMIFS(#REF!,#REF!,$B103,#REF!,$C103,#REF!,$H$91) -> #REF! | N103: =COUNTIFS(#REF!,$B14,#REF!,$C14,#REF!,$H$91) -> #REF! | O103: =COUNTIFS(#REF!,$B63,#REF!,$C63,#REF!,$H$91) -> #REF! | P103: =IF(MONTH(TODAY())>=$D14,COUNTIFS(#REF!,$C63,#REF!,$H$91)-COUNTIFS(#REF!,$C63,#REF!,$H$91),"") | R103: =IF(MONTH(TODAY())>=$D14,COUNTIFS(#REF!,$C63,#REF!,$H$91)-COUNTIFS(#REF!,$C63,#REF!,$H$91),"") | S103: =COUNTIFS(#REF!,$B63,#REF!,$C63,#REF!,$H$91) -> #REF! | T103: =COUNTIFS(#REF!,$B63,#REF!,$C63,#REF!,$H$91) -> #REF! | U103: =IF(MONTH(TODAY())>=$D14,COUNTIFS(#REF!,$C63,#REF!,$H$91)-COUNTIFS(#REF!,$C63,#REF!,$H$91),"") | W103: =IF(MONTH(TODAY())>=$D14,COUNTIFS(#REF!,$C63,#REF!,$H$91)-COUNTIFS(#REF!,$C63,#REF!,$H$91),"") | X103: 1 | Y103: =X103*428/$X$108 -> 53.5 | Z103: =X103*$Z$108/$X$108 -> 71814.064 | AA103: =COUNTIFS(#REF!,$B103,#REF!,$C103,#REF!,$H$91) -> #REF! | AB103: =SUMIFS(#REF!,#REF!,$B103,#REF!,$C103,#REF!,$H$91) -> #REF! | AC103: =SUMIFS(#REF!,#REF!,$B103,#REF!,$C103,#REF!,$H$91) -> #REF! | AD103: =COUNTIFS(#REF!,$B103,#REF!,$C103,#REF!,$H$91) -> #REF! | AE103: =SUMIFS(#REF!,#REF!,$B103,#REF!,$C103,#REF!,$H$91) -> #REF! | AF103: =SUMIFS(#REF!,#REF!,$B103,#REF!,$C103,#REF!,$H$91) -> #REF! | AH103: =IF(MONTH(TODAY())>=$D14,K103-H103,"") | AI103: =IF(MONTH(TODAY())>=$D14,L103-I103,"") | AJ103: =IF(MONTH(TODAY())>=$D14,M103-J103,"") | AL103: =IF(MONTH(TODAY())>=$D14,AD103-X103,"") | AM103: =IF(MONTH(TODAY())>=$D14,AE103-Y103,"") | AN103: =IF(MONTH(TODAY())>=$D14,AF103-Z103,"") | AP103: =IF(MONTH(TODAY())>=$D14,AD103-AA103,"") | AQ103: =IF(MONTH(TODAY())>=$D14,AE103-AB103,"") | AR103: =IF(MONTH(TODAY())>=$D14,AF103-AC103,"")
B104: >=10/1/24 | C104: <11/1/24 | D104: 10 | E104: =CONCATENATE(LEFT(B104,FIND(">=",B104) + 1),RIGHT(C104,LEN(C104) - (FIND("<",C104)))) -> >=11/1/24 | F104: October | G104: N/A | H104: 0 | I104: =H104*10 -> 0 | J104: =$J$108/$H$108*H104 -> 0 | K104: =COUNTIFS(#REF!,$B104,#REF!,$C104,#REF!,$H$91) -> #REF! | L104: =SUMIFS(#REF!,#REF!,$B104,#REF!,$C104,#REF!,$H$91) -> #REF! | M104: =SUMIFS(#REF!,#REF!,$B104,#REF!,$C104,#REF!,$H$91) -> #REF! | N104: =COUNTIFS(#REF!,$B15,#REF!,$C15,#REF!,$H$91) -> #REF! | O104: =COUNTIFS(#REF!,$B64,#REF!,$C64,#REF!,$H$91) -> #REF! | P104: =IF(MONTH(TODAY())>=$D15,COUNTIFS(#REF!,$C64,#REF!,$H$91)-COUNTIFS(#REF!,$C64,#REF!,$H$91),"") | R104: =IF(MONTH(TODAY())>=$D15,COUNTIFS(#REF!,$C64,#REF!,$H$91)-COUNTIFS(#REF!,$C64,#REF!,$H$91),"") | S104: =COUNTIFS(#REF!,$B64,#REF!,$C64,#REF!,$H$91) -> #REF! | T104: =COUNTIFS(#REF!,$B64,#REF!,$C64,#REF!,$H$91) -> #REF! | U104: =IF(MONTH(TODAY())>=$D15,COUNTIFS(#REF!,$C64,#REF!,$H$91)-COUNTIFS(#REF!,$C64,#REF!,$H$91),"") | W104: =IF(MONTH(TODAY())>=$D15,COUNTIFS(#REF!,$C64,#REF!,$H$91)-COUNTIFS(#REF!,$C64,#REF!,$H$91),"") | X104: 1 | Y104: =X104*428/$X$108 -> 53.5 | Z104: =X104*$Z$108/$X$108 -> 71814.064 | AA104: =COUNTIFS(#REF!,$B104,#REF!,$C104,#REF!,$H$91) -> #REF! | AB104: =SUMIFS(#REF!,#REF!,$B104,#REF!,$C104,#REF!,$H$91) -> #REF! | AC104: =SUMIFS(#REF!,#REF!,$B104,#REF!,$C104,#REF!,$H$91) -> #REF! | AD104: =COUNTIFS(#REF!,$B104,#REF!,$C104,#REF!,$H$91) -> #REF! | AE104: =SUMIFS(#REF!,#REF!,$B104,#REF!,$C104,#REF!,$H$91) -> #REF! | AF104: =SUMIFS(#REF!,#REF!,$B104,#REF!,$C104,#REF!,$H$91) -> #REF! | AH104: =IF(MONTH(TODAY())>=$D15,K104-H104,"") | AI104: =IF(MONTH(TODAY())>=$D15,L104-I104,"") | AJ104: =IF(MONTH(TODAY())>=$D15,M104-J104,"") | AL104: =IF(MONTH(TODAY())>=$D15,AD104-X104,"") | AM104: =IF(MONTH(TODAY())>=$D15,AE104-Y104,"") | AN104: =IF(MONTH(TODAY())>=$D15,AF104-Z104,"") | AP104: =IF(MONTH(TODAY())>=$D15,AD104-AA104,"") | AQ104: =IF(MONTH(TODAY())>=$D15,AE104-AB104,"") | AR104: =IF(MONTH(TODAY())>=$D15,AF104-AC104,"")
B105: >=11/1/24 | C105: <12/1/24 | D105: 11 | E105: =CONCATENATE(LEFT(B105,FIND(">=",B105) + 1),RIGHT(C105,LEN(C105) - (FIND("<",C105)))) -> >=12/1/24 | F105: November | G105: N/A | H105: 0 | I105: =H105*10 -> 0 | J105: =$J$108/$H$108*H105 -> 0 | K105: =COUNTIFS(#REF!,$B105,#REF!,$C105,#REF!,$H$91) -> #REF! | L105: =SUMIFS(#REF!,#REF!,$B105,#REF!,$C105,#REF!,$H$91) -> #REF! | M105: =SUMIFS(#REF!,#REF!,$B105,#REF!,$C105,#REF!,$H$91) -> #REF! | N105: =COUNTIFS(#REF!,$B16,#REF!,$C16,#REF!,$H$91) -> #REF! | O105: =COUNTIFS(#REF!,$B65,#REF!,$C65,#REF!,$H$91) -> #REF! | P105: =IF(MONTH(TODAY())>=$D16,COUNTIFS(#REF!,$C65,#REF!,$H$91)-COUNTIFS(#REF!,$C65,#REF!,$H$91),"") | R105: =IF(MONTH(TODAY())>=$D16,COUNTIFS(#REF!,$C65,#REF!,$H$91)-COUNTIFS(#REF!,$C65,#REF!,$H$91),"") | S105: =COUNTIFS(#REF!,$B65,#REF!,$C65,#REF!,$H$91) -> #REF! | T105: =COUNTIFS(#REF!,$B65,#REF!,$C65,#REF!,$H$91) -> #REF! | U105: =IF(MONTH(TODAY())>=$D16,COUNTIFS(#REF!,$C65,#REF!,$H$91)-COUNTIFS(#REF!,$C65,#REF!,$H$91),"") | W105: =IF(MONTH(TODAY())>=$D16,COUNTIFS(#REF!,$C65,#REF!,$H$91)-COUNTIFS(#REF!,$C65,#REF!,$H$91),"") | X105: 0 | Y105: =X105*428/$X$108 -> 0 | Z105: =$Z$68/$X$68*X105 -> 0 | AA105: =COUNTIFS(#REF!,$B105,#REF!,$C105,#REF!,$H$91) -> #REF! | AB105: =SUMIFS(#REF!,#REF!,$B105,#REF!,$C105,#REF!,$H$91) -> #REF! | AC105: =SUMIFS(#REF!,#REF!,$B105,#REF!,$C105,#REF!,$H$91) -> #REF! | AD105: =COUNTIFS(#REF!,$B105,#REF!,$C105,#REF!,$H$91) -> #REF! | AE105: =SUMIFS(#REF!,#REF!,$B105,#REF!,$C105,#REF!,$H$91) -> #REF! | AF105: =SUMIFS(#REF!,#REF!,$B105,#REF!,$C105,#REF!,$H$91) -> #REF! | AH105: =IF(MONTH(TODAY())>=$D16,K105-H105,"") | AI105: =IF(MONTH(TODAY())>=$D16,L105-I105,"") | AJ105: =IF(MONTH(TODAY())>=$D16,M105-J105,"") | AL105: =IF(MONTH(TODAY())>=$D16,AD105-X105,"") | AM105: =IF(MONTH(TODAY())>=$D16,AE105-Y105,"") | AN105: =IF(MONTH(TODAY())>=$D16,AF105-Z105,"") | AP105: =IF(MONTH(TODAY())>=$D16,AD105-AA105,"") | AQ105: =IF(MONTH(TODAY())>=$D16,AE105-AB105,"") | AR105: =IF(MONTH(TODAY())>=$D16,AF105-AC105,"")
B106: >=12/1/24 | C106: <1/1/25 | D106: 12 | E106: =CONCATENATE(LEFT(B106,FIND(">=",B106) + 1),RIGHT(C106,LEN(C106) - (FIND("<",C106)))) -> >=1/1/25 | F106: December | G106: N/A | H106: 0 | I106: =H106*10 -> 0 | J106: =$J$108/$H$108*H106 -> 0 | K106: =COUNTIFS(#REF!,$B106,#REF!,$C106,#REF!,$H$91) -> #REF! | L106: =SUMIFS(#REF!,#REF!,$B106,#REF!,$C106,#REF!,$H$91) -> #REF! | M106: =SUMIFS(#REF!,#REF!,$B106,#REF!,$C106,#REF!,$H$91) -> #REF! | N106: =COUNTIFS(#REF!,$B17,#REF!,$C17,#REF!,$H$91) -> #REF! | O106: =COUNTIFS(#REF!,$B66,#REF!,$C66,#REF!,$H$91) -> #REF! | P106: =IF(MONTH(TODAY())>=$D17,COUNTIFS(#REF!,$C66,#REF!,$H$91)-COUNTIFS(#REF!,$C66,#REF!,$H$91),"") | R106: =IF(MONTH(TODAY())>=$D17,COUNTIFS(#REF!,$C66,#REF!,$H$91)-COUNTIFS(#REF!,$C66,#REF!,$H$91),"") | S106: =COUNTIFS(#REF!,$B66,#REF!,$C66,#REF!,$H$91) -> #REF! | T106: =COUNTIFS(#REF!,$B66,#REF!,$C66,#REF!,$H$91) -> #REF! | U106: =IF(MONTH(TODAY())>=$D17,COUNTIFS(#REF!,$C66,#REF!,$H$91)-COUNTIFS(#REF!,$C66,#REF!,$H$91),"") | W106: =IF(MONTH(TODAY())>=$D17,COUNTIFS(#REF!,$C66,#REF!,$H$91)-COUNTIFS(#REF!,$C66,#REF!,$H$91),"") | X106: 0 | Y106: =X106*428/$X$108 -> 0 | Z106: =$Z$68/$X$68*X106 -> 0 | AA106: =COUNTIFS(#REF!,$B106,#REF!,$C106,#REF!,$H$91) -> #REF! | AB106: =SUMIFS(#REF!,#REF!,$B106,#REF!,$C106,#REF!,$H$91) -> #REF! | AC106: =SUMIFS(#REF!,#REF!,$B106,#REF!,$C106,#REF!,$H$91) -> #REF! | AD106: =COUNTIFS(#REF!,$B106,#REF!,$C106,#REF!,$H$91) -> #REF! | AE106: =SUMIFS(#REF!,#REF!,$B106,#REF!,$C106,#REF!,$H$91) -> #REF! | AF106: =SUMIFS(#REF!,#REF!,$B106,#REF!,$C106,#REF!,$H$91) -> #REF! | AH106: =IF(MONTH(TODAY())>=$D17,K106-H106,"") | AI106: =IF(MONTH(TODAY())>=$D17,L106-I106,"") | AJ106: =IF(MONTH(TODAY())>=$D17,M106-J106,"") | AL106: =IF(MONTH(TODAY())>=$D17,AD106-X106,"") | AM106: =IF(MONTH(TODAY())>=$D17,AE106-Y106,"") | AN106: =IF(MONTH(TODAY())>=$D17,AF106-Z106,"") | AP106: =IF(MONTH(TODAY())>=$D17,AD106-AA106,"") | AQ106: =IF(MONTH(TODAY())>=$D17,AE106-AB106,"") | AR106: =IF(MONTH(TODAY())>=$D17,AF106-AC106,"")
B107: >=1/1/25 | C107: <1/1/26 | E107: =CONCATENATE(LEFT(B107,FIND(">=",B107) + 1),RIGHT(C107,LEN(C107) - (FIND("<",C107)))) -> >=1/1/26 | F107: 2025 | G107: N/A | K107: =COUNTIFS(#REF!,$B107,#REF!,$C107,#REF!,$H$91) -> #REF! | L107: =SUMIFS(#REF!,#REF!,$B107,#REF!,$C107,#REF!,$H$91) -> #REF! | M107: =SUMIFS(#REF!,#REF!,$B107,#REF!,$C107,#REF!,$H$91) -> #REF! | N107: =COUNTIFS(#REF!,$B18,#REF!,$C18,#REF!,$H$91) -> #REF! | O107: =COUNTIFS(#REF!,$B67,#REF!,$C67,#REF!,$H$91) -> #REF! | S107: =COUNTIFS(#REF!,$B67,#REF!,$C67,#REF!,$H$91) -> #REF! | T107: =COUNTIFS(#REF!,$B67,#REF!,$C67,#REF!,$H$91) -> #REF! | AA107: =COUNTIFS(#REF!,$B107,#REF!,$C107,#REF!,$H$91) -> #REF! | AB107: =SUMIFS(#REF!,#REF!,$B107,#REF!,$C107,#REF!,$H$91) -> #REF! | AC107: =SUMIFS(#REF!,#REF!,$B107,#REF!,$C107,#REF!,$H$91) -> #REF! | AD107: =COUNTIFS(#REF!,$B107,#REF!,$C107,#REF!,$H$91) -> #REF! | AE107: =SUMIFS(#REF!,#REF!,$B107,#REF!,$C107,#REF!,$H$91) -> #REF! | AF107: =SUMIFS(#REF!,#REF!,$B107,#REF!,$C107,#REF!,$H$91) -> #REF!
F108: Total | G108: N/A | H108: =SUM(H95:H106) -> 9 | I108: =I19-I68 -> 446.95133 | J108: =J19-J68 -> 600000 | K108: =SUM(K94:K107) -> #REF! | L108: =SUM(L94:L107) -> #REF! | M108: =SUM(M94:M107) -> #REF! | N108: =SUM(N94:N107) -> #REF! | O108: =SUM(O94:O107) -> #REF! | P108: =INDEX(P94:P107,MONTH(TODAY())+1) -> #REF! | Q108: =INDEX(Q94:Q107,MONTH(TODAY())+1) | R108: =INDEX(R94:R107,MONTH(TODAY())+1) -> #REF! | S108: =SUM(S94:S107) -> #REF! | T108: =SUM(T94:T107) -> #REF! | U108: =INDEX(U94:U107,MONTH(TODAY())+1) -> #REF! | V108: =INDEX(V94:V107,MONTH(TODAY())+1) | W108: =INDEX(W94:W107,MONTH(TODAY())+1) -> #REF! | X108: =SUM(X94:X107) -> 8 | Y108: =SUM(Y94:Y107) -> 428 | Z108: =Z19-Z68 -> 574512.51 | AA108: =SUM(AA94:AA107) -> #REF! | AB108: =SUM(AB94:AB107) -> #REF! | AC108: =SUM(AC94:AC107) -> #REF! | AD108: =SUM(AD94:AD107) -> #REF! | AE108: =SUM(AE94:AE107) -> #REF! | AF108: =SUM(AF94:AF107) -> #REF! | AH108: =SUM(AH95:AH106) -> #REF! | AI108: =SUM(AI95:AI107) -> #REF! | AJ108: =SUM(AJ95:AJ107) -> #REF! | AL108: =SUM(AL95:AL107) -> #REF! | AM108: =SUM(AM95:AM107) -> #REF! | AN108: =SUM(AN95:AN107) -> #REF! | AP108: =SUM(AP94:AP107) -> #REF! | AQ108: =SUM(AQ94:AQ107) -> #REF! | AR108: =SUM(AR94:AR107) -> #REF!
F109: Total* | G109: N/A | K109: =SUM(K95:K106) -> #REF! | L109: =SUM(L95:L106) -> #REF! | M109: =SUM(M95:M106) -> #REF! | N109: =SUM(N95:N106) -> #REF! | O109: =SUM(O95:O106) -> #REF! | S109: =SUM(S95:S106) -> #REF! | T109: =SUM(T95:T106) -> #REF! | X109: =SUM(X95:X106) -> 8 | Y109: =SUM(Y95:Y106) -> 428 | Z109: =Z108 -> 574512.51 | AA109: =SUM(AA95:AA106) -> #REF! | AB109: =SUM(AB95:AB106) -> #REF! | AC109: =SUM(AC95:AC106) -> #REF! | AD109: =SUM(AD95:AD106) -> #REF! | AE109: =SUM(AE95:AE106) -> #REF! | AF109: =SUM(AF95:AF106) -> #REF! | AH109: =SUM(AH95:AH106) -> #REF! | AI109: =SUM(AI95:AI107) -> #REF! | AJ109: =SUM(AJ95:AJ107) -> #REF! | AL109: =SUM(AL95:AL107) -> #REF! | AM109: =SUM(AM95:AM107) -> #REF! | AN109: =SUM(AN95:AN107) -> #REF! | AP109: =SUM(AP95:AP106) -> #REF! | AQ109: =SUM(AQ95:AQ106) -> #REF! | AR109: =SUM(AR95:AR106) -> #REF!
AH112: Bookings | AL112: Installs
F113: Month | AF113: # of Months Left | AH113: Average monthly commercial bookings needed to be in line with Budgeted Goals | AL113: Average monthly residential installs needed to be in line with Budgeted Goals
F114: January | AF114: 12 | AH114: =IF(MONTH(TODAY())=$D6,$AH$126/$AF114,"") | AI114: =IF(MONTH(TODAY())=$D6,$AI$126/$AF114,"") | AJ114: =IF(MONTH(TODAY())=$D6,$AJ$126/AF114,"") | AL114: =IF(MONTH(TODAY())=$D6,$AL$86/$AF114,"") | AM114: =IF(MONTH(TODAY())=$D6,$AM$86/$AF114,"") | AN114: =IF(MONTH(TODAY())=$D6,$AN$86/AF114,"")
F115: February | AF115: 11 | AH115: =IF(MONTH(TODAY())=$D7,$AH$126/$AF115,"") | AI115: =IF(MONTH(TODAY())=$D7,$AI$126/$AF115,"") | AJ115: =IF(MONTH(TODAY())=$D7,$AJ$126/AF115,"") | AL115: =IF(MONTH(TODAY())=$D7,$AL$86/$AF115,"") | AM115: =IF(MONTH(TODAY())=$D7,$AM$86/$AF115,"") | AN115: =IF(MONTH(TODAY())=$D7,$AN$86/AF115,"")
F116: March | AF116: 10 | AH116: =IF(MONTH(TODAY())=$D8,$AH$126/$AF116,"") -> #REF! | AI116: =IF(MONTH(TODAY())=$D8,$AI$126/$AF116,"") -> #REF! | AJ116: =IF(MONTH(TODAY())=$D8,$AJ$126/AF116,"") -> #REF! | AL116: =IF(MONTH(TODAY())=$D8,$AL$126/$AF116,"") -> #REF! | AM116: =IF(MONTH(TODAY())=$D8,$AM$126/$AF116,"") -> #REF! | AN116: =IF(MONTH(TODAY())=$D8,$AN$126/AF116,"") -> #REF!
...

Sheet DTS Dashboard
B2: DTS Dashboard
B3: Item | C3: Month to Date Actual vs End of Month Target | G3: Year To Date
C4: Full MonthTarget | D4: Actual | E4: Target to Actual QTY | F4: Target to Actual % | G4: Target for the end of the month | H4: Actual | I4: Target to Actual QTY | J4: Target to Actual %
B5: QTY Installed | C5: =VLOOKUP(MONTH(TODAY()),'CORE METRICS +'!D5:'CORE METRICS +'!AR17,21) -> 7 | D5: =VLOOKUP(MONTH(TODAY()),'CORE METRICS +'!D5:'CORE METRICS +'!AR17,27) -> #REF! | E5: =D5-C5 -> #REF! | F5: =E5/C5 -> #REF! | G5: =H5-I5 -> #REF! | H5: {=SUM(INDEX('CORE METRICS +'!AD6:'CORE METRICS +'!AD17,0))} -> #REF! | I5: ='CORE METRICS +'!AL19 -> #REF! | J5: =I5/G5 -> #REF!
B6: kW Install | C6: =VLOOKUP(MONTH(TODAY()),'CORE METRICS +'!D5:'CORE METRICS +'!AR17,22) -> 113.5 | D6: =VLOOKUP(MONTH(TODAY()),'CORE METRICS +'!D5:'CORE METRICS +'!AR17,28) -> #REF! | E6: =D6-C6 -> #REF! | F6: =E6/C6 -> #REF! | G6: =H6-I6 -> #REF! | H6: {=SUM(INDEX('CORE METRICS +'!AE6:'CORE METRICS +'!AE17,0))} -> #REF! | I6: ='CORE METRICS +'!AM19 -> #REF! | J6: =I6/G6 -> #REF!
B7: Revenue $ Installed | C7: =VLOOKUP(MONTH(TODAY()),'CORE METRICS +'!D5:'CORE METRICS +'!AR17,23) -> 238422.69 | D7: =VLOOKUP(MONTH(TODAY()),'CORE METRICS +'!D5:'CORE METRICS +'!AR17,29) -> #REF! | E7: =D7-C7 -> #REF! | F7: =E7/C7 -> #REF! | G7: =H7-I7 -> #REF! | H7: {=SUM(INDEX('CORE METRICS +'!AD6:'CORE METRICS +'!AF17,0))} -> #REF! | I7: ='CORE METRICS +'!AN19 -> #REF! | J7: =I7/G7 -> #REF!
B8: Permits Submitted | D8: =VLOOKUP(MONTH(TODAY()),'CORE METRICS +'!D5:'CORE METRICS +'!AR17,11) -> #REF! | H8: {=SUM(INDEX('CORE METRICS +'!N6:'CORE METRICS +'!N17,0))} -> #REF!
B9: Permits Approved | D9: =VLOOKUP(MONTH(TODAY()),'CORE METRICS +'!D5:'CORE METRICS +'!AR17,12) -> #REF! | H9: {=SUM(INDEX('CORE METRICS +'!O6:'CORE METRICS +'!O17,0))} -> #REF!
B10: Jobs with Unsubmitted Permits | H10: ='CORE METRICS +'!P19 -> #REF!
B11: Outstanding Submitted Permits | H11: ='CORE METRICS +'!Q19
B12: Total Approved Permits for Uninstalled Projects | H12: ='CORE METRICS +'!R19 -> #REF!
B13: Utility Applications Submitted | D13: =VLOOKUP(MONTH(TODAY()),'CORE METRICS +'!D5:'CORE METRICS +'!AR17,16) -> #REF! | H13: {=SUM(INDEX('CORE METRICS +'!S6:'CORE METRICS +'!S17,0))} -> #REF!
B14: Utility Applications Approved | D14: =VLOOKUP(MONTH(TODAY()),'CORE METRICS +'!D5:'CORE METRICS +'!AR17,17) -> #REF! | H14: {=SUM(INDEX('CORE METRICS +'!T6:'CORE METRICS +'!T17,0))} -> #REF!
B15: Jobs with Unsubmitted Utility Applications | H15: ='CORE METRICS +'!U19 -> #REF!
B16: Outstanding Submitted Utility Applications | H16: ='CORE METRICS +'!V19
B17: Total Approved Utility Applications for Uninstalled Projects | H17: ='CORE METRICS +'!W19 -> #REF!
B18: QTY of Projects that have Full Approval to Move Forward Now | H18: =COUNTIFS(#REF!,"<>",#REF!,"<>",#REF!,"") -> #REF!
B19: QTY of Projects that do not have Full Approval to move forward now | H19: =COUNTIFS(#REF!,"<>",#REF!,"") - COUNTIFS(#REF!,"<>",#REF!,"<>",#REF!,"") -> #REF!
B20: QTY of Installed projects without PTO | H20: =COUNTIFS(#REF!,"<>",#REF!,"") -> #REF!
B21: Next Project on Calendar without full approval | H21: Crabb
B22: Days until that project | H22: =DATEDIF(TODAY(),"8/12/24","D") -> #NUM!
B23: Next Project on Calendar that we haven't submitted everything for | H23: Binsfeld
B24: Days until that project | H24: =DATEDIF(TODAY(),"09/9/24","D") -> #NUM!
B25: Permitted Project Lead Time (weeks) | G25: 8 | H25: =H22/7 -> #NUM!
B26: QTY of New Warranty Calls | D26: =IFERROR(__xludf.DUMMYFUNCTION("IMPORTRANGE(""https://docs.google.com/spreadsheets/d/1ej_V9sTbyoD-JmhHzgROxzKOy8bjZQHzmirCykaz6MQ/edit#gid=1962875292"",""Data!K5"")"),"#REF!") -> #REF! | H26: =IFERROR(__xludf.DUMMYFUNCTION("IMPORTRANGE(""https://docs.google.com/spreadsheets/d/1ej_V9sTbyoD-JmhHzgROxzKOy8bjZQHzmirCykaz6MQ/edit#gid=1962875292"",""Data!L5:L6"")"),"#REF!") -> #REF!
B27: QTY of Warranty Items Open
